Workbook

Sheet Runbook
B1: FBC Workbook — Adding a New Cup
B2: Runbook for adding a completed FBC (e.g., FBC 13). Most of the workbook updates itself — the manual steps are listed below.
B4: THE 30-SECOND VERSION
B5: Fastest path: in the scoring app press Admin → Export CSV once every match is reported, then hand that file to Claude with the prompt in the README (“Importing a cup with Claude”). Claude runs tools/import_cup.py, which appends the Archives rows, fills the Cups column and checks Data Health. Manual path: paste the new cup’s match results into the Archives tab. The live tabs — Leaderboard, Points, Singles & Doubles records, Rookies, and most of RecordBook — recalculate automatically. Then handle the manual items: add a row for any first-time player, and fill the per-cup input tabs (Cups, Handicaps, Ratings, Cup Info). Finally, ask Claude to recompute CAPA and the analytics tabs.
B7: STEP 1 — ENTER RESULTS IN ARCHIVES
B8: This is the only data entry that drives the automatic tabs.
B9: • Append the new cup’s matches to the bottom of the Archives tab (below the last row).
B10: • Fill the same columns as existing rows: Match #, FBC #, UniqueMatchID (FBC13-D1…, FBC13-S-Name-Name, FBC13-FT), Day, Date (a real Excel date), Geographic Location, Course, Format, Singles/Doubles (exactly Singles, Doubles or FTAS), Captain Size, Team (captain’s surname), Player 1, Player 2 (doubles), handicaps, Points at stake, W/L/T, Points earned, the numeric W / L / T flag columns (1 or 0), and the opponent columns.
B11: • Each head-to-head match = 2 rows (one per side). Whole-field (FTAS) events = one row per player.
B12: • Put the cup number (e.g., 13) in the FBC column, and use W, L, or T (uppercase) for the result.
B14: STEP 2 — ADD A ROW FOR ANY FIRST-TIME PLAYER
B15: A debuting player’s matches still count correctly for everyone else, but the live tabs won’t show the new player until you give them a row.
... B36: REFERENCE — AUTOMATIC vs MANUAL
B37: Tab | C37: On Archives update | D37: Your action
B38: Archives | C38: — | D38: Paste the new cup’s match rows here (Step 1).
B39: Leaderboard | C39: Automatic | D39: Add a row only for a first-time player.
B40: Points | C40: Automatic | D40: FBC 13–15 prebuilt. Add a row for new players; add columns after FBC 15.
B41: Singles_Doubles records | C41: Automatic | D41: Add a row for a new player or a new tandem.
B42: Rookies | C42: Automatic | D42: Add a row for a new player.
B43: RecordBook | C43: Mostly automatic | D43: Margin records (8&7, 5&4, streaks) are entered by hand.
B44: CAPA PPC | C44: Recompute | D44: Ask Claude — regression recalibration.
B45: Sandbagger · Chemistry · Clutch · Pythagorean Luck · Form Guide · MVP Hall of Fame · Nemesis & Patsy · Streak Tracker | C45: Recompute | D45: Ask Claude — computed analytics (same as CAPA).
B46: Cups | C46: Manual | D46: New 1 / 0 / X column each cup.
B47: Handicaps | C47: Manual | D47: New handicap-index column each cup.
B48: Ratings | C48: Manual | D48: New venue-score row each cup.
... B51: Bounties · 7yrFund · Lifetime Mulligans · Cyber Monday · NHI | C51: Manual | D51: Maintain as you always have.
B53: NOTES
B54: • Win % everywhere = (W + ½T) ÷ matches.
B55: • The result column accepts lowercase “t”, but enter “T” for clean data.
B56: • The web app (freddiebcup.streamlit.app) reads UniqueMatchID, Team, Date, Geographic Location, Course, Singles/Doubles and the numeric W / L / T flag columns — fill them all in. A blank UniqueMatchID silently drops the FTAS from the team totals. Only SingleEntity is legacy/unused. The app’s Data Health box (bottom of every page) lists anything it finds wrong after you upload.
B57: • "Live" tabs recompute from Archives automatically. "Computed" tabs — CAPA and the eight analytics tabs — are refreshed by Claude.
B59: Built June 2026 · current through FBC 12.

Sheet Archives
B1: Match # | C1: Match of Session | D1: FBC | E1: UniqueMatchID | F1: Day | G1: Date | H1: AM/PM | I1: Geographic Location | J1: Region | K1: Holes | L1: Front / Back / Full | M1: Course | N1: Tees | O1: Rating | P1: Slope | Q1: Yds | R1: Format | S1: Singles/Doubles | T1: Captain Size | U1: Team | V1: Player 1 | W1: Shirt | X1: Player 1 HCP | Y1: Player 2 | Z1: Player 2 HCP | AA1: Points at stake | AB1: W/L/T | AC1: Result | AD1: Singles Opponent | AE1: SingleEntity | AF1: Points earned | AG1: W | AH1: L | AI1: T | AJ1: W% | AK1: Opponent1 | AL1: Opponent1 Win% | AM1: Opponent2 | AN1: Opponent2 Win%
B2: 1 | C2: 1 | D2: 1 | E2: FBC1-D1 | F2: Saturday | G2: 41447 | H2: AM | I2: Saratoga, NY | J2: Northeast | K2: 9 | L2: Front | M2: Saratoga National | N2: White | O2: 71.3 | P2: 130 | Q2: 6225 | R2: Best Ball | S2: Doubles | T2: Under 6' | U2: Jackson | V2: Grise | W2: White | X2: 15 | Y2: Hickerson | Z2: 20 | AA2: 1 | AB2: W | AC2: 3 & 2 | AE2: =$V2&$Y2 -> GriseHickerson | AF2: 1 | AG2: 1 | AH2: 0 | AI2: 0 | AJ2: 1 | AK2: Hilts | AL2: 0.47321429 | AM2: Lynch | AN2: 0.5546875
B3: 1 | C3: 1 | D3: 1 | E3: FBC1-D1 | F3: Saturday | G3: 41447 | H3: AM | I3: Saratoga, NY | J3: Northeast | K3: 9 | L3: Front | M3: Saratoga National | N3: White | O3: 71.3 | P3: 130 | Q3: 6225 | R3: Best Ball | S3: Doubles | T3: Over 6' | U3: Hilts | V3: Hilts | W3: Red | X3: 18 | Y3: Lynch | Z3: 20 | AA3: 1 | AB3: L | AC3: 3 & 2 | AE3: =$V3&$Y3 -> HiltsLynch | AF3: 0 | AG3: 0 | AH3: 1 | AI3: 0 | AJ3: 0 | AK3: Grise | AL3: 0.546875 | AM3: Hickerson | AN3: 0.35714286
B4: 2 | C4: 2 | D4: 1 | E4: FBC1-D2 | F4: Saturday | G4: 41447 | H4: AM | I4: Saratoga, NY | J4: Northeast | K4: 9 | L4: Front | M4: Saratoga National | N4: White | O4: 71.3 | P4: 130 | Q4: 6225 | R4: Best Ball | S4: Doubles | T4: Under 6' | U4: Jackson | V4: Ferrin | W4: White | X4: 28 | Y4: Jackson | Z4: 15 | AA4: 1 | AB4: W | AC4: 2 & 1 | AE4: =$V4&$Y4 -> FerrinJackson | AF4: 1 | AG4: 1 | AH4: 0 | AI4: 0 | AJ4: 1 | AK4: Macklin | AL4: 0.3 | AM4: Poirier | AN4: 0.48611111
B5: 2 | C5: 2 | D5: 1 | E5: FBC1-D2 | F5: Saturday | G5: 41447 | H5: AM | I5: Saratoga, NY | J5: Northeast | K5: 9 | L5: Front | M5: Saratoga National | N5: White | O5: 71.3 | P5: 130 | Q5: 6225 | R5: Best Ball | S5: Doubles | T5: Over 6' | U5: Hilts | V5: Macklin | W5: Red | X5: 15 | Y5: Poirier | Z5: 10 | AA5: 1 | AB5: L | AC5: 2 & 1 | AE5: =$V5&$Y5 -> MacklinPoirier | AF5: 0 | AG5: 0 | AH5: 1 | AI5: 0 | AJ5: 0 | AK5: Ferrin | AL5: 0.5952381 | AM5: Jackson | AN5: 0.6171875
B6: 3 | C6: 3 | D6: 1 | E6: FBC1-D3 | F6: Saturday | G6: 41447 | H6: AM | I6: Saratoga, NY | J6: Northeast | K6: 9 | L6: Front | M6: Saratoga National | N6: White | O6: 71.3 | P6: 130 | Q6: 6225 | R6: Best Ball | S6: Doubles | T6: Under 6' | U6: Jackson | V6: Flanders | W6: White | X6: 15 | Y6: Mangold | Z6: 15 | AA6: 1 | AB6: L | AC6: 5 & 4 | AE6: =$V6&$Y6 -> FlandersMangold | AF6: 0 | AG6: 0 | AH6: 1 | AI6: 0 | AJ6: 0 | AK6: Connolly | AL6: 0.59375 | AM6: Shively
B7: 3 | C7: 3 | D7: 1 | E7: FBC1-D3 | F7: Saturday | G7: 41447 | H7: AM | I7: Saratoga, NY | J7: Northeast | K7: 9 | L7: Front | M7: Saratoga National | N7: White | O7: 71.3 | P7: 130 | Q7: 6225 | R7: Best Ball | S7: Doubles | T7: Over 6' | U7: Hilts | V7: Connolly | W7: Red | X7: 15 | Y7: Shively | Z7: 30 | AA7: 1 | AB7: W | AC7: 5 & 4 | AE7: =$V7&$Y7 -> ConnollyShively | AF7: 1 | AG7: 1 | AH7: 0 | AI7: 0 | AJ7: 1 | AK7: Flanders | AL7: 0.4296875 | AM7: Mangold | AN7: 0.38392857
B8: 4 | C8: 1 | D8: 1 | E8: FBC1-D4 | F8: Saturday | G8: 41447 | H8: AM | I8: Saratoga, NY | J8: Northeast | K8: 9 | L8: Back | M8: Saratoga National | N8: White | O8: 71.3 | P8: 130 | Q8: 6225 | R8: Scramble | S8: Doubles | T8: Under 6' | U8: Jackson | V8: Grise | W8: White | X8: 15 | Y8: Hickerson | Z8: 20 | AA8: 1 | AB8: T | AC8: Halved | AE8: =$V8&$Y8 -> GriseHickerson | AF8: 0.5 | AG8: 0 | AH8: 0 | AI8: 1 | AJ8: 0.5 | AK8: Hilts | AL8: 0.47321429 | AM8: Lynch | AN8: 0.5546875
B9: 4 | C9: 1 | D9: 1 | E9: FBC1-D4 | F9: Saturday | G9: 41447 | H9: AM | I9: Saratoga, NY | J9: Northeast | K9: 9 | L9: Back | M9: Saratoga National | N9: White | O9: 71.3 | P9: 130 | Q9: 6225 | R9: Scramble | S9: Doubles | T9: Over 6' | U9: Hilts | V9: Hilts | W9: Red | X9: 18 | Y9: Lynch | Z9: 20 | AA9: 1 | AB9: T | AC9: Halved | AE9: =$V9&$Y9 -> HiltsLynch | AF9: 0.5 | AG9: 0 | AH9: 0 | AI9: 1 | AJ9: 0.5 | AK9: Grise | AL9: 0.546875 | AM9: Hickerson | AN9: 0.35714286
B10: 5 | C10: 2 | D10: 1 | E10: FBC1-D5 | F10: Saturday | G10: 41447 | H10: AM | I10: Saratoga, NY | J10: Northeast | K10: 9 | L10: Back | M10: Saratoga National | N10: White | O10: 71.3 | P10: 130 | Q10: 6225 | R10: Scramble | S10: Doubles | T10: Under 6' | U10: Jackson | V10: Ferrin | W10: White | X10: 28 | Y10: Jackson | Z10: 15 | AA10: 1 | AB10: T | AC10: Halved | AE10: =$V10&$Y10 -> FerrinJackson | AF10: 0.5 | AG10: 0 | AH10: 0 | AI10: 1 | AJ10: 0.5 | AK10: Macklin | AL10: 0.3 | AM10: Poirier | AN10: 0.48611111
B11: 5 | C11: 2 | D11: 1 | E11: FBC1-D5 | F11: Saturday | G11: 41447 | H11: AM | I11: Saratoga, NY | J11: Northeast | K11: 9 | L11: Back | M11: Saratoga National | N11: White | O11: 71.3 | P11: 130 | Q11: 6225 | R11: Scramble | S11: Doubles | T11: Over 6' | U11: Hilts | V11: Macklin | W11: Red | X11: 15 | Y11: Poirier | Z11: 10 | AA11: 1 | AB11: T | AC11: Halved | AE11: =$V11&$Y11 -> MacklinPoirier | AF11: 0.5 | AG11: 0 | AH11: 0 | AI11: 1 | AJ11: 0.5 | AK11: Ferrin | AL11: 0.5952381 | AM11: Jackson | AN11: 0.6171875
B12: 6 | C12: 3 | D12: 1 | E12: FBC1-D6 | F12: Saturday | G12: 41447 | H12: AM | I12: Saratoga, NY | J12: Northeast | K12: 9 | L12: Back | M12: Saratoga National | N12: White | O12: 71.3 | P12: 130 | Q12: 6225 | R12: Scramble | S12: Doubles | T12: Under 6' | U12: Jackson | V12: Flanders | W12: White | X12: 15 | Y12: Mangold | Z12: 15 | AA12: 1 | AB12: L | AC12: 1UP | AE12: =$V12&$Y12 -> FlandersMangold | AF12: 0 | AG12: 0 | AH12: 1 | AI12: 0 | AJ12: 0 | AK12: Connolly | AL12: 0.59375 | AM12: Shively
B13: 6 | C13: 3 | D13: 1 | E13: FBC1-D6 | F13: Saturday | G13: 41447 | H13: AM | I13: Saratoga, NY | J13: Northeast | K13: 9 | L13: Back | M13: Saratoga National | N13: White | O13: 71.3 | P13: 130 | Q13: 6225 | R13: Scramble | S13: Doubles | T13: Over 6' | U13: Hilts | V13: Connolly | W13: Red | X13: 15 | Y13: Shively | Z13: 30 | AA13: 1 | AB13: W | AC13: 1UP | AE13: =$V13&$Y13 -> ConnollyShively | AF13: 1 | AG13: 1 | AH13: 0 | AI13: 0 | AJ13: 1 | AK13: Flanders | AL13: 0.4296875 | AM13: Mangold | AN13: 0.38392857
B14: 7 | C14: 1 | D14: 1 | E14: FBC1-D7 | F14: Saturday | G14: 41447 | H14: PM | I14: Saratoga, NY | J14: Northeast | K14: 9 | L14: Front | M14: Saratoga National | N14: White | O14: 71.3 | P14: 130 | Q14: 6225 | R14: Pinehurst | S14: Doubles | T14: Over 6' | U14: Hilts | V14: Macklin | W14: Red | X14: 15 | Y14: Poirier | Z14: 10 | AA14: 1 | AB14: W | AC14: 2 & 1 | AE14: =$V14&$Y14 -> MacklinPoirier | AF14: 1 | AG14: 1 | AH14: 0 | AI14: 0 | AJ14: 1 | AK14: Grise | AL14: 0.546875 | AM14: Hickerson | AN14: 0.35714286
B15: 7 | C15: 1 | D15: 1 | E15: FBC1-D7 | F15: Saturday | G15: 41447 | H15: PM | I15: Saratoga, NY | J15: Northeast | K15: 9 | L15: Front | M15: Saratoga National | N15: White | O15: 71.3 | P15: 130 | Q15: 6225 | R15: Pinehurst | S15: Doubles | T15: Under 6' | U15: Jackson | V15: Grise | W15: White | X15: 15 | Y15: Hickerson | Z15: 20 | AA15: 1 | AB15: L | AC15: 2 & 1 | AE15: =$V15&$Y15 -> GriseHickerson | AF15: 0 | AG15: 0 | AH15: 1 | AI15: 0 | AJ15: 0 | AK15: Macklin | AL15: 0.3 | AM15: Poirier | AN15: 0.48611111
B16: 8 | C16: 2 | D16: 1 | E16: FBC1-D8 | F16: Saturday | G16: 41447 | H16: PM | I16: Saratoga, NY | J16: Northeast | K16: 9 | L16: Front | M16: Saratoga National | N16: White | O16: 71.3 | P16: 130 | Q16: 6225 | R16: Pinehurst | S16: Doubles | T16: Over 6' | U16: Hilts | V16: Hilts | W16: Red | X16: 18 | Y16: Lynch | Z16: 20 | AA16: 1 | AB16: L | AC16: 3 & 2 | AE16: =$V16&$Y16 -> HiltsLynch | AF16: 0 | AG16: 0 | AH16: 1 | AI16: 0 | AJ16: 0 | AK16: Ferrin | AL16: 0.5952381 | AM16: Jackson | AN16: 0.6171875
B17: 8 | C17: 2 | D17: 1 | E17: FBC1-D8 | F17: Saturday | G17: 41447 | H17: PM | I17: Saratoga, NY | J17: Northeast | K17: 9 | L17: Front | M17: Saratoga National | N17: White | O17: 71.3 | P17: 130 | Q17: 6225 | R17: Pinehurst | S17: Doubles | T17: Under 6' | U17: Jackson | V17: Ferrin | W17: White | X17: 28 | Y17: Jackson | Z17: 15 | AA17: 1 | AB17: W | AC17: 3 & 2 | AE17: =$V17&$Y17 -> FerrinJackson | AF17: 1 | AG17: 1 | AH17: 0 | AI17: 0 | AJ17: 1 | AK17: Hilts | AL17: 0.47321429 | AM17: Lynch | AN17: 0.5546875
B18: 9 | C18: 3 | D18: 1 | E18: FBC1-D9 | F18: Saturday | G18: 41447 | H18: PM | I18: Saratoga, NY | J18: Northeast | K18: 9 | L18: Front | M18: Saratoga National | N18: White | O18: 71.3 | P18: 130 | Q18: 6225 | R18: Pinehurst | S18: Doubles | T18: Over 6' | U18: Hilts | V18: Connolly | W18: Red | X18: 15 | Y18: Shively | Z18: 30 | AA18: 1 | AB18: W | AC18: 5 & 4 | AE18: =$V18&$Y18 -> ConnollyShively | AF18: 1 | AG18: 1 | AH18: 0 | AI18: 0 | AJ18: 1 | AK18: Flanders | AL18: 0.4296875 | AM18: Mangold | AN18: 0.38392857
B19: 9 | C19: 3 | D19: 1 | E19: FBC1-D9 | F19: Saturday | G19: 41447 | H19: PM | I19: Saratoga, NY | J19: Northeast | K19: 9 | L19: Front | M19: Saratoga National | N19: White | O19: 71.3 | P19: 130 | Q19: 6225 | R19: Pinehurst | S19: Doubles | T19: Under 6' | U19: Jackson | V19: Flanders | W19: White | X19: 15 | Y19: Mangold | Z19: 15 | AA19: 1 | AB19: L | AC19: 5 & 4 | AE19: =$V19&$Y19 -> FlandersMangold | AF19: 0 | AG19: 0 | AH19: 1 | AI19: 0 | AJ19: 0 | AK19: Connolly | AL19: 0.59375 | AM19: Shively
B20: 10 | C20: 1 | D20: 1 | E20: FBC1-D10 | F20: Saturday | G20: 41447 | H20: PM | I20: Saratoga, NY | J20: Northeast | K20: 9 | L20: Back | M20: Saratoga National | N20: White | O20: 71.3 | P20: 130 | Q20: 6225 | R20: Best Ball | S20: Doubles | T20: Over 6' | U20: Hilts | V20: Macklin | W20: Red | X20: 15 | Y20: Poirier | Z20: 10 | AA20: 1 | AB20: L | AC20: 2 & 1 | AE20: =$V20&$Y20 -> MacklinPoirier | AF20: 0 | AG20: 0 | AH20: 1 | AI20: 0 | AJ20: 0 | AK20: Grise | AL20: 0.546875 | AM20: Hickerson | AN20: 0.35714286
B21: 10 | C21: 1 | D21: 1 | E21: FBC1-D10 | F21: Saturday | G21: 41447 | H21: PM | I21: Saratoga, NY | J21: Northeast | K21: 9 | L21: Back | M21: Saratoga National | N21: White | O21: 71.3 | P21: 130 | Q21: 6225 | R21: Best Ball | S21: Doubles | T21: Under 6' | U21: Jackson | V21: Grise | W21: White | X21: 15 | Y21: Hickerson | Z21: 20 | AA21: 1 | AB21: W | AC21: 2 & 1 | AE21: =$V21&$Y21 -> GriseHickerson | AF21: 1 | AG21: 1 | AH21: 0 | AI21: 0 | AJ21: 1 | AK21: Macklin | AL21: 0.3 | AM21: Poirier | AN21: 0.48611111
B22: 11 | C22: 2 | D22: 1 | E22: FBC1-D11 | F22: Saturday | G22: 41447 | H22: PM | I22: Saratoga, NY | J22: Northeast | K22: 9 | L22: Back | M22: Saratoga National | N22: White | O22: 71.3 | P22: 130 | Q22: 6225 | R22: Best Ball | S22: Doubles | T22: Over 6' | U22: Hilts | V22: Hilts | W22: Red | X22: 18 | Y22: Lynch | Z22: 20 | AA22: 1 | AB22: L | AC22: 2 Up | AE22: =$V22&$Y22 -> HiltsLynch | AF22: 0 | AG22: 0 | AH22: 1 | AI22: 0 | AJ22: 0 | AK22: Ferrin | AL22: 0.5952381 | AM22: Jackson | AN22: 0.6171875
B23: 11 | C23: 2 | D23: 1 | E23: FBC1-D11 | F23: Saturday | G23: 41447 | H23: PM | I23: Saratoga, NY | J23: Northeast | K23: 9 | L23: Back | M23: Saratoga National | N23: White | O23: 71.3 | P23: 130 | Q23: 6225 | R23: Best Ball | S23: Doubles | T23: Under 6' | U23: Jackson | V23: Ferrin | W23: White | X23: 28 | Y23: Jackson | Z23: 15 | AA23: 1 | AB23: W | AC23: 2 Up | AE23: =$V23&$Y23 -> FerrinJackson | AF23: 1 | AG23: 1 | AH23: 0 | AI23: 0 | AJ23: 1 | AK23: Hilts | AL23: 0.47321429 | AM23: Lynch | AN23: 0.5546875
B24: 12 | C24: 3 | D24: 1 | E24: FBC1-D12 | F24: Saturday | G24: 41447 | H24: PM | I24: Saratoga, NY | J24: Northeast | K24: 9 | L24: Back | M24: Saratoga National | N24: White | O24: 71.3 | P24: 130 | Q24: 6225 | R24: Best Ball | S24: Doubles | T24: Over 6' | U24: Hilts | V24: Connolly | W24: Red | X24: 15 | Y24: Shively | Z24: 30 | AA24: 1 | AB24: W | AC24: 3 & 2 | AE24: =$V24&$Y24 -> ConnollyShively | AF24: 1 | AG24: 1 | AH24: 0 | AI24: 0 | AJ24: 1 | AK24: Flanders | AL24: 0.4296875 | AM24: Mangold | AN24: 0.38392857
B25: 12 | C25: 3 | D25: 1 | E25: FBC1-D12 | F25: Saturday | G25: 41447 | H25: PM | I25: Saratoga, NY | J25: Northeast | K25: 9 | L25: Back | M25: Saratoga National | N25: White | O25: 71.3 | P25: 130 | Q25: 6225 | R25: Best Ball | S25: Doubles | T25: Under 6' | U25: Jackson | V25: Flanders | W25: White | X25: 15 | Y25: Mangold | Z25: 15 | AA25: 1 | AB25: L | AC25: 3 & 2 | AE25: =$V25&$Y25 -> FlandersMangold | AF25: 0 | AG25: 0 | AH25: 1 | AI25: 0 | AJ25: 0 | AK25: Connolly | AL25: 0.59375 | AM25: Shively
B26: 13 | C26: 1 | D26: 1 | E26: FBC1-S-Hilts-Mangold | F26: Sunday | G26: 41448 | H26: AM | I26: Saratoga, NY | J26: Northeast | K26: 18 | L26: Full | M26: Saratoga Spa | N26: Blue | O26: 72.2 | P26: 128 | Q26: 6772 | R26: Match Play | S26: Singles | T26: Over 6' | U26: Hilts | V26: Hilts | W26: Blue | X26: 18 | AA26: 2 | AB26: W | AC26: 4 & 3 | AD26: Mangold | AE26: =$V26&$Y26 -> Hilts | AF26: 2 | AG26: 1 | AH26: 0 | AI26: 0 | AJ26: 1 | AK26: Mangold | AL26: 0.38392857
B27: 13 | C27: 1 | D27: 1 | E27: FBC1-S-Hilts-Mangold | F27: Sunday | G27: 41448 | H27: AM | I27: Saratoga, NY | J27: Northeast | K27: 18 | L27: Full | M27: Saratoga Spa | N27: Blue | O27: 72.2 | P27: 128 | Q27: 6772 | R27: Match Play | S27: Singles | T27: Under 6' | U27: Jackson | V27: Mangold | W27: Blue | X27: 15 | AA27: 2 | AB27: L | AC27: 4 & 3 | AD27: Hilts | AE27: =$V27&$Y27 -> Mangold | AF27: 0 | AG27: 0 | AH27: 1 | AI27: 0 | AJ27: 0 | AK27: Hilts | AL27: 0.47321429
B28: 14 | C28: 2 | D28: 1 | E28: FBC1-S-Hickerson-Lynch | F28: Sunday | G28: 41448 | H28: AM | I28: Saratoga, NY | J28: Northeast | K28: 18 | L28: Full | M28: Saratoga Spa | N28: Blue | O28: 72.2 | P28: 128 | Q28: 6772 | R28: Match Play | S28: Singles | T28: Under 6' | U28: Jackson | V28: Hickerson | W28: Blue | X28: 20 | AA28: 2 | AB28: T | AC28: Halved | AD28: Lynch | AE28: =$V28&$Y28 -> Hickerson | AF28: 1 | AG28: 0 | AH28: 0 | AI28: 1 | AJ28: 0.5 | AK28: Lynch | AL28: 0.5546875
B29: 14 | C29: 2 | D29: 1 | E29: FBC1-S-Hickerson-Lynch | F29: Sunday | G29: 41448 | H29: AM | I29: Saratoga, NY | J29: Northeast | K29: 18 | L29: Full | M29: Saratoga Spa | N29: Blue | O29: 72.2 | P29: 128 | Q29: 6772 | R29: Match Play | S29: Singles | T29: Over 6' | U29: Hilts | V29: Lynch | W29: Blue | X29: 20 | AA29: 2 | AB29: T | AC29: Halved | AD29: Hickerson | AE29: =$V29&$Y29 -> Lynch | AF29: 1 | AG29: 0 | AH29: 0 | AI29: 1 | AJ29: 0.5 | AK29: Hickerson | AL29: 0.35714286
B30: 15 | C30: 3 | D30: 1 | E30: FBC1-S-Ferrin-Shively | F30: Sunday | G30: 41448 | H30: AM | I30: Saratoga, NY | J30: Northeast | K30: 18 | L30: Full | M30: Saratoga Spa | N30: Blue | O30: 72.2 | P30: 128 | Q30: 6772 | R30: Match Play | S30: Singles | T30: Over 6' | U30: Hilts | V30: Shively | W30: Blue | X30: 30 | AA30: 2 | AB30: L | AC30: 3 & 2 | AD30: Ferrin | AE30: =$V30&$Y30 -> Shively | AF30: 0 | AG30: 0 | AH30: 1 | AI30: 0 | AJ30: 0 | AK30: Ferrin | AL30: 0.5952381
B31: 15 | C31: 3 | D31: 1 | E31: FBC1-S-Ferrin-Shively | F31: Sunday | G31: 41448 | H31: AM | I31: Saratoga, NY | J31: Northeast | K31: 18 | L31: Full | M31: Saratoga Spa | N31: Blue | O31: 72.2 | P31: 128 | Q31: 6772 | R31: Match Play | S31: Singles | T31: Under 6' | U31: Jackson | V31: Ferrin | W31: Blue | X31: 28 | AA31: 2 | AB31: W | AC31: 3 & 2 | AD31: Shively | AE31: =$V31&$Y31 -> Ferrin | AF31: 2 | AG31: 1 | AH31: 0 | AI31: 0 | AJ31: 1 | AK31: Shively
B32: 16 | C32: 4 | D32: 1 | E32: FBC1-S-Flanders-Macklin | F32: Sunday | G32: 41448 | H32: AM | I32: Saratoga, NY | J32: Northeast | K32: 18 | L32: Full | M32: Saratoga Spa | N32: Blue | O32: 72.2 | P32: 128 | Q32: 6772 | R32: Match Play | S32: Singles | T32: Under 6' | U32: Jackson | V32: Flanders | W32: Blue | X32: 15 | AA32: 2 | AB32: W | AC32: 4 & 3 | AD32: Macklin | AE32: =$V32&$Y32 -> Flanders | AF32: 2 | AG32: 1 | AH32: 0 | AI32: 0 | AJ32: 1 | AK32: Macklin | AL32: 0.3
B33: 16 | C33: 4 | D33: 1 | E33: FBC1-S-Flanders-Macklin | F33: Sunday | G33: 41448 | H33: AM | I33: Saratoga, NY | J33: Northeast | K33: 18 | L33: Full | M33: Saratoga Spa | N33: Blue | O33: 72.2 | P33: 128 | Q33: 6772 | R33: Match Play | S33: Singles | T33: Over 6' | U33: Hilts | V33: Macklin | W33: Blue | X33: 15 | AA33: 2 | AB33: L | AC33: 4 & 3 | AD33: Flanders | AE33: =$V33&$Y33 -> Macklin | AF33: 0 | AG33: 0 | AH33: 1 | AI33: 0 | AJ33: 0 | AK33: Flanders | AL33: 0.4296875
B34: 17 | C34: 5 | D34: 1 | E34: FBC1-S-Connolly-Jackson | F34: Sunday | G34: 41448 | H34: AM | I34: Saratoga, NY | J34: Northeast | K34: 18 | L34: Full | M34: Saratoga Spa | N34: Blue | O34: 72.2 | P34: 128 | Q34: 6772 | R34: Match Play | S34: Singles | T34: Over 6' | U34: Hilts | V34: Connolly | W34: Blue | X34: 15 | AA34: 2 | AB34: W | AC34: 5 & 3 | AD34: Jackson | AE34: =$V34&$Y34 -> Connolly | AF34: 2 | AG34: 1 | AH34: 0 | AI34: 0 | AJ34: 1 | AK34: Jackson | AL34: 0.6171875
B35: 17 | C35: 5 | D35: 1 | E35: FBC1-S-Connolly-Jackson | F35: Sunday | G35: 41448 | H35: AM | I35: Saratoga, NY | J35: Northeast | K35: 18 | L35: Full | M35: Saratoga Spa | N35: Blue | O35: 72.2 | P35: 128 | Q35: 6772 | R35: Match Play | S35: Singles | T35: Under 6' | U35: Jackson | V35: Jackson | W35: Blue | X35: 15 | AA35: 2 | AB35: L | AC35: 5 & 3 | AD35: Connolly | AE35: =$V35&$Y35 -> Jackson | AF35: 0 | AG35: 0 | AH35: 1 | AI35: 0 | AJ35: 0 | AK35: Connolly | AL35: 0.59375
B36: 18 | C36: 6 | D36: 1 | E36: FBC1-S-Grise-Poirier | F36: Sunday | G36: 41448 | H36: AM | I36: Saratoga, NY | J36: Northeast | K36: 18 | L36: Full | M36: Saratoga Spa | N36: Blue | O36: 72.2 | P36: 128 | Q36: 6772 | R36: Match Play | S36: Singles | T36: Under 6' | U36: Jackson | V36: Grise | W36: Blue | X36: 15 | AA36: 2 | AB36: L | AC36: 6 & 5 | AD36: Poirier | AE36: =$V36&$Y36 -> Grise | AF36: 0 | AG36: 0 | AH36: 1 | AI36: 0 | AJ36: 0 | AK36: Poirier | AL36: 0.48611111
B37: 18 | C37: 6 | D37: 1 | E37: FBC1-S-Grise-Poirier | F37: Sunday | G37: 41448 | H37: AM | I37: Saratoga, NY | J37: Northeast | K37: 18 | L37: Full | M37: Saratoga Spa | N37: Blue | O37: 72.2 | P37: 128 | Q37: 6772 | R37: Match Play | S37: Singles | T37: Over 6' | U37: Hilts | V37: Poirier | W37: Blue | X37: 10 | AA37: 2 | AB37: W | AC37: 6 & 5 | AD37: Grise | AE37: =$V37&$Y37 -> Poirier | AF37: 2 | AG37: 1 | AH37: 0 | AI37: 0 | AJ37: 1 | AK37: Grise | AL37: 0.546875
B38: 1 | C38: 1 | D38: 2 | E38: FBC2-D1 | F38: Saturday | G38: 41797 | H38: AM | I38: Verona, NY (Turning Stone) | J38: Northeast | K38: 9 | L38: Front | M38: Atunyote | N38: White | O38: 71.6 | P38: 131 | Q38: 6561 | R38: Best Ball | S38: Doubles | T38: Over 6' | U38: Connolly | V38: Grise | W38: Green | X38: 2 | Y38: Jackson | Z38: 0 | AA38: 1 | AB38: W | AC38: 3 & 1 | AE38: =$V38&$Y38 -> GriseJackson | AF38: 1 | AG38: 1 | AH38: 0 | AI38: 0 | AJ38: 1 | AK38: Bussiculo | AL38: 0.44827586 | AM38: Fogan | AN38: 0.37288136
B39: 1 | C39: 1 | D39: 2 | E39: FBC2-D1 | F39: Saturday | G39: 41797 | H39: AM | I39: Verona, NY (Turning Stone) | J39: Northeast | K39: 9 | L39: Front | M39: Atunyote | N39: White | O39: 71.6 | P39: 131 | Q39: 6561 | R39: Best Ball | S39: Doubles | T39: Over 6' | U39: Ferrin | V39: Bussiculo | W39: Blue/White | X39: 0 | Y39: Fogan | Z39: 22 | AA39: 1 | AB39: L | AC39: 3 & 1 | AE39: =$V39&$Y39 -> BussiculoFogan | AF39: 0 | AG39: 0 | AH39: 1 | AI39: 0 | AJ39: 0 | AK39: Grise | AL39: 0.546875 | AM39: Jackson | AN39: 0.6171875
B40: 2 | C40: 2 | D40: 2 | E40: FBC2-D2 | F40: Saturday | G40: 41797 | H40: AM | I40: Verona, NY (Turning Stone) | J40: Northeast | K40: 9 | L40: Front | M40: Atunyote | N40: White | O40: 71.6 | P40: 131 | Q40: 6561 | R40: Best Ball | S40: Doubles | T40: Over 6' | U40: Ferrin | V40: Ferrin | W40: Blue/White | X40: 12 | Y40: Weisberger | Z40: 5 | AA40: 1 | AB40: T | AC40: Halved | AE40: =$V40&$Y40 -> FerrinWeisberger | AF40: 0.5 | AG40: 0 | AH40: 0 | AI40: 1 | AJ40: 0.5 | AK40: Flanders | AL40: 0.4296875 | AM40: Forster | AN40: 0.59649123
B41: 2 | C41: 2 | D41: 2 | E41: FBC2-D2 | F41: Saturday | G41: 41797 | H41: AM | I41: Verona, NY (Turning Stone) | J41: Northeast | K41: 9 | L41: Front | M41: Atunyote | N41: White | O41: 71.6 | P41: 131 | Q41: 6561 | R41: Best Ball | S41: Doubles | T41: Over 6' | U41: Connolly | V41: Flanders | W41: Green | X41: 5 | Y41: Forster | Z41: 21 | AA41: 1 | AB41: T | AC41: Halved | AE41: =$V41&$Y41 -> FlandersForster | AF41: 0.5 | AG41: 0 | AH41: 0 | AI41: 1 | AJ41: 0.5 | AK41: Ferrin | AL41: 0.5952381 | AM41: Weisberger | AN41: 0.5
B42: 3 | C42: 3 | D42: 2 | E42: FBC2-D3 | F42: Saturday | G42: 41797 | H42: AM | I42: Verona, NY (Turning Stone) | J42: Northeast | K42: 9 | L42: Front | M42: Atunyote | N42: White | O42: 71.6 | P42: 131 | Q42: 6561 | R42: Best Ball | S42: Doubles | T42: Over 6' | U42: Connolly | V42: Connolly | W42: Green | X42: 0 | Y42: Connors | Z42: 8 | AA42: 1 | AB42: T | AC42: Halved | AE42: =$V42&$Y42 -> ConnollyConnors | AF42: 0.5 | AG42: 0 | AH42: 0 | AI42: 1 | AJ42: 0.5 | AK42: Cole | AL42: 0.44067797 | AM42: Mangold | AN42: 0.38392857
B43: 3 | C43: 3 | D43: 2 | E43: FBC2-D3 | F43: Saturday | G43: 41797 | H43: AM | I43: Verona, NY (Turning Stone) | J43: Northeast | K43: 9 | L43: Front | M43: Atunyote | N43: White | O43: 71.6 | P43: 131 | Q43: 6561 | R43: Best Ball | S43: Doubles | T43: Over 6' | U43: Ferrin | V43: Cole | W43: Blue/White | X43: 24 | Y43: Mangold | Z43: 4 | AA43: 1 | AB43: T | AC43: Halved | AE43: =$V43&$Y43 -> ColeMangold | AF43: 0.5 | AG43: 0 | AH43: 0 | AI43: 1 | AJ43: 0.5 | AK43: Connolly | AL43: 0.59375 | AM43: Connors | AN43: 0.34745763
B44: 4 | C44: 4 | D44: 2 | E44: FBC2-D4 | F44: Saturday | G44: 41797 | H44: AM | I44: Verona, NY (Turning Stone) | J44: Northeast | K44: 9 | L44: Front | M44: Atunyote | N44: White | O44: 71.6 | P44: 131 | Q44: 6561 | R44: Best Ball | S44: Doubles | T44: Over 6' | U44: Ferrin | V44: Hickerson | W44: Blue/White | X44: 8 | Y44: Shively | Z44: 11 | AA44: 1 | AB44: L | AC44: 2 UP | AE44: =$V44&$Y44 -> HickersonShively | AF44: 0 | AG44: 0 | AH44: 1 | AI44: 0 | AJ44: 0 | AK44: Hilts | AL44: 0.47321429 | AM44: Lynch | AN44: 0.5546875
B45: 4 | C45: 4 | D45: 2 | E45: FBC2-D4 | F45: Saturday | G45: 41797 | H45: AM | I45: Verona, NY (Turning Stone) | J45: Northeast | K45: 9 | L45: Front | M45: Atunyote | N45: White | O45: 71.6 | P45: 131 | Q45: 6561 | R45: Best Ball | S45: Doubles | T45: Over 6' | U45: Connolly | V45: Hilts | W45: Green | X45: 7 | Y45: Lynch | Z45: 8 | AA45: 1 | AB45: W | AC45: 2 UP | AE45: =$V45&$Y45 -> HiltsLynch | AF45: 1 | AG45: 1 | AH45: 0 | AI45: 0 | AJ45: 1 | AK45: Hickerson | AL45: 0.35714286 | AM45: Shively
B46: 5 | C46: 1 | D46: 2 | E46: FBC2-D5 | F46: Saturday | G46: 41797 | H46: AM | I46: Verona, NY (Turning Stone) | J46: Northeast | K46: 9 | L46: Back | M46: Atunyote | N46: White | O46: 71.6 | P46: 131 | Q46: 6561 | R46: Shamble | S46: Doubles | T46: Over 6' | U46: Connolly | V46: Grise | W46: Green | X46: 2 | Y46: Jackson | Z46: 0 | AA46: 1 | AB46: W | AC46: 4 & 3 | AE46: =$V46&$Y46 -> GriseJackson | AF46: 1 | AG46: 1 | AH46: 0 | AI46: 0 | AJ46: 1 | AK46: Bussiculo | AL46: 0.44827586 | AM46: Fogan | AN46: 0.37288136
B47: 5 | C47: 1 | D47: 2 | E47: FBC2-D5 | F47: Saturday | G47: 41797 | H47: AM | I47: Verona, NY (Turning Stone) | J47: Northeast | K47: 9 | L47: Back | M47: Atunyote | N47: White | O47: 71.6 | P47: 131 | Q47: 6561 | R47: Shamble | S47: Doubles | T47: Over 6' | U47: Ferrin | V47: Bussiculo | W47: Blue/White | X47: 0 | Y47: Fogan | Z47: 22 | AA47: 1 | AB47: L | AC47: 4 & 3 | AE47: =$V47&$Y47 -> BussiculoFogan | AF47: 0 | AG47: 0 | AH47: 1 | AI47: 0 | AJ47: 0 | AK47: Grise | AL47: 0.546875 | AM47: Jackson | AN47: 0.6171875
B48: 6 | C48: 2 | D48: 2 | E48: FBC2-D6 | F48: Saturday | G48: 41797 | H48: AM | I48: Verona, NY (Turning Stone) | J48: Northeast | K48: 9 | L48: Back | M48: Atunyote | N48: White | O48: 71.6 | P48: 131 | Q48: 6561 | R48: Shamble | S48: Doubles | T48: Over 6' | U48: Ferrin | V48: Ferrin | W48: Blue/White | X48: 12 | Y48: Weisberger | Z48: 5 | AA48: 1 | AB48: L | AC48: 4 & 3 | AE48: =$V48&$Y48 -> FerrinWeisberger | AF48: 0 | AG48: 0 | AH48: 1 | AI48: 0 | AJ48: 0 | AK48: Flanders | AL48: 0.4296875 | AM48: Forster | AN48: 0.59649123
B49: 6 | C49: 2 | D49: 2 | E49: FBC2-D6 | F49: Saturday | G49: 41797 | H49: AM | I49: Verona, NY (Turning Stone) | J49: Northeast | K49: 9 | L49: Back | M49: Atunyote | N49: White | O49: 71.6 | P49: 131 | Q49: 6561 | R49: Shamble | S49: Doubles | T49: Over 6' | U49: Connolly | V49: Flanders | W49: Green | X49: 5 | Y49: Forster | Z49: 21 | AA49: 1 | AB49: W | AC49: 4 & 3 | AE49: =$V49&$Y49 -> FlandersForster | AF49: 1 | AG49: 1 | AH49: 0 | AI49: 0 | AJ49: 1 | AK49: Ferrin | AL49: 0.5952381 | AM49: Weisberger | AN49: 0.5
B50: 7 | C50: 3 | D50: 2 | E50: FBC2-D7 | F50: Saturday | G50: 41797 | H50: AM | I50: Verona, NY (Turning Stone) | J50: Northeast | K50: 9 | L50: Back | M50: Atunyote | N50: White | O50: 71.6 | P50: 131 | Q50: 6561 | R50: Shamble | S50: Doubles | T50: Over 6' | U50: Connolly | V50: Connolly | W50: Green | X50: 0 | Y50: Connors | Z50: 8 | AA50: 1 | AB50: W | AC50: 4 & 3 | AE50: =$V50&$Y50 -> ConnollyConnors | AF50: 1 | AG50: 1 | AH50: 0 | AI50: 0 | AJ50: 1 | AK50: Cole | AL50: 0.44067797 | AM50: Mangold | AN50: 0.38392857
B51: 7 | C51: 3 | D51: 2 | E51: FBC2-D7 | F51: Saturday | G51: 41797 | H51: AM | I51: Verona, NY (Turning Stone) | J51: Northeast | K51: 9 | L51: Back | M51: Atunyote | N51: White | O51: 71.6 | P51: 131 | Q51: 6561 | R51: Shamble | S51: Doubles | T51: Over 6' | U51: Ferrin | V51: Cole | W51: Blue/White | X51: 24 | Y51: Mangold | Z51: 4 | AA51: 1 | AB51: L | AC51: 4 & 3 | AE51: =$V51&$Y51 -> ColeMangold | AF51: 0 | AG51: 0 | AH51: 1 | AI51: 0 | AJ51: 0 | AK51: Connolly | AL51: 0.59375 | AM51: Connors | AN51: 0.34745763
B52: 8 | C52: 4 | D52: 2 | E52: FBC2-D8 | F52: Saturday | G52: 41797 | H52: AM | I52: Verona, NY (Turning Stone) | J52: Northeast | K52: 9 | L52: Back | M52: Atunyote | N52: White | O52: 71.6 | P52: 131 | Q52: 6561 | R52: Shamble | S52: Doubles | T52: Over 6' | U52: Ferrin | V52: Hickerson | W52: Blue/White | X52: 8 | Y52: Shively | Z52: 11 | AA52: 1 | AB52: L | AC52: 3 & 2 | AE52: =$V52&$Y52 -> HickersonShively | AF52: 0 | AG52: 0 | AH52: 1 | AI52: 0 | AJ52: 0 | AK52: Hilts | AL52: 0.47321429 | AM52: Lynch | AN52: 0.5546875
B53: 8 | C53: 4 | D53: 2 | E53: FBC2-D8 | F53: Saturday | G53: 41797 | H53: AM | I53: Verona, NY (Turning Stone) | J53: Northeast | K53: 9 | L53: Back | M53: Atunyote | N53: White | O53: 71.6 | P53: 131 | Q53: 6561 | R53: Shamble | S53: Doubles | T53: Over 6' | U53: Connolly | V53: Hilts | W53: Green | X53: 7 | Y53: Lynch | Z53: 8 | AA53: 1 | AB53: W | AC53: 3 & 2 | AE53: =$V53&$Y53 -> HiltsLynch | AF53: 1 | AG53: 1 | AH53: 0 | AI53: 0 | AJ53: 1 | AK53: Hickerson | AL53: 0.35714286 | AM53: Shively
B54: 9 | C54: 1 | D54: 2 | E54: FBC2-D9 | F54: Saturday | G54: 41797 | H54: PM | I54: Verona, NY (Turning Stone) | J54: Northeast | K54: 9 | L54: Front | M54: Shenendoah | N54: White | O54: 70.6 | P54: 133 | Q54: 6328 | R54: Hi-Lo | S54: Doubles | T54: Over 6' | U54: Connolly | V54: Forster | W54: Green | X54: 21 | Y54: Lynch | Z54: 8 | AA54: 1 | AB54: W | AC54: 7UP | AE54: =$V54&$Y54 -> ForsterLynch | AF54: 1 | AG54: 1 | AH54: 0 | AI54: 0 | AJ54: 1 | AK54: Cole | AL54: 0.44067797 | AM54: Ferrin | AN54: 0.5952381
B55: 9 | C55: 1 | D55: 2 | E55: FBC2-D9 | F55: Saturday | G55: 41797 | H55: PM | I55: Verona, NY (Turning Stone) | J55: Northeast | K55: 9 | L55: Front | M55: Shenendoah | N55: White | O55: 70.6 | P55: 133 | Q55: 6328 | R55: Hi-Lo | S55: Doubles | T55: Over 6' | U55: Ferrin | V55: Cole | W55: Blue/White | X55: 24 | Y55: Ferrin | Z55: 12 | AA55: 1 | AB55: L | AC55: 7UP | AE55: =$V55&$Y55 -> ColeFerrin | AF55: 0 | AG55: 0 | AH55: 1 | AI55: 0 | AJ55: 0 | AK55: Forster | AL55: 0.59649123 | AM55: Lynch | AN55: 0.5546875
B56: 10 | C56: 2 | D56: 2 | E56: FBC2-D10 | F56: Saturday | G56: 41797 | H56: PM | I56: Verona, NY (Turning Stone) | J56: Northeast | K56: 9 | L56: Front | M56: Shenendoah | N56: White | O56: 70.6 | P56: 133 | Q56: 6328 | R56: Hi-Lo | S56: Doubles | T56: Over 6' | U56: Ferrin | V56: Fogan | W56: Blue/White | X56: 22 | Y56: Weisberger | Z56: 5 | AA56: 1 | AB56: L | AC56: 2UP | AE56: =$V56&$Y56 -> FoganWeisberger | AF56: 0 | AG56: 0 | AH56: 1 | AI56: 0 | AJ56: 0 | AK56: Connolly | AL56: 0.59375 | AM56: Jackson | AN56: 0.6171875
B57: 10 | C57: 2 | D57: 2 | E57: FBC2-D10 | F57: Saturday | G57: 41797 | H57: PM | I57: Verona, NY (Turning Stone) | J57: Northeast | K57: 9 | L57: Front | M57: Shenendoah | N57: White | O57: 70.6 | P57: 133 | Q57: 6328 | R57: Hi-Lo | S57: Doubles | T57: Over 6' | U57: Connolly | V57: Connolly | W57: Green | X57: 0 | Y57: Jackson | Z57: 0 | AA57: 1 | AB57: W | AC57: 2UP | AE57: =$V57&$Y57 -> ConnollyJackson | AF57: 1 | AG57: 1 | AH57: 0 | AI57: 0 | AJ57: 1 | AK57: Fogan | AL57: 0.37288136 | AM57: Weisberger | AN57: 0.5
B58: 11 | C58: 3 | D58: 2 | E58: FBC2-D11 | F58: Saturday | G58: 41797 | H58: PM | I58: Verona, NY (Turning Stone) | J58: Northeast | K58: 9 | L58: Front | M58: Shenendoah | N58: White | O58: 70.6 | P58: 133 | Q58: 6328 | R58: Hi-Lo | S58: Doubles | T58: Over 6' | U58: Connolly | V58: Flanders | W58: Green | X58: 5 | Y58: Hilts | Z58: 7 | AA58: 1 | AB58: L | AC58: 1UP | AE58: =$V58&$Y58 -> FlandersHilts | AF58: 0 | AG58: 0 | AH58: 1 | AI58: 0 | AJ58: 0 | AK58: Bussiculo | AL58: 0.44827586 | AM58: Hickerson | AN58: 0.35714286
B59: 11 | C59: 3 | D59: 2 | E59: FBC2-D11 | F59: Saturday | G59: 41797 | H59: PM | I59: Verona, NY (Turning Stone) | J59: Northeast | K59: 9 | L59: Front | M59: Shenendoah | N59: White | O59: 70.6 | P59: 133 | Q59: 6328 | R59: Hi-Lo | S59: Doubles | T59: Over 6' | U59: Ferrin | V59: Bussiculo | W59: Blue/White | X59: 0 | Y59: Hickerson | Z59: 8 | AA59: 1 | AB59: W | AC59: 1UP | AE59: =$V59&$Y59 -> BussiculoHickerson | AF59: 1 | AG59: 1 | AH59: 0 | AI59: 0 | AJ59: 1 | AK59: Flanders | AL59: 0.4296875 | AM59: Hilts | AN59: 0.47321429
B60: 12 | C60: 4 | D60: 2 | E60: FBC2-D12 | F60: Saturday | G60: 41797 | H60: PM | I60: Verona, NY (Turning Stone) | J60: Northeast | K60: 9 | L60: Front | M60: Shenendoah | N60: White | O60: 70.6 | P60: 133 | Q60: 6328 | R60: Hi-Lo | S60: Doubles | T60: Over 6' | U60: Ferrin | V60: Mangold | W60: Blue/White | X60: 4 | Y60: Shively | Z60: 11 | AA60: 1 | AB60: W | AC60: 4UP | AE60: =$V60&$Y60 -> MangoldShively | AF60: 1 | AG60: 1 | AH60: 0 | AI60: 0 | AJ60: 1 | AK60: Connors | AL60: 0.34745763 | AM60: Grise | AN60: 0.546875
B61: 12 | C61: 4 | D61: 2 | E61: FBC2-D12 | F61: Saturday | G61: 41797 | H61: PM | I61: Verona, NY (Turning Stone) | J61: Northeast | K61: 9 | L61: Front | M61: Shenendoah | N61: White | O61: 70.6 | P61: 133 | Q61: 6328 | R61: Hi-Lo | S61: Doubles | T61: Over 6' | U61: Connolly | V61: Connors | W61: Green | X61: 8 | Y61: Grise | Z61: 2 | AA61: 1 | AB61: L | AC61: 4UP | AE61: =$V61&$Y61 -> ConnorsGrise | AF61: 0 | AG61: 0 | AH61: 1 | AI61: 0 | AJ61: 0 | AK61: Mangold | AL61: 0.38392857 | AM61: Shively
B62: 13 | C62: 1 | D62: 2 | E62: FBC2-D13 | F62: Saturday | G62: 41797 | H62: PM | I62: Verona, NY (Turning Stone) | J62: Northeast | K62: 9 | L62: Back | M62: Shenendoah | N62: White | O62: 70.6 | P62: 133 | Q62: 6328 | R62: Scramble-Stableford | S62: Doubles | T62: Over 6' | U62: Connolly | V62: Forster | W62: Green | X62: 21 | Y62: Lynch | Z62: 8 | AA62: 1 | AB62: W | AC62: 11.5-7 | AE62: =$V62&$Y62 -> ForsterLynch | AF62: 1 | AG62: 1 | AH62: 0 | AI62: 0 | AJ62: 1 | AK62: Cole | AL62: 0.44067797 | AM62: Ferrin | AN62: 0.5952381
B63: 13 | C63: 1 | D63: 2 | E63: FBC2-D13 | F63: Saturday | G63: 41797 | H63: PM | I63: Verona, NY (Turning Stone) | J63: Northeast | K63: 9 | L63: Back | M63: Shenendoah | N63: White | O63: 70.6 | P63: 133 | Q63: 6328 | R63: Scramble-Stableford | S63: Doubles | T63: Over 6' | U63: Ferrin | V63: Cole | W63: Blue/White | X63: 24 | Y63: Ferrin | Z63: 12 | AA63: 1 | AB63: L | AC63: 11.5-7 | AE63: =$V63&$Y63 -> ColeFerrin | AF63: 0 | AG63: 0 | AH63: 1 | AI63: 0 | AJ63: 0 | AK63: Forster | AL63: 0.59649123 | AM63: Lynch | AN63: 0.5546875
B64: 14 | C64: 2 | D64: 2 | E64: FBC2-D14 | F64: Saturday | G64: 41797 | H64: PM | I64: Verona, NY (Turning Stone) | J64: Northeast | K64: 9 | L64: Back | M64: Shenendoah | N64: White | O64: 70.6 | P64: 133 | Q64: 6328 | R64: Scramble-Stableford | S64: Doubles | T64: Over 6' | U64: Ferrin | V64: Fogan | W64: Blue/White | X64: 22 | Y64: Weisberger | Z64: 5 | AA64: 1 | AB64: L | AC64: 22.5-10 | AE64: =$V64&$Y64 -> FoganWeisberger | AF64: 0 | AG64: 0 | AH64: 1 | AI64: 0 | AJ64: 0 | AK64: Connolly | AL64: 0.59375 | AM64: Jackson | AN64: 0.6171875
B65: 14 | C65: 2 | D65: 2 | E65: FBC2-D14 | F65: Saturday | G65: 41797 | H65: PM | I65: Verona, NY (Turning Stone) | J65: Northeast | K65: 9 | L65: Back | M65: Shenendoah | N65: White | O65: 70.6 | P65: 133 | Q65: 6328 | R65: Scramble-Stableford | S65: Doubles | T65: Over 6' | U65: Connolly | V65: Connolly | W65: Green | X65: 0 | Y65: Jackson | Z65: 0 | AA65: 1 | AB65: W | AC65: 22.5-10 | AE65: =$V65&$Y65 -> ConnollyJackson | AF65: 1 | AG65: 1 | AH65: 0 | AI65: 0 | AJ65: 1 | AK65: Fogan | AL65: 0.37288136 | AM65: Weisberger | AN65: 0.5
B66: 15 | C66: 3 | D66: 2 | E66: FBC2-D15 | F66: Saturday | G66: 41797 | H66: PM | I66: Verona, NY (Turning Stone) | J66: Northeast | K66: 9 | L66: Back | M66: Shenendoah | N66: White | O66: 70.6 | P66: 133 | Q66: 6328 | R66: Scramble-Stableford | S66: Doubles | T66: Over 6' | U66: Connolly | V66: Flanders | W66: Green | X66: 5 | Y66: Hilts | Z66: 7 | AA66: 1 | AB66: L | AC66: 12.5-8 | AE66: =$V66&$Y66 -> FlandersHilts | AF66: 0 | AG66: 0 | AH66: 1 | AI66: 0 | AJ66: 0 | AK66: Bussiculo | AL66: 0.44827586 | AM66: Hickerson | AN66: 0.35714286
B67: 15 | C67: 3 | D67: 2 | E67: FBC2-D15 | F67: Saturday | G67: 41797 | H67: PM | I67: Verona, NY (Turning Stone) | J67: Northeast | K67: 9 | L67: Back | M67: Shenendoah | N67: White | O67: 70.6 | P67: 133 | Q67: 6328 | R67: Scramble-Stableford | S67: Doubles | T67: Over 6' | U67: Ferrin | V67: Bussiculo | W67: Blue/White | X67: 0 | Y67: Hickerson | Z67: 8 | AA67: 1 | AB67: W | AC67: 12.5-8 | AE67: =$V67&$Y67 -> BussiculoHickerson | AF67: 1 | AG67: 1 | AH67: 0 | AI67: 0 | AJ67: 1 | AK67: Flanders | AL67: 0.4296875 | AM67: Hilts | AN67: 0.47321429
B68: 16 | C68: 4 | D68: 2 | E68: FBC2-D16 | F68: Saturday | G68: 41797 | H68: PM | I68: Verona, NY (Turning Stone) | J68: Northeast | K68: 9 | L68: Back | M68: Shenendoah | N68: White | O68: 70.6 | P68: 133 | Q68: 6328 | R68: Scramble-Stableford | S68: Doubles | T68: Over 6' | U68: Ferrin | V68: Mangold | W68: Blue/White | X68: 4 | Y68: Shively | Z68: 11 | AA68: 1 | AB68: L | AC68: 20-11 | AE68: =$V68&$Y68 -> MangoldShively | AF68: 0 | AG68: 0 | AH68: 1 | AI68: 0 | AJ68: 0 | AK68: Connors | AL68: 0.34745763 | AM68: Grise | AN68: 0.546875
B69: 16 | C69: 4 | D69: 2 | E69: FBC2-D16 | F69: Saturday | G69: 41797 | H69: PM | I69: Verona, NY (Turning Stone) | J69: Northeast | K69: 9 | L69: Back | M69: Shenendoah | N69: White | O69: 70.6 | P69: 133 | Q69: 6328 | R69: Scramble-Stableford | S69: Doubles | T69: Over 6' | U69: Connolly | V69: Connors | W69: Green | X69: 8 | Y69: Grise | Z69: 2 | AA69: 1 | AB69: W | AC69: 20-11 | AE69: =$V69&$Y69 -> ConnorsGrise | AF69: 1 | AG69: 1 | AH69: 0 | AI69: 0 | AJ69: 1 | AK69: Mangold | AL69: 0.38392857 | AM69: Shively
B70: 17 | C70: 1 | D70: 2 | E70: FBC2-S-Ferrin-Flanders | F70: Sunday | G70: 41798 | H70: AM | I70: Verona, NY (Turning Stone) | J70: Northeast | K70: 18 | L70: Full | M70: Kaluhyat | N70: White | O70: 70.9 | P70: 132 | Q70: 6183 | R70: Match Play | S70: Singles | T70: Over 6' | U70: Connolly | V70: Flanders | W70: White | X70: 5 | AA70: 2 | AB70: L | AC70: 6 & 4 | AD70: Ferrin | AE70: =$V70&$Y70 -> Flanders | AF70: 0 | AG70: 0 | AH70: 1 | AI70: 0 | AJ70: 0 | AK70: Ferrin | AL70: 0.5952381
B71: 18 | C71: 2 | D71: 2 | E71: FBC2-S-Connors-Fogan | F71: Sunday | G71: 41798 | H71: AM | I71: Verona, NY (Turning Stone) | J71: Northeast | K71: 18 | L71: Full | M71: Kaluhyat | N71: White | O71: 70.9 | P71: 132 | Q71: 6183 | R71: Match Play | S71: Singles | T71: Over 6' | U71: Connolly | V71: Connors | W71: White | X71: 8 | AA71: 2 | AB71: L | AC71: 7 & 5 | AD71: Fogan | AE71: =$V71&$Y71 -> Connors | AF71: 0 | AG71: 0 | AH71: 1 | AI71: 0 | AJ71: 0 | AK71: Fogan | AL71: 0.37288136
B72: 18 | C72: 3 | D72: 2 | E72: FBC2-S-Connolly-Shively | F72: Sunday | G72: 41798 | H72: AM | I72: Verona, NY (Turning Stone) | J72: Northeast | K72: 18 | L72: Full | M72: Kaluhyat | N72: White | O72: 70.9 | P72: 132 | Q72: 6183 | R72: Match Play | S72: Singles | T72: Over 6' | U72: Connolly | V72: Connolly | W72: White | X72: 0 | AA72: 2 | AB72: L | AC72: 1 UP | AD72: Shively | AE72: =$V72&$Y72 -> Connolly | AF72: 0 | AG72: 0 | AH72: 1 | AI72: 0 | AJ72: 0 | AK72: Shively
B73: 18 | C73: 4 | D73: 2 | E73: FBC2-S-Cole-Grise | F73: Sunday | G73: 41798 | H73: AM | I73: Verona, NY (Turning Stone) | J73: Northeast | K73: 18 | L73: Full | M73: Kaluhyat | N73: White | O73: 70.9 | P73: 132 | Q73: 6183 | R73: Match Play | S73: Singles | T73: Over 6' | U73: Connolly | V73: Grise | W73: White | X73: 2 | AA73: 2 | AB73: W | AC73: 8 & 6 | AD73: Cole | AE73: =$V73&$Y73 -> Grise | AF73: 2 | AG73: 1 | AH73: 0 | AI73: 0 | AJ73: 1 | AK73: Cole | AL73: 0.44067797
B74: 19 | C74: 5 | D74: 2 | E74: FBC2-S-Lynch-Weisberger | F74: Sunday | G74: 41798 | H74: AM | I74: Verona, NY (Turning Stone) | J74: Northeast | K74: 18 | L74: Full | M74: Kaluhyat | N74: White | O74: 70.9 | P74: 132 | Q74: 6183 | R74: Match Play | S74: Singles | T74: Over 6' | U74: Connolly | V74: Lynch | W74: White | X74: 8 | AA74: 2 | AB74: L | AC74: 5 & 3 | AD74: Weisberger | AE74: =$V74&$Y74 -> Lynch | AF74: 0 | AG74: 0 | AH74: 1 | AI74: 0 | AJ74: 0 | AK74: Weisberger | AL74: 0.5
B75: 19 | C75: 6 | D75: 2 | E75: FBC2-S-Forster-Hickerson | F75: Sunday | G75: 41798 | H75: AM | I75: Verona, NY (Turning Stone) | J75: Northeast | K75: 18 | L75: Full | M75: Kaluhyat | N75: White | O75: 70.9 | P75: 132 | Q75: 6183 | R75: Match Play | S75: Singles | T75: Over 6' | U75: Connolly | V75: Forster | W75: White | X75: 21 | AA75: 2 | AB75: W | AC75: 1UP | AD75: Hickerson | AE75: =$V75&$Y75 -> Forster | AF75: 2 | AG75: 1 | AH75: 0 | AI75: 0 | AJ75: 1 | AK75: Hickerson | AL75: 0.35714286
B76: 20 | C76: 7 | D76: 2 | E76: FBC2-S-Bussiculo-Jackson | F76: Sunday | G76: 41798 | H76: AM | I76: Verona, NY (Turning Stone) | J76: Northeast | K76: 18 | L76: Full | M76: Kaluhyat | N76: White | O76: 70.9 | P76: 132 | Q76: 6183 | R76: Match Play | S76: Singles | T76: Over 6' | U76: Connolly | V76: Jackson | W76: White | X76: 0 | AA76: 2 | AB76: W | AC76: 5 & 3 | AD76: Bussiculo | AE76: =$V76&$Y76 -> Jackson | AF76: 2 | AG76: 1 | AH76: 0 | AI76: 0 | AJ76: 1 | AK76: Bussiculo | AL76: 0.44827586
B77: 20 | C77: 8 | D77: 2 | E77: FBC2-S-Hilts-Mangold | F77: Sunday | G77: 41798 | H77: AM | I77: Verona, NY (Turning Stone) | J77: Northeast | K77: 18 | L77: Full | M77: Kaluhyat | N77: White | O77: 70.9 | P77: 132 | Q77: 6183 | R77: Match Play | S77: Singles | T77: Over 6' | U77: Connolly | V77: Hilts | W77: White | X77: 7 | AA77: 2 | AB77: L | AC77: 2 & 1 | AD77: Mangold | AE77: =$V77&$Y77 -> Hilts | AF77: 0 | AG77: 0 | AH77: 1 | AI77: 0 | AJ77: 0 | AK77: Mangold | AL77: 0.38392857
B78: 21 | C78: 1 | D78: 2 | E78: FBC2-S-Ferrin-Flanders | F78: Sunday | G78: 41798 | H78: AM | I78: Verona, NY (Turning Stone) | J78: Northeast | K78: 18 | L78: Full | M78: Kaluhyat | N78: White | O78: 70.9 | P78: 132 | Q78: 6183 | R78: Match Play | S78: Singles | T78: Over 6' | U78: Ferrin | V78: Ferrin | W78: Blue | X78: 12 | AA78: 2 | AB78: W | AC78: 6 & 4 | AD78: Flanders | AE78: =$V78&$Y78 -> Ferrin | AF78: 2 | AG78: 1 | AH78: 0 | AI78: 0 | AJ78: 1 | AK78: Flanders | AL78: 0.4296875
B79: 21 | C79: 2 | D79: 2 | E79: FBC2-S-Connors-Fogan | F79: Sunday | G79: 41798 | H79: AM | I79: Verona, NY (Turning Stone) | J79: Northeast | K79: 18 | L79: Full | M79: Kaluhyat | N79: White | O79: 70.9 | P79: 132 | Q79: 6183 | R79: Match Play | S79: Singles | T79: Over 6' | U79: Ferrin | V79: Fogan | W79: Blue | X79: 22 | AA79: 2 | AB79: W | AC79: 7 & 5 | AD79: Connors | AE79: =$V79&$Y79 -> Fogan | AF79: 2 | AG79: 1 | AH79: 0 | AI79: 0 | AJ79: 1 | AK79: Connors | AL79: 0.34745763
B80: 22 | C80: 3 | D80: 2 | E80: FBC2-S-Connolly-Shively | F80: Sunday | G80: 41798 | H80: AM | I80: Verona, NY (Turning Stone) | J80: Northeast | K80: 18 | L80: Full | M80: Kaluhyat | N80: White | O80: 70.9 | P80: 132 | Q80: 6183 | R80: Match Play | S80: Singles | T80: Over 6' | U80: Ferrin | V80: Shively | W80: Blue | X80: 11 | AA80: 2 | AB80: W | AC80: 1 UP | AD80: Connolly | AE80: =$V80&$Y80 -> Shively | AF80: 2 | AG80: 1 | AH80: 0 | AI80: 0 | AJ80: 1 | AK80: Connolly | AL80: 0.59375
B81: 22 | C81: 4 | D81: 2 | E81: FBC2-S-Cole-Grise | F81: Sunday | G81: 41798 | H81: AM | I81: Verona, NY (Turning Stone) | J81: Northeast | K81: 18 | L81: Full | M81: Kaluhyat | N81: White | O81: 70.9 | P81: 132 | Q81: 6183 | R81: Match Play | S81: Singles | T81: Over 6' | U81: Ferrin | V81: Cole | W81: Blue | X81: 24 | AA81: 2 | AB81: L | AC81: 8 & 6 | AD81: Grise | AE81: =$V81&$Y81 -> Cole | AF81: 0 | AG81: 0 | AH81: 1 | AI81: 0 | AJ81: 0 | AK81: Grise | AL81: 0.546875
B82: 23 | C82: 5 | D82: 2 | E82: FBC2-S-Lynch-Weisberger | F82: Sunday | G82: 41798 | H82: AM | I82: Verona, NY (Turning Stone) | J82: Northeast | K82: 18 | L82: Full | M82: Kaluhyat | N82: White | O82: 70.9 | P82: 132 | Q82: 6183 | R82: Match Play | S82: Singles | T82: Over 6' | U82: Ferrin | V82: Weisberger | W82: Blue | X82: 5 | AA82: 2 | AB82: W | AC82: 5 & 3 | AD82: Lynch | AE82: =$V82&$Y82 -> Weisberger | AF82: 2 | AG82: 1 | AH82: 0 | AI82: 0 | AJ82: 1 | AK82: Lynch | AL82: 0.5546875
B83: 23 | C83: 6 | D83: 2 | E83: FBC2-S-Forster-Hickerson | F83: Sunday | G83: 41798 | H83: AM | I83: Verona, NY (Turning Stone) | J83: Northeast | K83: 18 | L83: Full | M83: Kaluhyat | N83: White | O83: 70.9 | P83: 132 | Q83: 6183 | R83: Match Play | S83: Singles | T83: Over 6' | U83: Ferrin | V83: Hickerson | W83: Blue | X83: 8 | AA83: 2 | AB83: L | AC83: 1UP | AD83: Forster | AE83: =$V83&$Y83 -> Hickerson | AF83: 0 | AG83: 0 | AH83: 1 | AI83: 0 | AJ83: 0 | AK83: Forster | AL83: 0.59649123
B84: 24 | C84: 7 | D84: 2 | E84: FBC2-S-Bussiculo-Jackson | F84: Sunday | G84: 41798 | H84: AM | I84: Verona, NY (Turning Stone) | J84: Northeast | K84: 18 | L84: Full | M84: Kaluhyat | N84: White | O84: 70.9 | P84: 132 | Q84: 6183 | R84: Match Play | S84: Singles | T84: Over 6' | U84: Ferrin | V84: Bussiculo | W84: Blue | X84: 0 | AA84: 2 | AB84: L | AC84: 5 & 3 | AD84: Jackson | AE84: =$V84&$Y84 -> Bussiculo | AF84: 0 | AG84: 0 | AH84: 1 | AI84: 0 | AJ84: 0 | AK84: Jackson | AL84: 0.6171875
B85: 24 | C85: 8 | D85: 2 | E85: FBC2-S-Hilts-Mangold | F85: Sunday | G85: 41798 | H85: AM | I85: Verona, NY (Turning Stone) | J85: Northeast | K85: 18 | L85: Full | M85: Kaluhyat | N85: White | O85: 70.9 | P85: 132 | Q85: 6183 | R85: Match Play | S85: Singles | T85: Over 6' | U85: Ferrin | V85: Mangold | W85: Blue | X85: 4 | AA85: 2 | AB85: W | AC85: 2 & 1 | AD85: Hilts | AE85: =$V85&$Y85 -> Mangold | AF85: 2 | AG85: 1 | AH85: 0 | AI85: 0 | AJ85: 1 | AK85: Hilts | AL85: 0.47321429
B86: 1 | C86: 1 | D86: 3 | E86: FBC3-D1 | F86: Saturday | G86: 42168 | H86: AM | I86: Sea Island, GA | J86: South | K86: 9 | L86: Front | M86: Seaside | N86: Green | O86: 71.1 | P86: 135 | Q86: 6323 | R86: Best Ball | S86: Doubles | T86: Under 6' | U86: Shively | V86: Ferrin | W86: Steel | X86: 24 | Y86: Shively | Z86: 21 | AA86: 1 | AB86: W | AC86: 4&3 | AE86: =$V86&$Y86 -> FerrinShively | AF86: 1 | AG86: 1 | AH86: 0 | AI86: 0 | AJ86: 1 | AK86: Connolly | AL86: 0.59375 | AM86: Hilts | AN86: 0.47321429
B87: 1 | C87: 1 | D87: 3 | E87: FBC3-D1 | F87: Saturday | G87: 42168 | H87: AM | I87: Sea Island, GA | J87: South | K87: 9 | L87: Front | M87: Seaside | N87: Green | O87: 71.1 | P87: 135 | Q87: 6323 | R87: Best Ball | S87: Doubles | T87: Over 6' | U87: Lynch | V87: Connolly | W87: Green | X87: 10.79115 | Y87: Hilts | Z87: 21.226549 | AA87: 1 | AB87: L | AC87: 4&3 | AE87: =$V87&$Y87 -> ConnollyHilts | AF87: 0 | AG87: 0 | AH87: 1 | AI87: 0 | AJ87: 0 | AK87: Ferrin | AL87: 0.5952381 | AM87: Shively
B88: 2 | C88: 2 | D88: 3 | E88: FBC3-D2 | F88: Saturday | G88: 42168 | H88: AM | I88: Sea Island, GA | J88: South | K88: 9 | L88: Front | M88: Seaside | N88: Green | O88: 71.1 | P88: 135 | Q88: 6323 | R88: Best Ball | S88: Doubles | T88: Over 6' | U88: Lynch | V88: Fogan | W88: Green | X88: 29.646018 | Y88: Weisberger | Z88: 18.736283 | AA88: 1 | AB88: W | AC88: 4&3 | AE88: =$V88&$Y88 -> FoganWeisberger | AF88: 1 | AG88: 1 | AH88: 0 | AI88: 0 | AJ88: 1 | AK88: Grise | AL88: 0.546875 | AM88: Jackson | AN88: 0.6171875
B89: 2 | C89: 2 | D89: 3 | E89: FBC3-D2 | F89: Saturday | G89: 42168 | H89: AM | I89: Sea Island, GA | J89: South | K89: 9 | L89: Front | M89: Seaside | N89: Green | O89: 71.1 | P89: 135 | Q89: 6323 | R89: Best Ball | S89: Doubles | T89: Under 6' | U89: Shively | V89: Grise | W89: Steel | X89: 17 | Y89: Jackson | Z89: 15 | AA89: 1 | AB89: L | AC89: 4&3 | AE89: =$V89&$Y89 -> GriseJackson | AF89: 0 | AG89: 0 | AH89: 1 | AI89: 0 | AJ89: 0 | AK89: Fogan | AL89: 0.37288136 | AM89: Weisberger | AN89: 0.5
B90: 3 | C90: 3 | D90: 3 | E90: FBC3-D3 | F90: Saturday | G90: 42168 | H90: AM | I90: Sea Island, GA | J90: South | K90: 9 | L90: Front | M90: Seaside | N90: Green | O90: 71.1 | P90: 135 | Q90: 6323 | R90: Best Ball | S90: Doubles | T90: Under 6' | U90: Shively | V90: Flanders | W90: Steel | X90: 15.890265 | Y90: Forster | Z90: 29.646018 | AA90: 1 | AB90: L | AC90: 2&1 | AE90: =$V90&$Y90 -> FlandersForster | AF90: 0 | AG90: 0 | AH90: 1 | AI90: 0 | AJ90: 0 | AK90: Gray | AL90: 0.6547619 | AM90: Zimmer | AN90: 0.5
B91: 3 | C91: 3 | D91: 3 | E91: FBC3-D3 | F91: Saturday | G91: 42168 | H91: AM | I91: Sea Island, GA | J91: South | K91: 9 | L91: Front | M91: Seaside | N91: Green | O91: 71.1 | P91: 135 | Q91: 6323 | R91: Best Ball | S91: Doubles | T91: Over 6' | U91: Lynch | V91: Gray | W91: Green | X91: 13.044248 | Y91: Zimmer | Z91: 16.957522 | AA91: 1 | AB91: W | AC91: 2&1 | AE91: =$V91&$Y91 -> GrayZimmer | AF91: 1 | AG91: 1 | AH91: 0 | AI91: 0 | AJ91: 1 | AK91: Flanders | AL91: 0.4296875 | AM91: Forster | AN91: 0.59649123
B92: 4 | C92: 4 | D92: 3 | E92: FBC3-D4 | F92: Saturday | G92: 42168 | H92: AM | I92: Sea Island, GA | J92: South | K92: 9 | L92: Front | M92: Seaside | N92: Green | O92: 71.1 | P92: 135 | Q92: 6323 | R92: Best Ball | S92: Doubles | T92: Over 6' | U92: Lynch | V92: Hickerson | W92: Green | X92: 22.293805 | Y92: Lynch | Z92: 18.973451 | AA92: 1 | AB92: W | AC92: 2&1 | AE92: =$V92&$Y92 -> HickersonLynch | AF92: 1 | AG92: 1 | AH92: 0 | AI92: 0 | AJ92: 1 | AK92: Bussiculo | AL92: 0.44827586 | AM92: Mangold | AN92: 0.38392857
B93: 4 | C93: 4 | D93: 3 | E93: FBC3-D4 | F93: Saturday | G93: 42168 | H93: AM | I93: Sea Island, GA | J93: South | K93: 9 | L93: Front | M93: Seaside | N93: Green | O93: 71.1 | P93: 135 | Q93: 6323 | R93: Best Ball | S93: Doubles | T93: Under 6' | U93: Shively | V93: Bussiculo | W93: Steel | X93: 16 | Y93: Mangold | Z93: 19 | AA93: 1 | AB93: L | AC93: 2&1 | AE93: =$V93&$Y93 -> BussiculoMangold | AF93: 0 | AG93: 0 | AH93: 1 | AI93: 0 | AJ93: 0 | AK93: Hickerson | AL93: 0.35714286 | AM93: Lynch | AN93: 0.5546875
B94: 5 | C94: 5 | D94: 3 | E94: FBC3-D5 | F94: Saturday | G94: 42168 | H94: AM | I94: Sea Island, GA | J94: South | K94: 9 | L94: Front | M94: Seaside | N94: Green | O94: 71.1 | P94: 135 | Q94: 6323 | R94: Best Ball | S94: Doubles | T94: Under 6' | U94: Shively | V94: Connors | W94: Steel | X94: 19.80354 | Y94: Norat | Z94: 22.175221 | AA94: 1 | AB94: L | AC94: 2&1 | AE94: =$V94&$Y94 -> ConnorsNorat | AF94: 0 | AG94: 0 | AH94: 1 | AI94: 0 | AJ94: 0 | AK94: Cole | AL94: 0.44067797 | AM94: McInerney | AN94: 0.5
B95: 5 | C95: 5 | D95: 3 | E95: FBC3-D5 | F95: Saturday | G95: 42168 | H95: AM | I95: Sea Island, GA | J95: South | K95: 9 | L95: Front | M95: Seaside | N95: Green | O95: 71.1 | P95: 135 | Q95: 6323 | R95: Best Ball | S95: Doubles | T95: Over 6' | U95: Lynch | V95: Cole | W95: Green | X95: 29.40885 | Y95: McInerney | Z95: 11.265487 | AA95: 1 | AB95: W | AC95: 2&1 | AE95: =$V95&$Y95 -> ColeMcInerney | AF95: 1 | AG95: 1 | AH95: 0 | AI95: 0 | AJ95: 1 | AK95: Connors | AL95: 0.34745763 | AM95: Norat | AN95: 0.52777778
B96: 6 | C96: 1 | D96: 3 | E96: FBC3-D6 | F96: Saturday | G96: 42168 | H96: AM | I96: Sea Island, GA | J96: South | K96: 9 | L96: Back | M96: Seaside | N96: Green | O96: 71.1 | P96: 135 | Q96: 6323 | R96: Hi-Lo | S96: Doubles | T96: Under 6' | U96: Shively | V96: Ferrin | W96: Steel | X96: 24 | Y96: Shively | Z96: 21 | AA96: 1 | AB96: L | AC96: 4UP | AE96: =$V96&$Y96 -> FerrinShively | AF96: 0 | AG96: 0 | AH96: 1 | AI96: 0 | AJ96: 0 | AK96: Connolly | AL96: 0.59375 | AM96: Hilts | AN96: 0.47321429
B97: 6 | C97: 1 | D97: 3 | E97: FBC3-D6 | F97: Saturday | G97: 42168 | H97: AM | I97: Sea Island, GA | J97: South | K97: 9 | L97: Back | M97: Seaside | N97: Green | O97: 71.1 | P97: 135 | Q97: 6323 | R97: Hi-Lo | S97: Doubles | T97: Over 6' | U97: Lynch | V97: Connolly | W97: Green | X97: 10.79115 | Y97: Hilts | Z97: 21.226549 | AA97: 1 | AB97: W | AC97: 4UP | AE97: =$V97&$Y97 -> ConnollyHilts | AF97: 1 | AG97: 1 | AH97: 0 | AI97: 0 | AJ97: 1 | AK97: Ferrin | AL97: 0.5952381 | AM97: Shively
B98: 7 | C98: 2 | D98: 3 | E98: FBC3-D7 | F98: Saturday | G98: 42168 | H98: AM | I98: Sea Island, GA | J98: South | K98: 9 | L98: Back | M98: Seaside | N98: Green | O98: 71.1 | P98: 135 | Q98: 6323 | R98: Hi-Lo | S98: Doubles | T98: Over 6' | U98: Lynch | V98: Fogan | W98: Green | X98: 29.646018 | Y98: Weisberger | Z98: 18.736283 | AA98: 1 | AB98: L | AC98: 3UP | AE98: =$V98&$Y98 -> FoganWeisberger | AF98: 0 | AG98: 0 | AH98: 1 | AI98: 0 | AJ98: 0 | AK98: Grise | AL98: 0.546875 | AM98: Jackson | AN98: 0.6171875
B99: 7 | C99: 2 | D99: 3 | E99: FBC3-D7 | F99: Saturday | G99: 42168 | H99: AM | I99: Sea Island, GA | J99: South | K99: 9 | L99: Back | M99: Seaside | N99: Green | O99: 71.1 | P99: 135 | Q99: 6323 | R99: Hi-Lo | S99: Doubles | T99: Under 6' | U99: Shively | V99: Grise | W99: Steel | X99: 17 | Y99: Jackson | Z99: 15 | AA99: 1 | AB99: W | AC99: 3UP | AE99: =$V99&$Y99 -> GriseJackson | AF99: 1 | AG99: 1 | AH99: 0 | AI99: 0 | AJ99: 1 | AK99: Fogan | AL99: 0.37288136 | AM99: Weisberger | AN99: 0.5
B100: 8 | C100: 3 | D100: 3 | E100: FBC3-D8 | F100: Saturday | G100: 42168 | H100: AM | I100: Sea Island, GA | J100: South | K100: 9 | L100: Back | M100: Seaside | N100: Green | O100: 71.1 | P100: 135 | Q100: 6323 | R100: Hi-Lo | S100: Doubles | T100: Under 6' | U100: Shively | V100: Flanders | W100: Steel | X100: 15.890265 | Y100: Forster | Z100: 29.646018 | AA100: 1 | AB100: L | AC100: 1UP | AE100: =$V100&$Y100 -> FlandersForster | AF100: 0 | AG100: 0 | AH100: 1 | AI100: 0 | AJ100: 0 | AK100: Gray | AL100: 0.6547619 | AM100: Zimmer | AN100: 0.5
...

Sheet Cups
B2: Player | C2: FBC 1 | D2: FBC 2 | E2: FBC 3 | F2: FBC 4 | G2: FBC 5 | H2: FBC 6 | I2: FBC 7 | J2: FBC 8 | K2: FBC 9 | L2: FBC 10 | M2: FBC 11 | N2: FBC 12 | O2: FBC 13 | P2: Total | Q2: Played | R2: % | S2: Lost
B3: Lynch | C3: 1 | D3: 1 | E3: 1 | F3: 1 | G3: 1 | H3: 1 | I3: 1 | J3: 0 | K3: 1 | L3: 1 | M3: 0 | N3: 1 | O3: 0 | P3: =SUM(C3:O3) -> 10 | Q3: 13 | R3: =P3/Q3 -> 0.76923077 | S3: =Q3-P3 -> 3
B4: Connolly | C4: 1 | D4: 1 | E4: 1 | F4: 1 | G4: 1 | H4: 0 | I4: 0 | J4: 1 | K4: 1 | L4: 1 | M4: 1 | N4: 0 | O4: 1 | P4: =SUM(C4:O4) -> 10 | Q4: 13 | R4: =P4/Q4 -> 0.76923077 | S4: =Q4-P4 -> 3
B5: Grise | C5: 0 | D5: 1 | E5: 0 | F5: 1 | G5: 1 | H5: 1 | I5: 1 | J5: 1 | K5: 0 | L5: 1 | M5: 0 | N5: 1 | O5: 1 | P5: =SUM(C5:O5) -> 9 | Q5: 13 | R5: =P5/Q5 -> 0.69230769 | S5: =Q5-P5 -> 4
B6: Hilts | C6: 1 | D6: 1 | E6: 1 | F6: X | G6: 0 | H6: 1 | I6: 0 | J6: 1 | K6: 1 | L6: 1 | M6: 0 | N6: 1 | O6: 1 | P6: =SUM(C6:O6) -> 9 | Q6: 12 | R6: =P6/Q6 -> 0.75 | S6: =Q6-P6 -> 3
B7: Shively | C7: 1 | D7: 0 | E7: 0 | F7: 1 | G7: 1 | H7: 1 | I7: 0 | J7: 0 | K7: 1 | L7: X | M7: 1 | N7: 1 | O7: 0 | P7: =SUM(C7:O7) -> 7 | Q7: 12 | R7: =P7/Q7 -> 0.58333333 | S7: =Q7-P7 -> 5
B8: Zimmer | C8: X | D8: X | E8: 1 | F8: 1 | G8: 1 | H8: 0 | I8: 1 | J8: 1 | K8: 0 | L8: 0 | M8: 1 | N8: 0 | O8: 1 | P8: =SUM(C8:O8) -> 7 | Q8: 11 | R8: =P8/Q8 -> 0.63636364 | S8: =Q8-P8 -> 4
B9: McInerney | C9: X | D9: X | E9: 1 | F9: 1 | G9: 1 | H9: 1 | I9: 0 | J9: 0 | K9: 1 | L9: 0 | M9: X | N9: X | O9: 0 | P9: =SUM(C9:O9) -> 5 | Q9: 9 | R9: =P9/Q9 -> 0.55555556 | S9: =Q9-P9 -> 4
B10: Flanders | C10: 0 | D10: 1 | E10: 0 | F10: 0 | G10: 0 | H10: 0 | I10: 1 | J10: 0 | K10: 1 | L10: 1 | M10: 0 | N10: 1 | O10: 1 | P10: =SUM(C10:O10) -> 6 | Q10: 13 | R10: =P10/Q10 -> 0.46153846 | S10: =Q10-P10 -> 7
B11: Fogan | C11: X | D11: 0 | E11: 1 | F11: 1 | G11: 0 | H11: 1 | I11: 0 | J11: 0 | K11: 0 | L11: 0 | M11: 1 | N11: 0 | O11: 0 | P11: =SUM(C11:O11) -> 4 | Q11: 12 | R11: =P11/Q11 -> 0.33333333 | S11: =Q11-P11 -> 8
B12: Connors | C12: X | D12: 1 | E12: 0 | F12: 0 | G12: 0 | H12: 0 | I12: 1 | J12: 1 | K12: 1 | L12: 0 | M12: 0 | N12: X | O12: X | P12: =SUM(C12:O12) -> 4 | Q12: 10 | R12: =P12/Q12 -> 0.4 | S12: =Q12-P12 -> 6
B13: Cole | C13: X | D13: 0 | E13: 1 | F13: 0 | G13: 0 | H13: 0 | I13: 1 | J13: 0 | K13: 1 | L13: 1 | M13: 0 | N13: X | O13: 1 | P13: =SUM(C13:O13) -> 5 | Q13: 11 | R13: =P13/Q13 -> 0.45454545 | S13: =Q13-P13 -> 6
B14: Delaney | C14: X | D14: X | E14: X | F14: X | G14: 1 | H14: X | I14: X | J14: 1 | K14: 1 | L14: 1 | M14: 0 | N14: 0 | O14: 1 | P14: =SUM(C14:O14) -> 5 | Q14: 7 | R14: =P14/Q14 -> 0.71428571 | S14: =Q14-P14 -> 2
B15: Gray | C15: X | D15: X | E15: 1 | F15: 0 | G15: 0 | H15: 1 | I15: 1 | J15: X | K15: X | L15: 0 | M15: 1 | N15: X | O15: 0 | P15: =SUM(C15:O15) -> 4 | Q15: 8 | R15: =P15/Q15 -> 0.5 | S15: =Q15-P15 -> 4
B16: Ferrin | C16: 0 | D16: 0 | E16: 0 | F16: 0 | G16: 0 | H16: 0 | I16: 1 | J16: 1 | K16: 0 | L16: 1 | M16: 1 | N16: 0 | O16: 0 | P16: =SUM(C16:O16) -> 4 | Q16: 13 | R16: =P16/Q16 -> 0.30769231 | S16: =Q16-P16 -> 9
B17: Perkins | C17: X | D17: X | E17: X | F17: X | G17: X | H17: X | I17: X | J17: 1 | K17: 1 | L17: 1 | M17: X | N17: 1 | O17: 0 | P17: =SUM(C17:O17) -> 4 | Q17: 5 | R17: =P17/Q17 -> 0.8 | S17: =Q17-P17 -> 1
B18: Forster | C18: X | D18: 1 | E18: 0 | F18: 0 | G18: 1 | H18: 0 | I18: 0 | J18: 0 | K18: 0 | L18: 0 | M18: 1 | N18: 1 | O18: 1 | P18: =SUM(C18:O18) -> 5 | Q18: 12 | R18: =P18/Q18 -> 0.41666667 | S18: =Q18-P18 -> 7
B19: Bussiculo | C19: X | D19: 0 | E19: 0 | F19: 1 | G19: 0 | H19: 1 | I19: 1 | J19: X | K19: X | L19: X | M19: X | N19: X | O19: X | P19: =SUM(C19:O19) -> 3 | Q19: 6 | R19: =P19/Q19 -> 0.5 | S19: =Q19-P19 -> 3
B20: Jackson | C20: 0 | D20: 1 | E20: 0 | F20: 0 | G20: 0 | H20: 1 | I20: 1 | J20: 0 | K20: 0 | L20: 0 | M20: 0 | N20: 0 | O20: 0 | P20: =SUM(C20:O20) -> 3 | Q20: 13 | R20: =P20/Q20 -> 0.23076923 | S20: =Q20-P20 -> 10
B21: Mangold | C21: 0 | D21: 0 | E21: 0 | F21: 0 | G21: 1 | H21: 1 | I21: 0 | J21: 0 | K21: X | L21: 0 | M21: 0 | N21: 1 | O21: 0 | P21: =SUM(C21:O21) -> 3 | Q21: 12 | R21: =P21/Q21 -> 0.25 | S21: =Q21-P21 -> 9
B22: Poirier | C22: 1 | D22: X | E22: X | F22: X | G22: 0 | H22: 0 | I22: 0 | J22: X | K22: 0 | L22: X | M22: 1 | N22: 1 | O22: 1 | P22: =SUM(C22:O22) -> 4 | Q22: 8 | R22: =P22/Q22 -> 0.5 | S22: =Q22-P22 -> 4
B23: Hickerson | C23: 0 | D23: 0 | E23: 1 | F23: 1 | G23: X | H23: X | I23: X | J23: X | K23: X | L23: X | M23: X | N23: X | O23: X | P23: =SUM(C23:O23) -> 2 | Q23: 4 | R23: =P23/Q23 -> 0.5 | S23: =Q23-P23 -> 2
B24: Welker | C24: X | D24: X | E24: X | F24: 1 | G24: 0 | H24: 0 | I24: 0 | J24: 1 | K24: 0 | L24: 0 | M24: 0 | N24: X | O24: 0 | P24: =SUM(C24:O24) -> 2 | Q24: 9 | R24: =P24/Q24 -> 0.22222222 | S24: =Q24-P24 -> 7
B25: Delneky | C25: X | D25: X | E25: X | F25: X | G25: X | H25: X | I25: X | J25: 1 | K25: 0 | L25: 0 | M25: 1 | N25: 0 | O25: 1 | P25: =SUM(C25:O25) -> 3 | Q25: 6 | R25: =P25/Q25 -> 0.5 | S25: =Q25-P25 -> 3
B26: Norat | C26: X | D26: 0 | E26: 0 | F26: 0 | G26: 1 | H26: 0 | I26: 0 | J26: X | K26: X | L26: X | M26: 1 | N26: X | O26: 1 | P26: =SUM(C26:O26) -> 3 | Q26: 8 | R26: =P26/Q26 -> 0.375 | S26: =Q26-P26 -> 5
B27: DeOteris | C27: X | D27: X | E27: X | F27: X | G27: X | H27: X | I27: X | J27: 1 | K27: 0 | L27: X | M27: X | N27: 0 | O27: 0 | P27: =SUM(C27:O27) -> 1 | Q27: 4 | R27: =P27/Q27 -> 0.25 | S27: =Q27-P27 -> 3
B28: Macklin | C28: 1 | D28: X | E28: X | F28: X | G28: X | H28: X | I28: X | J28: X | K28: X | L28: X | M28: X | N28: X | O28: X | P28: =SUM(C28:O28) -> 1 | Q28: 1 | R28: =P28/Q28 -> 1 | S28: =Q28-P28 -> 0
B29: Weisberger | C29: X | D29: 0 | E29: 1 | F29: 0 | G29: X | H29: X | I29: X | J29: X | K29: X | L29: X | M29: X | N29: X | O29: X | P29: =SUM(C29:O29) -> 1 | Q29: 2 | R29: =P29/Q29 -> 0.5 | S29: =Q29-P29 -> 1
B30: R. Connolly | C30: X | D30: X | E30: X | F30: X | G30: X | H30: X | I30: X | J30: X | K30: X | L30: 1 | M30: X | N30: 0 | O30: 1 | P30: =SUM(C30:O30) -> 2 | Q30: 3 | R30: =P30/Q30 -> 0.66666667 | S30: =Q30-P30 -> 1
B31: Snyder | C31: X | D31: X | E31: X | F31: X | G31: X | H31: X | I31: X | J31: X | K31: X | L31: X | M31: X | N31: 1 | O31: X | P31: =SUM(C31:O31) -> 1 | Q31: 1 | R31: =P31/Q31 -> 1 | S31: =Q31-P31 -> 0
B32: Piegari | C32: X | D32: X | E32: X | F32: X | G32: X | H32: X | I32: X | J32: 0 | K32: X | L32: X | M32: X | N32: 0 | O32: 0 | P32: =SUM(C32:O32) -> 0 | Q32: 3 | R32: =P32/Q32 -> 0 | S32: =Q32-P32 -> 3
B33: Ramsay | C33: X | D33: X | E33: X | F33: X | G33: X | H33: X | I33: X | J33: 0 | K33: X | L33: X | M33: X | N33: X | O33: X | P33: =SUM(C33:O33) -> 0 | Q33: 2 | R33: =P33/Q33 -> 0 | S33: =Q33-P33 -> 1
B34: Total | C34: =SUM(C3:C33) -> 6 | D34: =SUM(D3:D33) -> 8 | E34: =SUM(E3:E33) -> 10 | F34: =SUM(F3:F33) -> 10 | G34: =SUM(G3:G33) -> 10 | H34: =SUM(H3:H33) -> 10 | I34: =SUM(I3:I33) -> 10 | J34: =SUM(J3:J33) -> 11 | ... Q34: =SUM(Q3:Q33) -> 256 | S34: =SUM(S3:S33) -> 128
B37: Tab shows whether the players was on the winning team with a "1" meaning they were on the winning team, a "0" meaning they were on the losing team, and "X" meaning they did not participate

Sheet Handicaps
B1: FBC Handicap Index by Cup (master)
B2: Source: Handicaps & Points (Historical) FBC2–13; FBC1 from Archives. 'X' = did not play. Blank = no record.
B3: Player | C3: FBC1 | D3: FBC2 | E3: FBC3 | F3: FBC4 | G3: FBC5 | H3: FBC6 | I3: FBC7 | J3: FBC8 | K3: FBC9 | L3: FBC10 | M3: FBC11 | N3: FBC12 | O3: FBC13 | P3: Average
B4: Bussiculo
B5: Cole | D5: 32.4 | E5: 24.8 | F5: 22 | G5: 18.9 | H5: 20.2 | I5: 17.8 | J5: 15.5 | K5: 15.2 | L5: 16 | M5: 16.5 | N5: X | O5: 16.3 | P5: =IFERROR(AVERAGE(C5:O5),"") -> 19.6
B6: Connolly | C6: 15 | D6: 12.4 | E6: 9.1 | F6: 10.1 | G6: 11.1 | H6: 10.5 | I6: 10.5 | J6: 10.8 | K6: 8.3 | L6: 10.1 | M6: 9.5 | N6: 9.4 | O6: 9.3 | P6: =IFERROR(AVERAGE(C6:O6),"") -> 10.469231
B7: Connors | D7: 18.8 | E7: 16.7 | F7: 16.2 | G7: 15.5 | H7: 15.4 | I7: 16.4 | J7: 17.1 | K7: 18.3 | L7: 17.6 | M7: 17.6 | N7: X | O7: X | P7: =IFERROR(AVERAGE(C7:O7),"") -> 16.96
B8: Delaney | D8: X | E8: X | F8: X | G8: 14.2 | H8: X | I8: X | J8: 11.7 | K8: 10.7 | L8: 11.7 | M8: 9.5 | N8: 11.8 | O8: 14 | P8: =IFERROR(AVERAGE(C8:O8),"") -> 11.942857
B9: Delneky | D9: X | E9: X | F9: X | G9: X | H9: X | I9: X | J9: 17.2 | K9: 18.5 | L9: 18.4 | M9: 17.2 | N9: 17.8 | O9: 17.1 | P9: =IFERROR(AVERAGE(C9:O9),"") -> 17.7
B10: DeOteris | D10: X | E10: X | F10: X | G10: X | H10: X | I10: X | J10: 12.8 | K10: 12.5 | L10: X | M10: X | N10: 12.4 | O10: 11.3 | P10: =IFERROR(AVERAGE(C10:O10),"")
B11: Ferrin | C11: 28 | D11: 22.3 | E11: 19.9 | F11: 17.3 | G11: 15.2 | H11: 14.6 | I11: 14.8 | J11: 12.4 | K11: 13.5 | L11: 12.7 | M11: 10 | N11: 10.1 | O11: 9.8 | P11: =IFERROR(AVERAGE(C11:O11),"") -> 15.430769
B12: Flanders | C12: 15 | D12: 16.8 | E12: 13.4 | F12: 7.8 | G12: 4.6 | H12: 3.9 | I12: 4 | J12: 3.3 | K12: 6.3 | L12: 6.7 | M12: 6.8 | N12: 6.7 | O12: 10.7 | P12: =IFERROR(AVERAGE(C12:O12),"") -> 8.1538462
B13: Fogan | D13: 31.4 | E13: 25 | F13: 27.2 | G13: 26.2 | H13: 25.2 | I13: 23.5 | J13: 18.9 | K13: 19.2 | L13: 19.9 | M13: 18 | N13: 17.4 | O13: 16.6 | P13: =IFERROR(AVERAGE(C13:O13),"") -> 22.375
B14: Forster | D14: 30 | E14: 25 | F14: 22.4 | G14: 19.2 | H14: 15.8 | I14: 16.9 | J14: 15.1 | K14: 12 | L14: 12.7 | M14: 13.1 | N14: 10.9 | O14: 12.1 | P14: =IFERROR(AVERAGE(C14:O14),"") -> 17.1
B15: Gray | D15: X | E15: 11 | F15: 9.4 | G15: 6.8 | H15: 7.5 | I15: 7.3 | J15: X | K15: X | L15: 9 | M15: 8 | N15: X | O15: 8.8 | P15: =IFERROR(AVERAGE(C15:O15),"") -> 8.475
B16: Grise | C16: 15 | D16: 14.1 | E16: 14.7 | F16: 13.1 | G16: 11.8 | H16: 12.5 | I16: 11.9 | J16: 12 | K16: 11.7 | L16: 11.7 | M16: 10.9 | N16: 11.6 | O16: 10.4 | P16: =IFERROR(AVERAGE(C16:O16),"") -> 12.415385
B17: Hickerson | C17: 20 | P17: =IFERROR(AVERAGE(C17:O17),"") -> 20
B18: Hilts | C18: 18 | D18: 18.4 | E18: 17.9 | F18: X | G18: 18.5 | H18: 18.4 | I18: 19.6 | J18: 19.6 | K18: 19.1 | L18: 17.1 | M18: 16.4 | N18: 16 | O18: 16.5 | P18: =IFERROR(AVERAGE(C18:O18),"") -> 17.958333
B19: Jackson | C19: 15 | D19: 12.8 | E19: 12.3 | F19: 12.5 | G19: 12.7 | H19: 12.5 | I19: 11.3 | J19: 9.1 | K19: 8.8 | L19: 8.7 | M19: 9.4 | N19: 7.4 | O19: 8.4 | P19: =IFERROR(AVERAGE(C19:O19),"") -> 10.838462
B20: Lynch | C20: 20 | D20: 18.8 | E20: 16 | F20: 13.9 | G20: 11.8 | H20: 14.4 | I20: 13.4 | J20: 8.9 | K20: 9.3 | L20: 8.7 | M20: 7.9 | N20: 8.9 | O20: 8.5 | P20: =IFERROR(AVERAGE(C20:O20),"") -> 12.346154
B21: Macklin | C21: 15 | P21: =IFERROR(AVERAGE(C21:O21),"") -> 15
B22: Mangold | C22: 15 | D22: 15.7 | E22: 16.4 | F22: 15.9 | G22: 14.3 | H22: 14 | I22: 15.4 | J22: 14.5 | K22: X | L22: 15.9 | M22: 16.2 | N22: 14.7 | O22: 15.2 | P22: =IFERROR(AVERAGE(C22:O22),"") -> 15.266667
B23: McInerney | D23: X | E23: 9.5 | F23: 8.7 | G23: 7.5 | H23: 8.6 | I23: 8.3 | J23: 4.2 | K23: 5.3 | L23: 5.7 | M23: X | N23: X | O23: 4.1 | P23: =IFERROR(AVERAGE(C23:O23),"") -> 6.8777778
B24: Norat | D24: X | E24: 18.7 | F24: 18.2 | G24: 18.6 | H24: 18.9 | I24: 15 | J24: X | K24: X | L24: X | M24: 18 | N24: X | O24: 16.85 | P24: =IFERROR(AVERAGE(C24:O24),"") -> 17.75
B25: Perkins | D25: X | E25: X | F25: X | G25: X | H25: X | I25: X | J25: 5.7 | K25: 8.8 | L25: 6.8 | M25: X | N25: 10.5 | O25: 7.9 | P25: =IFERROR(AVERAGE(C25:O25),"") -> 7.94
B26: Piegari | D26: X | E26: X | F26: X | G26: X | H26: X | I26: X | J26: 10.1 | K26: X | L26: X | M26: X | N26: 9 | O26: 9.9 | P26: =IFERROR(AVERAGE(C26:O26),"") -> 9.6666667
B27: Poirier | C27: 10 | D27: X | E27: X | F27: X | G27: 9.5 | H27: 7.5 | I27: 7.7 | J27: X | K27: 4.5 | L27: X | M27: 5.7 | N27: 4.3 | O27: 5.2 | P27: =IFERROR(AVERAGE(C27:O27),"") -> 6.8
B28: R. Connolly | D28: X | E28: X | F28: X | G28: X | H28: X | I28: X | J28: X | K28: X | L28: 14.6 | M28: X | N28: 12.1 | O28: 10.8 | P28: =IFERROR(AVERAGE(C28:O28),"") -> 12.5
B29: Ramsay
B30: Shively | C30: 30 | D30: 21.8 | E30: 17.7 | F30: 17.3 | G30: 16.5 | H30: 16.2 | I30: 14.6 | J30: 14.6 | K30: 14.4 | L30: X | M30: 12.9 | N30: 12.9 | O30: 13 | P30: =IFERROR(AVERAGE(C30:O30),"") -> 16.825
B31: Snyder
B32: Weisberger
B33: Welker | D33: X | E33: X | F33: 12.7 | G33: 13.6 | H33: 15 | I33: 13.6 | J33: 9 | K33: 9.3 | L33: 10 | M33: 9.5 | N33: X | O33: 13.5 | P33: =IFERROR(AVERAGE(C33:O33),"") -> 11.8
B34: Zimmer | D34: X | E34: 14.3 | F34: 13 | G34: 11.9 | H34: 11.1 | I34: 9.9 | J34: 10.2 | K34: 10.4 | L34: 8.9 | M34: 10.2 | N34: 8.6 | O34: 7.5 | P34: =IFERROR(AVERAGE(C34:O34),"") -> 10.545455

Sheet Points
B1: Points by Cup
B2: Live from Archives. FBC 13–15 columns are pre-built — they auto-populate when those cups are added to Archives.
B4: Player | C4: FBC 1 | D4: FBC 2 | E4: FBC 3 | F4: FBC 4 | G4: FBC 5 | H4: FBC 6 | I4: FBC 7 | J4: FBC 8 | K4: FBC 9 | L4: FBC 10 | M4: FBC 11 | N4: FBC 12 | O4: FBC 13 | P4: FBC 14 | Q4: FBC 15 | R4: Total
B5: Connolly | C5: =SUMIFS(Archives!$AF$2:$AF$1048576,Archives!$D$2:$D$1048576,1,Archives!$V$2:$V$1048576,$B5)+SUMIFS(Archives!$AF$2:$AF$1048576,Archives!$D$2:$D$1048576,1,Archives!$Y$2:$Y$1048576,$B5) -> 6 | D5: =SUMIFS(Archives!$AF$2:$AF$1048576,Archives!$D$2:$D$1048576,2,Archives!$V$2:$V$1048576,$B5)+SUMIFS(Archives!$AF$2:$AF$1048576,Archives!$D$2:$D$1048576,2,Archives!$Y$2:$Y$1048576,$B5) -> 3.5 | E5: =SUMIFS(Archives!$AF$2:$AF$1048576,Archives!$D$2:$D$1048576,3,Archives!$V$2:$V$1048576,$B5)+SUMIFS(Archives!$AF$2:$AF$1048576,Archives!$D$2:$D$1048576,3,Archives!$Y$2:$Y$1048576,$B5) -> 4.5 | F5: =SUMIFS(Archives!$AF$2:$AF$1048576,Archives!$D$2:$D$1048576,4,Archives!$V$2:$V$1048576,$B5)+SUMIFS(Archives!$AF$2:$AF$1048576,Archives!$D$2:$D$1048576,4,Archives!$Y$2:$Y$1048576,$B5) -> 3.5 | G5: =SUMIFS(Archives!$AF$2:$AF$1048576,Archives!$D$2:$D$1048576,5,Archives!$V$2:$V$1048576,$B5)+SUMIFS(Archives!$AF$2:$AF$1048576,Archives!$D$2:$D$1048576,5,Archives!$Y$2:$Y$1048576,$B5) -> 4 | H5: =SUMIFS(Archives!$AF$2:$AF$1048576,Archives!$D$2:$D$1048576,6,Archives!$V$2:$V$1048576,$B5)+SUMIFS(Archives!$AF$2:$AF$1048576,Archives!$D$2:$D$1048576,6,Archives!$Y$2:$Y$1048576,$B5) -> 2 | I5: =SUMIFS(Archives!$AF$2:$AF$1048576,Archives!$D$2:$D$1048576,7,Archives!$V$2:$V$1048576,$B5)+SUMIFS(Archives!$AF$2:$AF$1048576,Archives!$D$2:$D$1048576,7,Archives!$Y$2:$Y$1048576,$B5) -> 2 | J5: =SUMIFS(Archives!$AF$2:$AF$1048576,Archives!$D$2:$D$1048576,8,Archives!$V$2:$V$1048576,$B5)+SUMIFS(Archives!$AF$2:$AF$1048576,Archives!$D$2:$D$1048576,8,Archives!$Y$2:$Y$1048576,$B5) -> 4 | K5: =SUMIFS(Archives!$AF$2:$AF$1048576,Archives!$D$2:$D$1048576,9,Archives!$V$2:$V$1048576,$B5)+SUMIFS(Archives!$AF$2:$AF$1048576,Archives!$D$2:$D$1048576,9,Archives!$Y$2:$Y$1048576,$B5) -> 3.5 | L5: =SUMIFS(Archives!$AF$2:$AF$1048576,Archives!$D$2:$D$1048576,10,Archives!$V$2:$V$1048576,$B5)+SUMIFS(Archives!$AF$2:$AF$1048576,Archives!$D$2:$D$1048576,10,Archives!$Y$2:$Y$1048576,$B5) -> 6 | M5: =SUMIFS(Archives!$AF$2:$AF$1048576,Archives!$D$2:$D$1048576,11,Archives!$V$2:$V$1048576,$B5)+SUMIFS(Archives!$AF$2:$AF$1048576,Archives!$D$2:$D$1048576,11,Archives!$Y$2:$Y$1048576,$B5) -> 5 | N5: =SUMIFS(Archives!$AF$2:$AF$1048576,Archives!$D$2:$D$1048576,12,Archives!$V$2:$V$1048576,$B5)+SUMIFS(Archives!$AF$2:$AF$1048576,Archives!$D$2:$D$1048576,12,Archives!$Y$2:$Y$1048576,$B5) -> 6.5 | O5: =SUMIFS(Archives!$AF$2:$AF$1048576,Archives!$D$2:$D$1048576,13,Archives!$V$2:$V$1048576,$B5)+SUMIFS(Archives!$AF$2:$AF$1048576,Archives!$D$2:$D$1048576,13,Archives!$Y$2:$Y$1048576,$B5) -> 0 | P5: =SUMIFS(Archives!$AF$2:$AF$1048576,Archives!$D$2:$D$1048576,14,Archives!$V$2:$V$1048576,$B5)+SUMIFS(Archives!$AF$2:$AF$1048576,Archives!$D$2:$D$1048576,14,Archives!$Y$2:$Y$1048576,$B5) -> 0 | Q5: =SUMIFS(Archives!$AF$2:$AF$1048576,Archives!$D$2:$D$1048576,15,Archives!$V$2:$V$1048576,$B5)+SUMIFS(Archives!$AF$2:$AF$1048576,Archives!$D$2:$D$1048576,15,Archives!$Y$2:$Y$1048576,$B5) -> 0 | R5: =SUM(C5:Q5) -> 50.5
B6: Ferrin | C6: =SUMIFS(Archives!$AF$2:$AF$1048576,Archives!$D$2:$D$1048576,1,Archives!$V$2:$V$1048576,$B6)+SUMIFS(Archives!$AF$2:$AF$1048576,Archives!$D$2:$D$1048576,1,Archives!$Y$2:$Y$1048576,$B6) -> 5.5 | D6: =SUMIFS(Archives!$AF$2:$AF$1048576,Archives!$D$2:$D$1048576,2,Archives!$V$2:$V$1048576,$B6)+SUMIFS(Archives!$AF$2:$AF$1048576,Archives!$D$2:$D$1048576,2,Archives!$Y$2:$Y$1048576,$B6) -> 2.5 | E6: =SUMIFS(Archives!$AF$2:$AF$1048576,Archives!$D$2:$D$1048576,3,Archives!$V$2:$V$1048576,$B6)+SUMIFS(Archives!$AF$2:$AF$1048576,Archives!$D$2:$D$1048576,3,Archives!$Y$2:$Y$1048576,$B6) -> 5 | F6: =SUMIFS(Archives!$AF$2:$AF$1048576,Archives!$D$2:$D$1048576,4,Archives!$V$2:$V$1048576,$B6)+SUMIFS(Archives!$AF$2:$AF$1048576,Archives!$D$2:$D$1048576,4,Archives!$Y$2:$Y$1048576,$B6) -> 2.5 | G6: =SUMIFS(Archives!$AF$2:$AF$1048576,Archives!$D$2:$D$1048576,5,Archives!$V$2:$V$1048576,$B6)+SUMIFS(Archives!$AF$2:$AF$1048576,Archives!$D$2:$D$1048576,5,Archives!$Y$2:$Y$1048576,$B6) -> 4.5 | H6: =SUMIFS(Archives!$AF$2:$AF$1048576,Archives!$D$2:$D$1048576,6,Archives!$V$2:$V$1048576,$B6)+SUMIFS(Archives!$AF$2:$AF$1048576,Archives!$D$2:$D$1048576,6,Archives!$Y$2:$Y$1048576,$B6) -> 3 | I6: =SUMIFS(Archives!$AF$2:$AF$1048576,Archives!$D$2:$D$1048576,7,Archives!$V$2:$V$1048576,$B6)+SUMIFS(Archives!$AF$2:$AF$1048576,Archives!$D$2:$D$1048576,7,Archives!$Y$2:$Y$1048576,$B6) -> 4.5 | J6: =SUMIFS(Archives!$AF$2:$AF$1048576,Archives!$D$2:$D$1048576,8,Archives!$V$2:$V$1048576,$B6)+SUMIFS(Archives!$AF$2:$AF$1048576,Archives!$D$2:$D$1048576,8,Archives!$Y$2:$Y$1048576,$B6) -> 3.5 | K6: =SUMIFS(Archives!$AF$2:$AF$1048576,Archives!$D$2:$D$1048576,9,Archives!$V$2:$V$1048576,$B6)+SUMIFS(Archives!$AF$2:$AF$1048576,Archives!$D$2:$D$1048576,9,Archives!$Y$2:$Y$1048576,$B6) -> 2.5 | L6: =SUMIFS(Archives!$AF$2:$AF$1048576,Archives!$D$2:$D$1048576,10,Archives!$V$2:$V$1048576,$B6)+SUMIFS(Archives!$AF$2:$AF$1048576,Archives!$D$2:$D$1048576,10,Archives!$Y$2:$Y$1048576,$B6) -> 4 | M6: =SUMIFS(Archives!$AF$2:$AF$1048576,Archives!$D$2:$D$1048576,11,Archives!$V$2:$V$1048576,$B6)+SUMIFS(Archives!$AF$2:$AF$1048576,Archives!$D$2:$D$1048576,11,Archives!$Y$2:$Y$1048576,$B6) -> 5 | N6: =SUMIFS(Archives!$AF$2:$AF$1048576,Archives!$D$2:$D$1048576,12,Archives!$V$2:$V$1048576,$B6)+SUMIFS(Archives!$AF$2:$AF$1048576,Archives!$D$2:$D$1048576,12,Archives!$Y$2:$Y$1048576,$B6) -> 3.5 | O6: =SUMIFS(Archives!$AF$2:$AF$1048576,Archives!$D$2:$D$1048576,13,Archives!$V$2:$V$1048576,$B6)+SUMIFS(Archives!$AF$2:$AF$1048576,Archives!$D$2:$D$1048576,13,Archives!$Y$2:$Y$1048576,$B6) -> 0 | P6: =SUMIFS(Archives!$AF$2:$AF$1048576,Archives!$D$2:$D$1048576,14,Archives!$V$2:$V$1048576,$B6)+SUMIFS(Archives!$AF$2:$AF$1048576,Archives!$D$2:$D$1048576,14,Archives!$Y$2:$Y$1048576,$B6) -> 0 | Q6: =SUMIFS(Archives!$AF$2:$AF$1048576,Archives!$D$2:$D$1048576,15,Archives!$V$2:$V$1048576,$B6)+SUMIFS(Archives!$AF$2:$AF$1048576,Archives!$D$2:$D$1048576,15,Archives!$Y$2:$Y$1048576,$B6) -> 0 | R6: =SUM(C6:Q6) -> 46
B7: Jackson | C7: =SUMIFS(Archives!$AF$2:$AF$1048576,Archives!$D$2:$D$1048576,1,Archives!$V$2:$V$1048576,$B7)+SUMIFS(Archives!$AF$2:$AF$1048576,Archives!$D$2:$D$1048576,1,Archives!$Y$2:$Y$1048576,$B7) -> 3.5 | D7: =SUMIFS(Archives!$AF$2:$AF$1048576,Archives!$D$2:$D$1048576,2,Archives!$V$2:$V$1048576,$B7)+SUMIFS(Archives!$AF$2:$AF$1048576,Archives!$D$2:$D$1048576,2,Archives!$Y$2:$Y$1048576,$B7) -> 6 | E7: =SUMIFS(Archives!$AF$2:$AF$1048576,Archives!$D$2:$D$1048576,3,Archives!$V$2:$V$1048576,$B7)+SUMIFS(Archives!$AF$2:$AF$1048576,Archives!$D$2:$D$1048576,3,Archives!$Y$2:$Y$1048576,$B7) -> 5 | F7: =SUMIFS(Archives!$AF$2:$AF$1048576,Archives!$D$2:$D$1048576,4,Archives!$V$2:$V$1048576,$B7)+SUMIFS(Archives!$AF$2:$AF$1048576,Archives!$D$2:$D$1048576,4,Archives!$Y$2:$Y$1048576,$B7) -> 2.5 | G7: =SUMIFS(Archives!$AF$2:$AF$1048576,Archives!$D$2:$D$1048576,5,Archives!$V$2:$V$1048576,$B7)+SUMIFS(Archives!$AF$2:$AF$1048576,Archives!$D$2:$D$1048576,5,Archives!$Y$2:$Y$1048576,$B7) -> 3.5 | H7: =SUMIFS(Archives!$AF$2:$AF$1048576,Archives!$D$2:$D$1048576,6,Archives!$V$2:$V$1048576,$B7)+SUMIFS(Archives!$AF$2:$AF$1048576,Archives!$D$2:$D$1048576,6,Archives!$Y$2:$Y$1048576,$B7) -> 6.5 | I7: =SUMIFS(Archives!$AF$2:$AF$1048576,Archives!$D$2:$D$1048576,7,Archives!$V$2:$V$1048576,$B7)+SUMIFS(Archives!$AF$2:$AF$1048576,Archives!$D$2:$D$1048576,7,Archives!$Y$2:$Y$1048576,$B7) -> 4 | J7: =SUMIFS(Archives!$AF$2:$AF$1048576,Archives!$D$2:$D$1048576,8,Archives!$V$2:$V$1048576,$B7)+SUMIFS(Archives!$AF$2:$AF$1048576,Archives!$D$2:$D$1048576,8,Archives!$Y$2:$Y$1048576,$B7) -> 2.5 | K7: =SUMIFS(Archives!$AF$2:$AF$1048576,Archives!$D$2:$D$1048576,9,Archives!$V$2:$V$1048576,$B7)+SUMIFS(Archives!$AF$2:$AF$1048576,Archives!$D$2:$D$1048576,9,Archives!$Y$2:$Y$1048576,$B7) -> 1 | L7: =SUMIFS(Archives!$AF$2:$AF$1048576,Archives!$D$2:$D$1048576,10,Archives!$V$2:$V$1048576,$B7)+SUMIFS(Archives!$AF$2:$AF$1048576,Archives!$D$2:$D$1048576,10,Archives!$Y$2:$Y$1048576,$B7) -> 5.5 | M7: =SUMIFS(Archives!$AF$2:$AF$1048576,Archives!$D$2:$D$1048576,11,Archives!$V$2:$V$1048576,$B7)+SUMIFS(Archives!$AF$2:$AF$1048576,Archives!$D$2:$D$1048576,11,Archives!$Y$2:$Y$1048576,$B7) -> 2.5 | N7: =SUMIFS(Archives!$AF$2:$AF$1048576,Archives!$D$2:$D$1048576,12,Archives!$V$2:$V$1048576,$B7)+SUMIFS(Archives!$AF$2:$AF$1048576,Archives!$D$2:$D$1048576,12,Archives!$Y$2:$Y$1048576,$B7) -> 3.5 | O7: =SUMIFS(Archives!$AF$2:$AF$1048576,Archives!$D$2:$D$1048576,13,Archives!$V$2:$V$1048576,$B7)+SUMIFS(Archives!$AF$2:$AF$1048576,Archives!$D$2:$D$1048576,13,Archives!$Y$2:$Y$1048576,$B7) -> 0 | P7: =SUMIFS(Archives!$AF$2:$AF$1048576,Archives!$D$2:$D$1048576,14,Archives!$V$2:$V$1048576,$B7)+SUMIFS(Archives!$AF$2:$AF$1048576,Archives!$D$2:$D$1048576,14,Archives!$Y$2:$Y$1048576,$B7) -> 0 | Q7: =SUMIFS(Archives!$AF$2:$AF$1048576,Archives!$D$2:$D$1048576,15,Archives!$V$2:$V$1048576,$B7)+SUMIFS(Archives!$AF$2:$AF$1048576,Archives!$D$2:$D$1048576,15,Archives!$Y$2:$Y$1048576,$B7) -> 0 | R7: =SUM(C7:Q7) -> 46
B8: Grise | C8: =SUMIFS(Archives!$AF$2:$AF$1048576,Archives!$D$2:$D$1048576,1,Archives!$V$2:$V$1048576,$B8)+SUMIFS(Archives!$AF$2:$AF$1048576,Archives!$D$2:$D$1048576,1,Archives!$Y$2:$Y$1048576,$B8) -> 2.5 | D8: =SUMIFS(Archives!$AF$2:$AF$1048576,Archives!$D$2:$D$1048576,2,Archives!$V$2:$V$1048576,$B8)+SUMIFS(Archives!$AF$2:$AF$1048576,Archives!$D$2:$D$1048576,2,Archives!$Y$2:$Y$1048576,$B8) -> 5 | E8: =SUMIFS(Archives!$AF$2:$AF$1048576,Archives!$D$2:$D$1048576,3,Archives!$V$2:$V$1048576,$B8)+SUMIFS(Archives!$AF$2:$AF$1048576,Archives!$D$2:$D$1048576,3,Archives!$Y$2:$Y$1048576,$B8) -> 1 | F8: =SUMIFS(Archives!$AF$2:$AF$1048576,Archives!$D$2:$D$1048576,4,Archives!$V$2:$V$1048576,$B8)+SUMIFS(Archives!$AF$2:$AF$1048576,Archives!$D$2:$D$1048576,4,Archives!$Y$2:$Y$1048576,$B8) -> 5 | G8: =SUMIFS(Archives!$AF$2:$AF$1048576,Archives!$D$2:$D$1048576,5,Archives!$V$2:$V$1048576,$B8)+SUMIFS(Archives!$AF$2:$AF$1048576,Archives!$D$2:$D$1048576,5,Archives!$Y$2:$Y$1048576,$B8) -> 2.5 | H8: =SUMIFS(Archives!$AF$2:$AF$1048576,Archives!$D$2:$D$1048576,6,Archives!$V$2:$V$1048576,$B8)+SUMIFS(Archives!$AF$2:$AF$1048576,Archives!$D$2:$D$1048576,6,Archives!$Y$2:$Y$1048576,$B8) -> 4.5 | I8: =SUMIFS(Archives!$AF$2:$AF$1048576,Archives!$D$2:$D$1048576,7,Archives!$V$2:$V$1048576,$B8)+SUMIFS(Archives!$AF$2:$AF$1048576,Archives!$D$2:$D$1048576,7,Archives!$Y$2:$Y$1048576,$B8) -> 6.5 | J8: =SUMIFS(Archives!$AF$2:$AF$1048576,Archives!$D$2:$D$1048576,8,Archives!$V$2:$V$1048576,$B8)+SUMIFS(Archives!$AF$2:$AF$1048576,Archives!$D$2:$D$1048576,8,Archives!$Y$2:$Y$1048576,$B8) -> 4.5 | K8: =SUMIFS(Archives!$AF$2:$AF$1048576,Archives!$D$2:$D$1048576,9,Archives!$V$2:$V$1048576,$B8)+SUMIFS(Archives!$AF$2:$AF$1048576,Archives!$D$2:$D$1048576,9,Archives!$Y$2:$Y$1048576,$B8) -> 2 | L8: =SUMIFS(Archives!$AF$2:$AF$1048576,Archives!$D$2:$D$1048576,10,Archives!$V$2:$V$1048576,$B8)+SUMIFS(Archives!$AF$2:$AF$1048576,Archives!$D$2:$D$1048576,10,Archives!$Y$2:$Y$1048576,$B8) -> 5 | M8: =SUMIFS(Archives!$AF$2:$AF$1048576,Archives!$D$2:$D$1048576,11,Archives!$V$2:$V$1048576,$B8)+SUMIFS(Archives!$AF$2:$AF$1048576,Archives!$D$2:$D$1048576,11,Archives!$Y$2:$Y$1048576,$B8) -> 0.5 | N8: =SUMIFS(Archives!$AF$2:$AF$1048576,Archives!$D$2:$D$1048576,12,Archives!$V$2:$V$1048576,$B8)+SUMIFS(Archives!$AF$2:$AF$1048576,Archives!$D$2:$D$1048576,12,Archives!$Y$2:$Y$1048576,$B8) -> 4 | O8: =SUMIFS(Archives!$AF$2:$AF$1048576,Archives!$D$2:$D$1048576,13,Archives!$V$2:$V$1048576,$B8)+SUMIFS(Archives!$AF$2:$AF$1048576,Archives!$D$2:$D$1048576,13,Archives!$Y$2:$Y$1048576,$B8) -> 0 | P8: =SUMIFS(Archives!$AF$2:$AF$1048576,Archives!$D$2:$D$1048576,14,Archives!$V$2:$V$1048576,$B8)+SUMIFS(Archives!$AF$2:$AF$1048576,Archives!$D$2:$D$1048576,14,Archives!$Y$2:$Y$1048576,$B8) -> 0 | Q8: =SUMIFS(Archives!$AF$2:$AF$1048576,Archives!$D$2:$D$1048576,15,Archives!$V$2:$V$1048576,$B8)+SUMIFS(Archives!$AF$2:$AF$1048576,Archives!$D$2:$D$1048576,15,Archives!$Y$2:$Y$1048576,$B8) -> 0 | R8: =SUM(C8:Q8) -> 43
B9: Forster | C9: =SUMIFS(Archives!$AF$2:$AF$1048576,Archives!$D$2:$D$1048576,1,Archives!$V$2:$V$1048576,$B9)+SUMIFS(Archives!$AF$2:$AF$1048576,Archives!$D$2:$D$1048576,1,Archives!$Y$2:$Y$1048576,$B9) -> 0 | D9: =SUMIFS(Archives!$AF$2:$AF$1048576,Archives!$D$2:$D$1048576,2,Archives!$V$2:$V$1048576,$B9)+SUMIFS(Archives!$AF$2:$AF$1048576,Archives!$D$2:$D$1048576,2,Archives!$Y$2:$Y$1048576,$B9) -> 5.5 | E9: =SUMIFS(Archives!$AF$2:$AF$1048576,Archives!$D$2:$D$1048576,3,Archives!$V$2:$V$1048576,$B9)+SUMIFS(Archives!$AF$2:$AF$1048576,Archives!$D$2:$D$1048576,3,Archives!$Y$2:$Y$1048576,$B9) -> 3.5 | F9: =SUMIFS(Archives!$AF$2:$AF$1048576,Archives!$D$2:$D$1048576,4,Archives!$V$2:$V$1048576,$B9)+SUMIFS(Archives!$AF$2:$AF$1048576,Archives!$D$2:$D$1048576,4,Archives!$Y$2:$Y$1048576,$B9) -> 5.5 | G9: =SUMIFS(Archives!$AF$2:$AF$1048576,Archives!$D$2:$D$1048576,5,Archives!$V$2:$V$1048576,$B9)+SUMIFS(Archives!$AF$2:$AF$1048576,Archives!$D$2:$D$1048576,5,Archives!$Y$2:$Y$1048576,$B9) -> 5 | H9: =SUMIFS(Archives!$AF$2:$AF$1048576,Archives!$D$2:$D$1048576,6,Archives!$V$2:$V$1048576,$B9)+SUMIFS(Archives!$AF$2:$AF$1048576,Archives!$D$2:$D$1048576,6,Archives!$Y$2:$Y$1048576,$B9) -> 5 | I9: =SUMIFS(Archives!$AF$2:$AF$1048576,Archives!$D$2:$D$1048576,7,Archives!$V$2:$V$1048576,$B9)+SUMIFS(Archives!$AF$2:$AF$1048576,Archives!$D$2:$D$1048576,7,Archives!$Y$2:$Y$1048576,$B9) -> 4.5 | J9: =SUMIFS(Archives!$AF$2:$AF$1048576,Archives!$D$2:$D$1048576,8,Archives!$V$2:$V$1048576,$B9)+SUMIFS(Archives!$AF$2:$AF$1048576,Archives!$D$2:$D$1048576,8,Archives!$Y$2:$Y$1048576,$B9) -> 1 | K9: =SUMIFS(Archives!$AF$2:$AF$1048576,Archives!$D$2:$D$1048576,9,Archives!$V$2:$V$1048576,$B9)+SUMIFS(Archives!$AF$2:$AF$1048576,Archives!$D$2:$D$1048576,9,Archives!$Y$2:$Y$1048576,$B9) -> 4.5 | L9: =SUMIFS(Archives!$AF$2:$AF$1048576,Archives!$D$2:$D$1048576,10,Archives!$V$2:$V$1048576,$B9)+SUMIFS(Archives!$AF$2:$AF$1048576,Archives!$D$2:$D$1048576,10,Archives!$Y$2:$Y$1048576,$B9) -> 0 | M9: =SUMIFS(Archives!$AF$2:$AF$1048576,Archives!$D$2:$D$1048576,11,Archives!$V$2:$V$1048576,$B9)+SUMIFS(Archives!$AF$2:$AF$1048576,Archives!$D$2:$D$1048576,11,Archives!$Y$2:$Y$1048576,$B9) -> 3.5 | N9: =SUMIFS(Archives!$AF$2:$AF$1048576,Archives!$D$2:$D$1048576,12,Archives!$V$2:$V$1048576,$B9)+SUMIFS(Archives!$AF$2:$AF$1048576,Archives!$D$2:$D$1048576,12,Archives!$Y$2:$Y$1048576,$B9) -> 4 | O9: =SUMIFS(Archives!$AF$2:$AF$1048576,Archives!$D$2:$D$1048576,13,Archives!$V$2:$V$1048576,$B9)+SUMIFS(Archives!$AF$2:$AF$1048576,Archives!$D$2:$D$1048576,13,Archives!$Y$2:$Y$1048576,$B9) -> 0 | P9: =SUMIFS(Archives!$AF$2:$AF$1048576,Archives!$D$2:$D$1048576,14,Archives!$V$2:$V$1048576,$B9)+SUMIFS(Archives!$AF$2:$AF$1048576,Archives!$D$2:$D$1048576,14,Archives!$Y$2:$Y$1048576,$B9) -> 0 | Q9: =SUMIFS(Archives!$AF$2:$AF$1048576,Archives!$D$2:$D$1048576,15,Archives!$V$2:$V$1048576,$B9)+SUMIFS(Archives!$AF$2:$AF$1048576,Archives!$D$2:$D$1048576,15,Archives!$Y$2:$Y$1048576,$B9) -> 0 | R9: =SUM(C9:Q9) -> 42
B10: Lynch | C10: =SUMIFS(Archives!$AF$2:$AF$1048576,Archives!$D$2:$D$1048576,1,Archives!$V$2:$V$1048576,$B10)+SUMIFS(Archives!$AF$2:$AF$1048576,Archives!$D$2:$D$1048576,1,Archives!$Y$2:$Y$1048576,$B10) -> 1.5 | D10: =SUMIFS(Archives!$AF$2:$AF$1048576,Archives!$D$2:$D$1048576,2,Archives!$V$2:$V$1048576,$B10)+SUMIFS(Archives!$AF$2:$AF$1048576,Archives!$D$2:$D$1048576,2,Archives!$Y$2:$Y$1048576,$B10) -> 4 | E10: =SUMIFS(Archives!$AF$2:$AF$1048576,Archives!$D$2:$D$1048576,3,Archives!$V$2:$V$1048576,$B10)+SUMIFS(Archives!$AF$2:$AF$1048576,Archives!$D$2:$D$1048576,3,Archives!$Y$2:$Y$1048576,$B10) -> 4 | F10: =SUMIFS(Archives!$AF$2:$AF$1048576,Archives!$D$2:$D$1048576,4,Archives!$V$2:$V$1048576,$B10)+SUMIFS(Archives!$AF$2:$AF$1048576,Archives!$D$2:$D$1048576,4,Archives!$Y$2:$Y$1048576,$B10) -> 4 | G10: =SUMIFS(Archives!$AF$2:$AF$1048576,Archives!$D$2:$D$1048576,5,Archives!$V$2:$V$1048576,$B10)+SUMIFS(Archives!$AF$2:$AF$1048576,Archives!$D$2:$D$1048576,5,Archives!$Y$2:$Y$1048576,$B10) -> 3.5 | H10: =SUMIFS(Archives!$AF$2:$AF$1048576,Archives!$D$2:$D$1048576,6,Archives!$V$2:$V$1048576,$B10)+SUMIFS(Archives!$AF$2:$AF$1048576,Archives!$D$2:$D$1048576,6,Archives!$Y$2:$Y$1048576,$B10) -> 1.5 | I10: =SUMIFS(Archives!$AF$2:$AF$1048576,Archives!$D$2:$D$1048576,7,Archives!$V$2:$V$1048576,$B10)+SUMIFS(Archives!$AF$2:$AF$1048576,Archives!$D$2:$D$1048576,7,Archives!$Y$2:$Y$1048576,$B10) -> 4.5 | J10: =SUMIFS(Archives!$AF$2:$AF$1048576,Archives!$D$2:$D$1048576,8,Archives!$V$2:$V$1048576,$B10)+SUMIFS(Archives!$AF$2:$AF$1048576,Archives!$D$2:$D$1048576,8,Archives!$Y$2:$Y$1048576,$B10) -> 4 | K10: =SUMIFS(Archives!$AF$2:$AF$1048576,Archives!$D$2:$D$1048576,9,Archives!$V$2:$V$1048576,$B10)+SUMIFS(Archives!$AF$2:$AF$1048576,Archives!$D$2:$D$1048576,9,Archives!$Y$2:$Y$1048576,$B10) -> 5.5 | L10: =SUMIFS(Archives!$AF$2:$AF$1048576,Archives!$D$2:$D$1048576,10,Archives!$V$2:$V$1048576,$B10)+SUMIFS(Archives!$AF$2:$AF$1048576,Archives!$D$2:$D$1048576,10,Archives!$Y$2:$Y$1048576,$B10) -> 3.5 | M10: =SUMIFS(Archives!$AF$2:$AF$1048576,Archives!$D$2:$D$1048576,11,Archives!$V$2:$V$1048576,$B10)+SUMIFS(Archives!$AF$2:$AF$1048576,Archives!$D$2:$D$1048576,11,Archives!$Y$2:$Y$1048576,$B10) -> 2 | N10: =SUMIFS(Archives!$AF$2:$AF$1048576,Archives!$D$2:$D$1048576,12,Archives!$V$2:$V$1048576,$B10)+SUMIFS(Archives!$AF$2:$AF$1048576,Archives!$D$2:$D$1048576,12,Archives!$Y$2:$Y$1048576,$B10) -> 3 | O10: =SUMIFS(Archives!$AF$2:$AF$1048576,Archives!$D$2:$D$1048576,13,Archives!$V$2:$V$1048576,$B10)+SUMIFS(Archives!$AF$2:$AF$1048576,Archives!$D$2:$D$1048576,13,Archives!$Y$2:$Y$1048576,$B10) -> 0 | P10: =SUMIFS(Archives!$AF$2:$AF$1048576,Archives!$D$2:$D$1048576,14,Archives!$V$2:$V$1048576,$B10)+SUMIFS(Archives!$AF$2:$AF$1048576,Archives!$D$2:$D$1048576,14,Archives!$Y$2:$Y$1048576,$B10) -> 0 | Q10: =SUMIFS(Archives!$AF$2:$AF$1048576,Archives!$D$2:$D$1048576,15,Archives!$V$2:$V$1048576,$B10)+SUMIFS(Archives!$AF$2:$AF$1048576,Archives!$D$2:$D$1048576,15,Archives!$Y$2:$Y$1048576,$B10) -> 0 | R10: =SUM(C10:Q10) -> 41
B11: Flanders | C11: =SUMIFS(Archives!$AF$2:$AF$1048576,Archives!$D$2:$D$1048576,1,Archives!$V$2:$V$1048576,$B11)+SUMIFS(Archives!$AF$2:$AF$1048576,Archives!$D$2:$D$1048576,1,Archives!$Y$2:$Y$1048576,$B11) -> 2 | D11: =SUMIFS(Archives!$AF$2:$AF$1048576,Archives!$D$2:$D$1048576,2,Archives!$V$2:$V$1048576,$B11)+SUMIFS(Archives!$AF$2:$AF$1048576,Archives!$D$2:$D$1048576,2,Archives!$Y$2:$Y$1048576,$B11) -> 1.5 | E11: =SUMIFS(Archives!$AF$2:$AF$1048576,Archives!$D$2:$D$1048576,3,Archives!$V$2:$V$1048576,$B11)+SUMIFS(Archives!$AF$2:$AF$1048576,Archives!$D$2:$D$1048576,3,Archives!$Y$2:$Y$1048576,$B11) -> 0.5 | F11: =SUMIFS(Archives!$AF$2:$AF$1048576,Archives!$D$2:$D$1048576,4,Archives!$V$2:$V$1048576,$B11)+SUMIFS(Archives!$AF$2:$AF$1048576,Archives!$D$2:$D$1048576,4,Archives!$Y$2:$Y$1048576,$B11) -> 5.5 | G11: =SUMIFS(Archives!$AF$2:$AF$1048576,Archives!$D$2:$D$1048576,5,Archives!$V$2:$V$1048576,$B11)+SUMIFS(Archives!$AF$2:$AF$1048576,Archives!$D$2:$D$1048576,5,Archives!$Y$2:$Y$1048576,$B11) -> 3 | H11: =SUMIFS(Archives!$AF$2:$AF$1048576,Archives!$D$2:$D$1048576,6,Archives!$V$2:$V$1048576,$B11)+SUMIFS(Archives!$AF$2:$AF$1048576,Archives!$D$2:$D$1048576,6,Archives!$Y$2:$Y$1048576,$B11) -> 3 | I11: =SUMIFS(Archives!$AF$2:$AF$1048576,Archives!$D$2:$D$1048576,7,Archives!$V$2:$V$1048576,$B11)+SUMIFS(Archives!$AF$2:$AF$1048576,Archives!$D$2:$D$1048576,7,Archives!$Y$2:$Y$1048576,$B11) -> 4 | J11: =SUMIFS(Archives!$AF$2:$AF$1048576,Archives!$D$2:$D$1048576,8,Archives!$V$2:$V$1048576,$B11)+SUMIFS(Archives!$AF$2:$AF$1048576,Archives!$D$2:$D$1048576,8,Archives!$Y$2:$Y$1048576,$B11) -> 3 | K11: =SUMIFS(Archives!$AF$2:$AF$1048576,Archives!$D$2:$D$1048576,9,Archives!$V$2:$V$1048576,$B11)+SUMIFS(Archives!$AF$2:$AF$1048576,Archives!$D$2:$D$1048576,9,Archives!$Y$2:$Y$1048576,$B11) -> 2 | L11: =SUMIFS(Archives!$AF$2:$AF$1048576,Archives!$D$2:$D$1048576,10,Archives!$V$2:$V$1048576,$B11)+SUMIFS(Archives!$AF$2:$AF$1048576,Archives!$D$2:$D$1048576,10,Archives!$Y$2:$Y$1048576,$B11) -> 4 | M11: =SUMIFS(Archives!$AF$2:$AF$1048576,Archives!$D$2:$D$1048576,11,Archives!$V$2:$V$1048576,$B11)+SUMIFS(Archives!$AF$2:$AF$1048576,Archives!$D$2:$D$1048576,11,Archives!$Y$2:$Y$1048576,$B11) -> 1.5 | N11: =SUMIFS(Archives!$AF$2:$AF$1048576,Archives!$D$2:$D$1048576,12,Archives!$V$2:$V$1048576,$B11)+SUMIFS(Archives!$AF$2:$AF$1048576,Archives!$D$2:$D$1048576,12,Archives!$Y$2:$Y$1048576,$B11) -> 6.5 | O11: =SUMIFS(Archives!$AF$2:$AF$1048576,Archives!$D$2:$D$1048576,13,Archives!$V$2:$V$1048576,$B11)+SUMIFS(Archives!$AF$2:$AF$1048576,Archives!$D$2:$D$1048576,13,Archives!$Y$2:$Y$1048576,$B11) -> 0 | P11: =SUMIFS(Archives!$AF$2:$AF$1048576,Archives!$D$2:$D$1048576,14,Archives!$V$2:$V$1048576,$B11)+SUMIFS(Archives!$AF$2:$AF$1048576,Archives!$D$2:$D$1048576,14,Archives!$Y$2:$Y$1048576,$B11) -> 0 | Q11: =SUMIFS(Archives!$AF$2:$AF$1048576,Archives!$D$2:$D$1048576,15,Archives!$V$2:$V$1048576,$B11)+SUMIFS(Archives!$AF$2:$AF$1048576,Archives!$D$2:$D$1048576,15,Archives!$Y$2:$Y$1048576,$B11) -> 0 | R11: =SUM(C11:Q11) -> 36.5
B12: Hilts | C12: =SUMIFS(Archives!$AF$2:$AF$1048576,Archives!$D$2:$D$1048576,1,Archives!$V$2:$V$1048576,$B12)+SUMIFS(Archives!$AF$2:$AF$1048576,Archives!$D$2:$D$1048576,1,Archives!$Y$2:$Y$1048576,$B12) -> 2.5 | D12: =SUMIFS(Archives!$AF$2:$AF$1048576,Archives!$D$2:$D$1048576,2,Archives!$V$2:$V$1048576,$B12)+SUMIFS(Archives!$AF$2:$AF$1048576,Archives!$D$2:$D$1048576,2,Archives!$Y$2:$Y$1048576,$B12) -> 2 | E12: =SUMIFS(Archives!$AF$2:$AF$1048576,Archives!$D$2:$D$1048576,3,Archives!$V$2:$V$1048576,$B12)+SUMIFS(Archives!$AF$2:$AF$1048576,Archives!$D$2:$D$1048576,3,Archives!$Y$2:$Y$1048576,$B12) -> 2.5 | F12: =SUMIFS(Archives!$AF$2:$AF$1048576,Archives!$D$2:$D$1048576,4,Archives!$V$2:$V$1048576,$B12)+SUMIFS(Archives!$AF$2:$AF$1048576,Archives!$D$2:$D$1048576,4,Archives!$Y$2:$Y$1048576,$B12) -> 0 | G12: =SUMIFS(Archives!$AF$2:$AF$1048576,Archives!$D$2:$D$1048576,5,Archives!$V$2:$V$1048576,$B12)+SUMIFS(Archives!$AF$2:$AF$1048576,Archives!$D$2:$D$1048576,5,Archives!$Y$2:$Y$1048576,$B12) -> 3 | H12: =SUMIFS(Archives!$AF$2:$AF$1048576,Archives!$D$2:$D$1048576,6,Archives!$V$2:$V$1048576,$B12)+SUMIFS(Archives!$AF$2:$AF$1048576,Archives!$D$2:$D$1048576,6,Archives!$Y$2:$Y$1048576,$B12) -> 3.5 | I12: =SUMIFS(Archives!$AF$2:$AF$1048576,Archives!$D$2:$D$1048576,7,Archives!$V$2:$V$1048576,$B12)+SUMIFS(Archives!$AF$2:$AF$1048576,Archives!$D$2:$D$1048576,7,Archives!$Y$2:$Y$1048576,$B12) -> 2 | J12: =SUMIFS(Archives!$AF$2:$AF$1048576,Archives!$D$2:$D$1048576,8,Archives!$V$2:$V$1048576,$B12)+SUMIFS(Archives!$AF$2:$AF$1048576,Archives!$D$2:$D$1048576,8,Archives!$Y$2:$Y$1048576,$B12) -> 5 | K12: =SUMIFS(Archives!$AF$2:$AF$1048576,Archives!$D$2:$D$1048576,9,Archives!$V$2:$V$1048576,$B12)+SUMIFS(Archives!$AF$2:$AF$1048576,Archives!$D$2:$D$1048576,9,Archives!$Y$2:$Y$1048576,$B12) -> 3.5 | L12: =SUMIFS(Archives!$AF$2:$AF$1048576,Archives!$D$2:$D$1048576,10,Archives!$V$2:$V$1048576,$B12)+SUMIFS(Archives!$AF$2:$AF$1048576,Archives!$D$2:$D$1048576,10,Archives!$Y$2:$Y$1048576,$B12) -> 3 | M12: =SUMIFS(Archives!$AF$2:$AF$1048576,Archives!$D$2:$D$1048576,11,Archives!$V$2:$V$1048576,$B12)+SUMIFS(Archives!$AF$2:$AF$1048576,Archives!$D$2:$D$1048576,11,Archives!$Y$2:$Y$1048576,$B12) -> 5.5 | N12: =SUMIFS(Archives!$AF$2:$AF$1048576,Archives!$D$2:$D$1048576,12,Archives!$V$2:$V$1048576,$B12)+SUMIFS(Archives!$AF$2:$AF$1048576,Archives!$D$2:$D$1048576,12,Archives!$Y$2:$Y$1048576,$B12) -> 4.5 | O12: =SUMIFS(Archives!$AF$2:$AF$1048576,Archives!$D$2:$D$1048576,13,Archives!$V$2:$V$1048576,$B12)+SUMIFS(Archives!$AF$2:$AF$1048576,Archives!$D$2:$D$1048576,13,Archives!$Y$2:$Y$1048576,$B12) -> 0 | P12: =SUMIFS(Archives!$AF$2:$AF$1048576,Archives!$D$2:$D$1048576,14,Archives!$V$2:$V$1048576,$B12)+SUMIFS(Archives!$AF$2:$AF$1048576,Archives!$D$2:$D$1048576,14,Archives!$Y$2:$Y$1048576,$B12) -> 0 | Q12: =SUMIFS(Archives!$AF$2:$AF$1048576,Archives!$D$2:$D$1048576,15,Archives!$V$2:$V$1048576,$B12)+SUMIFS(Archives!$AF$2:$AF$1048576,Archives!$D$2:$D$1048576,15,Archives!$Y$2:$Y$1048576,$B12) -> 0 | R12: =SUM(C12:Q12) -> 37
B13: Zimmer | C13: =SUMIFS(Archives!$AF$2:$AF$1048576,Archives!$D$2:$D$1048576,1,Archives!$V$2:$V$1048576,$B13)+SUMIFS(Archives!$AF$2:$AF$1048576,Archives!$D$2:$D$1048576,1,Archives!$Y$2:$Y$1048576,$B13) -> 0 | D13: =SUMIFS(Archives!$AF$2:$AF$1048576,Archives!$D$2:$D$1048576,2,Archives!$V$2:$V$1048576,$B13)+SUMIFS(Archives!$AF$2:$AF$1048576,Archives!$D$2:$D$1048576,2,Archives!$Y$2:$Y$1048576,$B13) -> 0 | E13: =SUMIFS(Archives!$AF$2:$AF$1048576,Archives!$D$2:$D$1048576,3,Archives!$V$2:$V$1048576,$B13)+SUMIFS(Archives!$AF$2:$AF$1048576,Archives!$D$2:$D$1048576,3,Archives!$Y$2:$Y$1048576,$B13) -> 4 | F13: =SUMIFS(Archives!$AF$2:$AF$1048576,Archives!$D$2:$D$1048576,4,Archives!$V$2:$V$1048576,$B13)+SUMIFS(Archives!$AF$2:$AF$1048576,Archives!$D$2:$D$1048576,4,Archives!$Y$2:$Y$1048576,$B13) -> 4 | G13: =SUMIFS(Archives!$AF$2:$AF$1048576,Archives!$D$2:$D$1048576,5,Archives!$V$2:$V$1048576,$B13)+SUMIFS(Archives!$AF$2:$AF$1048576,Archives!$D$2:$D$1048576,5,Archives!$Y$2:$Y$1048576,$B13) -> 4.5 | H13: =SUMIFS(Archives!$AF$2:$AF$1048576,Archives!$D$2:$D$1048576,6,Archives!$V$2:$V$1048576,$B13)+SUMIFS(Archives!$AF$2:$AF$1048576,Archives!$D$2:$D$1048576,6,Archives!$Y$2:$Y$1048576,$B13) -> 1 | I13: =SUMIFS(Archives!$AF$2:$AF$1048576,Archives!$D$2:$D$1048576,7,Archives!$V$2:$V$1048576,$B13)+SUMIFS(Archives!$AF$2:$AF$1048576,Archives!$D$2:$D$1048576,7,Archives!$Y$2:$Y$1048576,$B13) -> 6 | J13: =SUMIFS(Archives!$AF$2:$AF$1048576,Archives!$D$2:$D$1048576,8,Archives!$V$2:$V$1048576,$B13)+SUMIFS(Archives!$AF$2:$AF$1048576,Archives!$D$2:$D$1048576,8,Archives!$Y$2:$Y$1048576,$B13) -> 4.5 | K13: =SUMIFS(Archives!$AF$2:$AF$1048576,Archives!$D$2:$D$1048576,9,Archives!$V$2:$V$1048576,$B13)+SUMIFS(Archives!$AF$2:$AF$1048576,Archives!$D$2:$D$1048576,9,Archives!$Y$2:$Y$1048576,$B13) -> 3.5 | L13: =SUMIFS(Archives!$AF$2:$AF$1048576,Archives!$D$2:$D$1048576,10,Archives!$V$2:$V$1048576,$B13)+SUMIFS(Archives!$AF$2:$AF$1048576,Archives!$D$2:$D$1048576,10,Archives!$Y$2:$Y$1048576,$B13) -> 1 | M13: =SUMIFS(Archives!$AF$2:$AF$1048576,Archives!$D$2:$D$1048576,11,Archives!$V$2:$V$1048576,$B13)+SUMIFS(Archives!$AF$2:$AF$1048576,Archives!$D$2:$D$1048576,11,Archives!$Y$2:$Y$1048576,$B13) -> 2.5 | N13: =SUMIFS(Archives!$AF$2:$AF$1048576,Archives!$D$2:$D$1048576,12,Archives!$V$2:$V$1048576,$B13)+SUMIFS(Archives!$AF$2:$AF$1048576,Archives!$D$2:$D$1048576,12,Archives!$Y$2:$Y$1048576,$B13) -> 1.5 | O13: =SUMIFS(Archives!$AF$2:$AF$1048576,Archives!$D$2:$D$1048576,13,Archives!$V$2:$V$1048576,$B13)+SUMIFS(Archives!$AF$2:$AF$1048576,Archives!$D$2:$D$1048576,13,Archives!$Y$2:$Y$1048576,$B13) -> 0 | P13: =SUMIFS(Archives!$AF$2:$AF$1048576,Archives!$D$2:$D$1048576,14,Archives!$V$2:$V$1048576,$B13)+SUMIFS(Archives!$AF$2:$AF$1048576,Archives!$D$2:$D$1048576,14,Archives!$Y$2:$Y$1048576,$B13) -> 0 | Q13: =SUMIFS(Archives!$AF$2:$AF$1048576,Archives!$D$2:$D$1048576,15,Archives!$V$2:$V$1048576,$B13)+SUMIFS(Archives!$AF$2:$AF$1048576,Archives!$D$2:$D$1048576,15,Archives!$Y$2:$Y$1048576,$B13) -> 0 | R13: =SUM(C13:Q13) -> 32.5
B14: Gray | C14: =SUMIFS(Archives!$AF$2:$AF$1048576,Archives!$D$2:$D$1048576,1,Archives!$V$2:$V$1048576,$B14)+SUMIFS(Archives!$AF$2:$AF$1048576,Archives!$D$2:$D$1048576,1,Archives!$Y$2:$Y$1048576,$B14) -> 0 | D14: =SUMIFS(Archives!$AF$2:$AF$1048576,Archives!$D$2:$D$1048576,2,Archives!$V$2:$V$1048576,$B14)+SUMIFS(Archives!$AF$2:$AF$1048576,Archives!$D$2:$D$1048576,2,Archives!$Y$2:$Y$1048576,$B14) -> 0 | E14: =SUMIFS(Archives!$AF$2:$AF$1048576,Archives!$D$2:$D$1048576,3,Archives!$V$2:$V$1048576,$B14)+SUMIFS(Archives!$AF$2:$AF$1048576,Archives!$D$2:$D$1048576,3,Archives!$Y$2:$Y$1048576,$B14) -> 4 | F14: =SUMIFS(Archives!$AF$2:$AF$1048576,Archives!$D$2:$D$1048576,4,Archives!$V$2:$V$1048576,$B14)+SUMIFS(Archives!$AF$2:$AF$1048576,Archives!$D$2:$D$1048576,4,Archives!$Y$2:$Y$1048576,$B14) -> 4 | G14: =SUMIFS(Archives!$AF$2:$AF$1048576,Archives!$D$2:$D$1048576,5,Archives!$V$2:$V$1048576,$B14)+SUMIFS(Archives!$AF$2:$AF$1048576,Archives!$D$2:$D$1048576,5,Archives!$Y$2:$Y$1048576,$B14) -> 3.5 | H14: =SUMIFS(Archives!$AF$2:$AF$1048576,Archives!$D$2:$D$1048576,6,Archives!$V$2:$V$1048576,$B14)+SUMIFS(Archives!$AF$2:$AF$1048576,Archives!$D$2:$D$1048576,6,Archives!$Y$2:$Y$1048576,$B14) -> 4.5 | I14: =SUMIFS(Archives!$AF$2:$AF$1048576,Archives!$D$2:$D$1048576,7,Archives!$V$2:$V$1048576,$B14)+SUMIFS(Archives!$AF$2:$AF$1048576,Archives!$D$2:$D$1048576,7,Archives!$Y$2:$Y$1048576,$B14) -> 7 | J14: =SUMIFS(Archives!$AF$2:$AF$1048576,Archives!$D$2:$D$1048576,8,Archives!$V$2:$V$1048576,$B14)+SUMIFS(Archives!$AF$2:$AF$1048576,Archives!$D$2:$D$1048576,8,Archives!$Y$2:$Y$1048576,$B14) -> 0 | K14: =SUMIFS(Archives!$AF$2:$AF$1048576,Archives!$D$2:$D$1048576,9,Archives!$V$2:$V$1048576,$B14)+SUMIFS(Archives!$AF$2:$AF$1048576,Archives!$D$2:$D$1048576,9,Archives!$Y$2:$Y$1048576,$B14) -> 0 | L14: =SUMIFS(Archives!$AF$2:$AF$1048576,Archives!$D$2:$D$1048576,10,Archives!$V$2:$V$1048576,$B14)+SUMIFS(Archives!$AF$2:$AF$1048576,Archives!$D$2:$D$1048576,10,Archives!$Y$2:$Y$1048576,$B14) -> 5.5 | M14: =SUMIFS(Archives!$AF$2:$AF$1048576,Archives!$D$2:$D$1048576,11,Archives!$V$2:$V$1048576,$B14)+SUMIFS(Archives!$AF$2:$AF$1048576,Archives!$D$2:$D$1048576,11,Archives!$Y$2:$Y$1048576,$B14) -> 2.5 | N14: =SUMIFS(Archives!$AF$2:$AF$1048576,Archives!$D$2:$D$1048576,12,Archives!$V$2:$V$1048576,$B14)+SUMIFS(Archives!$AF$2:$AF$1048576,Archives!$D$2:$D$1048576,12,Archives!$Y$2:$Y$1048576,$B14) -> 0 | O14: =SUMIFS(Archives!$AF$2:$AF$1048576,Archives!$D$2:$D$1048576,13,Archives!$V$2:$V$1048576,$B14)+SUMIFS(Archives!$AF$2:$AF$1048576,Archives!$D$2:$D$1048576,13,Archives!$Y$2:$Y$1048576,$B14) -> 0 | P14: =SUMIFS(Archives!$AF$2:$AF$1048576,Archives!$D$2:$D$1048576,14,Archives!$V$2:$V$1048576,$B14)+SUMIFS(Archives!$AF$2:$AF$1048576,Archives!$D$2:$D$1048576,14,Archives!$Y$2:$Y$1048576,$B14) -> 0 | Q14: =SUMIFS(Archives!$AF$2:$AF$1048576,Archives!$D$2:$D$1048576,15,Archives!$V$2:$V$1048576,$B14)+SUMIFS(Archives!$AF$2:$AF$1048576,Archives!$D$2:$D$1048576,15,Archives!$Y$2:$Y$1048576,$B14) -> 0 | R14: =SUM(C14:Q14) -> 31
B15: Fogan | C15: =SUMIFS(Archives!$AF$2:$AF$1048576,Archives!$D$2:$D$1048576,1,Archives!$V$2:$V$1048576,$B15)+SUMIFS(Archives!$AF$2:$AF$1048576,Archives!$D$2:$D$1048576,1,Archives!$Y$2:$Y$1048576,$B15) -> 0 | D15: =SUMIFS(Archives!$AF$2:$AF$1048576,Archives!$D$2:$D$1048576,2,Archives!$V$2:$V$1048576,$B15)+SUMIFS(Archives!$AF$2:$AF$1048576,Archives!$D$2:$D$1048576,2,Archives!$Y$2:$Y$1048576,$B15) -> 2 | E15: =SUMIFS(Archives!$AF$2:$AF$1048576,Archives!$D$2:$D$1048576,3,Archives!$V$2:$V$1048576,$B15)+SUMIFS(Archives!$AF$2:$AF$1048576,Archives!$D$2:$D$1048576,3,Archives!$Y$2:$Y$1048576,$B15) -> 3 | F15: =SUMIFS(Archives!$AF$2:$AF$1048576,Archives!$D$2:$D$1048576,4,Archives!$V$2:$V$1048576,$B15)+SUMIFS(Archives!$AF$2:$AF$1048576,Archives!$D$2:$D$1048576,4,Archives!$Y$2:$Y$1048576,$B15) -> 3 | G15: =SUMIFS(Archives!$AF$2:$AF$1048576,Archives!$D$2:$D$1048576,5,Archives!$V$2:$V$1048576,$B15)+SUMIFS(Archives!$AF$2:$AF$1048576,Archives!$D$2:$D$1048576,5,Archives!$Y$2:$Y$1048576,$B15) -> 1 | H15: =SUMIFS(Archives!$AF$2:$AF$1048576,Archives!$D$2:$D$1048576,6,Archives!$V$2:$V$1048576,$B15)+SUMIFS(Archives!$AF$2:$AF$1048576,Archives!$D$2:$D$1048576,6,Archives!$Y$2:$Y$1048576,$B15) -> 0.5 | I15: =SUMIFS(Archives!$AF$2:$AF$1048576,Archives!$D$2:$D$1048576,7,Archives!$V$2:$V$1048576,$B15)+SUMIFS(Archives!$AF$2:$AF$1048576,Archives!$D$2:$D$1048576,7,Archives!$Y$2:$Y$1048576,$B15) -> 3 | J15: =SUMIFS(Archives!$AF$2:$AF$1048576,Archives!$D$2:$D$1048576,8,Archives!$V$2:$V$1048576,$B15)+SUMIFS(Archives!$AF$2:$AF$1048576,Archives!$D$2:$D$1048576,8,Archives!$Y$2:$Y$1048576,$B15) -> 3 | K15: =SUMIFS(Archives!$AF$2:$AF$1048576,Archives!$D$2:$D$1048576,9,Archives!$V$2:$V$1048576,$B15)+SUMIFS(Archives!$AF$2:$AF$1048576,Archives!$D$2:$D$1048576,9,Archives!$Y$2:$Y$1048576,$B15) -> 4.5 | L15: =SUMIFS(Archives!$AF$2:$AF$1048576,Archives!$D$2:$D$1048576,10,Archives!$V$2:$V$1048576,$B15)+SUMIFS(Archives!$AF$2:$AF$1048576,Archives!$D$2:$D$1048576,10,Archives!$Y$2:$Y$1048576,$B15) -> 1.5 | M15: =SUMIFS(Archives!$AF$2:$AF$1048576,Archives!$D$2:$D$1048576,11,Archives!$V$2:$V$1048576,$B15)+SUMIFS(Archives!$AF$2:$AF$1048576,Archives!$D$2:$D$1048576,11,Archives!$Y$2:$Y$1048576,$B15) -> 4.5 | N15: =SUMIFS(Archives!$AF$2:$AF$1048576,Archives!$D$2:$D$1048576,12,Archives!$V$2:$V$1048576,$B15)+SUMIFS(Archives!$AF$2:$AF$1048576,Archives!$D$2:$D$1048576,12,Archives!$Y$2:$Y$1048576,$B15) -> 4 | O15: =SUMIFS(Archives!$AF$2:$AF$1048576,Archives!$D$2:$D$1048576,13,Archives!$V$2:$V$1048576,$B15)+SUMIFS(Archives!$AF$2:$AF$1048576,Archives!$D$2:$D$1048576,13,Archives!$Y$2:$Y$1048576,$B15) -> 0 | P15: =SUMIFS(Archives!$AF$2:$AF$1048576,Archives!$D$2:$D$1048576,14,Archives!$V$2:$V$1048576,$B15)+SUMIFS(Archives!$AF$2:$AF$1048576,Archives!$D$2:$D$1048576,14,Archives!$Y$2:$Y$1048576,$B15) -> 0 | Q15: =SUMIFS(Archives!$AF$2:$AF$1048576,Archives!$D$2:$D$1048576,15,Archives!$V$2:$V$1048576,$B15)+SUMIFS(Archives!$AF$2:$AF$1048576,Archives!$D$2:$D$1048576,15,Archives!$Y$2:$Y$1048576,$B15) -> 0 | R15: =SUM(C15:Q15) -> 30
B16: Cole | C16: =SUMIFS(Archives!$AF$2:$AF$1048576,Archives!$D$2:$D$1048576,1,Archives!$V$2:$V$1048576,$B16)+SUMIFS(Archives!$AF$2:$AF$1048576,Archives!$D$2:$D$1048576,1,Archives!$Y$2:$Y$1048576,$B16) -> 0 | D16: =SUMIFS(Archives!$AF$2:$AF$1048576,Archives!$D$2:$D$1048576,2,Archives!$V$2:$V$1048576,$B16)+SUMIFS(Archives!$AF$2:$AF$1048576,Archives!$D$2:$D$1048576,2,Archives!$Y$2:$Y$1048576,$B16) -> 0.5 | E16: =SUMIFS(Archives!$AF$2:$AF$1048576,Archives!$D$2:$D$1048576,3,Archives!$V$2:$V$1048576,$B16)+SUMIFS(Archives!$AF$2:$AF$1048576,Archives!$D$2:$D$1048576,3,Archives!$Y$2:$Y$1048576,$B16) -> 3.5 | F16: =SUMIFS(Archives!$AF$2:$AF$1048576,Archives!$D$2:$D$1048576,4,Archives!$V$2:$V$1048576,$B16)+SUMIFS(Archives!$AF$2:$AF$1048576,Archives!$D$2:$D$1048576,4,Archives!$Y$2:$Y$1048576,$B16) -> 2.5 | G16: =SUMIFS(Archives!$AF$2:$AF$1048576,Archives!$D$2:$D$1048576,5,Archives!$V$2:$V$1048576,$B16)+SUMIFS(Archives!$AF$2:$AF$1048576,Archives!$D$2:$D$1048576,5,Archives!$Y$2:$Y$1048576,$B16) -> 1 | H16: =SUMIFS(Archives!$AF$2:$AF$1048576,Archives!$D$2:$D$1048576,6,Archives!$V$2:$V$1048576,$B16)+SUMIFS(Archives!$AF$2:$AF$1048576,Archives!$D$2:$D$1048576,6,Archives!$Y$2:$Y$1048576,$B16) -> 4 | I16: =SUMIFS(Archives!$AF$2:$AF$1048576,Archives!$D$2:$D$1048576,7,Archives!$V$2:$V$1048576,$B16)+SUMIFS(Archives!$AF$2:$AF$1048576,Archives!$D$2:$D$1048576,7,Archives!$Y$2:$Y$1048576,$B16) -> 4.5 | J16: =SUMIFS(Archives!$AF$2:$AF$1048576,Archives!$D$2:$D$1048576,8,Archives!$V$2:$V$1048576,$B16)+SUMIFS(Archives!$AF$2:$AF$1048576,Archives!$D$2:$D$1048576,8,Archives!$Y$2:$Y$1048576,$B16) -> 3.5 | K16: =SUMIFS(Archives!$AF$2:$AF$1048576,Archives!$D$2:$D$1048576,9,Archives!$V$2:$V$1048576,$B16)+SUMIFS(Archives!$AF$2:$AF$1048576,Archives!$D$2:$D$1048576,9,Archives!$Y$2:$Y$1048576,$B16) -> 2.5 | L16: =SUMIFS(Archives!$AF$2:$AF$1048576,Archives!$D$2:$D$1048576,10,Archives!$V$2:$V$1048576,$B16)+SUMIFS(Archives!$AF$2:$AF$1048576,Archives!$D$2:$D$1048576,10,Archives!$Y$2:$Y$1048576,$B16) -> 4.5 | M16: =SUMIFS(Archives!$AF$2:$AF$1048576,Archives!$D$2:$D$1048576,11,Archives!$V$2:$V$1048576,$B16)+SUMIFS(Archives!$AF$2:$AF$1048576,Archives!$D$2:$D$1048576,11,Archives!$Y$2:$Y$1048576,$B16) -> 3.5 | N16: =SUMIFS(Archives!$AF$2:$AF$1048576,Archives!$D$2:$D$1048576,12,Archives!$V$2:$V$1048576,$B16)+SUMIFS(Archives!$AF$2:$AF$1048576,Archives!$D$2:$D$1048576,12,Archives!$Y$2:$Y$1048576,$B16) -> 0 | O16: =SUMIFS(Archives!$AF$2:$AF$1048576,Archives!$D$2:$D$1048576,13,Archives!$V$2:$V$1048576,$B16)+SUMIFS(Archives!$AF$2:$AF$1048576,Archives!$D$2:$D$1048576,13,Archives!$Y$2:$Y$1048576,$B16) -> 0 | P16: =SUMIFS(Archives!$AF$2:$AF$1048576,Archives!$D$2:$D$1048576,14,Archives!$V$2:$V$1048576,$B16)+SUMIFS(Archives!$AF$2:$AF$1048576,Archives!$D$2:$D$1048576,14,Archives!$Y$2:$Y$1048576,$B16) -> 0 | Q16: =SUMIFS(Archives!$AF$2:$AF$1048576,Archives!$D$2:$D$1048576,15,Archives!$V$2:$V$1048576,$B16)+SUMIFS(Archives!$AF$2:$AF$1048576,Archives!$D$2:$D$1048576,15,Archives!$Y$2:$Y$1048576,$B16) -> 0 | R16: =SUM(C16:Q16) -> 30
... B35: Macklin | C35: =SUMIFS(Archives!$AF$2:$AF$1048576,Archives!$D$2:$D$1048576,1,Archives!$V$2:$V$1048576,$B35)+SUMIFS(Archives!$AF$2:$AF$1048576,Archives!$D$2:$D$1048576,1,Archives!$Y$2:$Y$1048576,$B35) -> 1.5 | D35: =SUMIFS(Archives!$AF$2:$AF$1048576,Archives!$D$2:$D$1048576,2,Archives!$V$2:$V$1048576,$B35)+SUMIFS(Archives!$AF$2:$AF$1048576,Archives!$D$2:$D$1048576,2,Archives!$Y$2:$Y$1048576,$B35) -> 0 | E35: =SUMIFS(Archives!$AF$2:$AF$1048576,Archives!$D$2:$D$1048576,3,Archives!$V$2:$V$1048576,$B35)+SUMIFS(Archives!$AF$2:$AF$1048576,Archives!$D$2:$D$1048576,3,Archives!$Y$2:$Y$1048576,$B35) -> 0 | F35: =SUMIFS(Archives!$AF$2:$AF$1048576,Archives!$D$2:$D$1048576,4,Archives!$V$2:$V$1048576,$B35)+SUMIFS(Archives!$AF$2:$AF$1048576,Archives!$D$2:$D$1048576,4,Archives!$Y$2:$Y$1048576,$B35) -> 0 | G35: =SUMIFS(Archives!$AF$2:$AF$1048576,Archives!$D$2:$D$1048576,5,Archives!$V$2:$V$1048576,$B35)+SUMIFS(Archives!$AF$2:$AF$1048576,Archives!$D$2:$D$1048576,5,Archives!$Y$2:$Y$1048576,$B35) -> 0 | H35: =SUMIFS(Archives!$AF$2:$AF$1048576,Archives!$D$2:$D$1048576,6,Archives!$V$2:$V$1048576,$B35)+SUMIFS(Archives!$AF$2:$AF$1048576,Archives!$D$2:$D$1048576,6,Archives!$Y$2:$Y$1048576,$B35) -> 0 | I35: =SUMIFS(Archives!$AF$2:$AF$1048576,Archives!$D$2:$D$1048576,7,Archives!$V$2:$V$1048576,$B35)+SUMIFS(Archives!$AF$2:$AF$1048576,Archives!$D$2:$D$1048576,7,Archives!$Y$2:$Y$1048576,$B35) -> 0 | J35: =SUMIFS(Archives!$AF$2:$AF$1048576,Archives!$D$2:$D$1048576,8,Archives!$V$2:$V$1048576,$B35)+SUMIFS(Archives!$AF$2:$AF$1048576,Archives!$D$2:$D$1048576,8,Archives!$Y$2:$Y$1048576,$B35) -> 0 | K35: =SUMIFS(Archives!$AF$2:$AF$1048576,Archives!$D$2:$D$1048576,9,Archives!$V$2:$V$1048576,$B35)+SUMIFS(Archives!$AF$2:$AF$1048576,Archives!$D$2:$D$1048576,9,Archives!$Y$2:$Y$1048576,$B35) -> 0 | L35: =SUMIFS(Archives!$AF$2:$AF$1048576,Archives!$D$2:$D$1048576,10,Archives!$V$2:$V$1048576,$B35)+SUMIFS(Archives!$AF$2:$AF$1048576,Archives!$D$2:$D$1048576,10,Archives!$Y$2:$Y$1048576,$B35) -> 0 | M35: =SUMIFS(Archives!$AF$2:$AF$1048576,Archives!$D$2:$D$1048576,11,Archives!$V$2:$V$1048576,$B35)+SUMIFS(Archives!$AF$2:$AF$1048576,Archives!$D$2:$D$1048576,11,Archives!$Y$2:$Y$1048576,$B35) -> 0 | N35: =SUMIFS(Archives!$AF$2:$AF$1048576,Archives!$D$2:$D$1048576,12,Archives!$V$2:$V$1048576,$B35)+SUMIFS(Archives!$AF$2:$AF$1048576,Archives!$D$2:$D$1048576,12,Archives!$Y$2:$Y$1048576,$B35) -> 0 | O35: =SUMIFS(Archives!$AF$2:$AF$1048576,Archives!$D$2:$D$1048576,13,Archives!$V$2:$V$1048576,$B35)+SUMIFS(Archives!$AF$2:$AF$1048576,Archives!$D$2:$D$1048576,13,Archives!$Y$2:$Y$1048576,$B35) -> 0 | P35: =SUMIFS(Archives!$AF$2:$AF$1048576,Archives!$D$2:$D$1048576,14,Archives!$V$2:$V$1048576,$B35)+SUMIFS(Archives!$AF$2:$AF$1048576,Archives!$D$2:$D$1048576,14,Archives!$Y$2:$Y$1048576,$B35) -> 0 | Q35: =SUMIFS(Archives!$AF$2:$AF$1048576,Archives!$D$2:$D$1048576,15,Archives!$V$2:$V$1048576,$B35)+SUMIFS(Archives!$AF$2:$AF$1048576,Archives!$D$2:$D$1048576,15,Archives!$Y$2:$Y$1048576,$B35) -> 0 | R35: =SUM(C35:Q35) -> 1.5
B36: Total | C36: =SUM(C5:C35) -> 36 | D36: =SUM(D5:D35) -> 48 | E36: =SUM(E5:E35) -> 60 | F36: =SUM(F5:F35) -> 65 | G36: =SUM(G5:G35) -> 65 | H36: =SUM(H5:H35) -> 65 | I36: =SUM(I5:I35) -> 75 | J36: =SUM(J5:J35) -> 67.5 | ... R36: =SUM(R5:R35) -> 761.5

Sheet LifetimeLeaderboard
B1: Lifetime Leaderboard
B2: Live from Archives — points, record, and per-cup rate across all FBCs. Win % = (W + ½T) ÷ matches.
B4: Player | C4: Points | D4: W | E4: L | F4: T | G4: Win % | H4: Matches | I4: Cups | J4: Pts/Cup
B5: Connolly | C5: =SUMIFS(Archives!$AF$2:$AF$1048576,Archives!$V$2:$V$1048576,$B5)+SUMIFS(Archives!$AF$2:$AF$1048576,Archives!$Y$2:$Y$1048576,$B5) -> 50.5 | D5: =COUNTIFS(Archives!$AB$2:$AB$1048576,"W",Archives!$V$2:$V$1048576,$B5)+COUNTIFS(Archives!$AB$2:$AB$1048576,"W",Archives!$Y$2:$Y$1048576,$B5) -> 39 | E5: =COUNTIFS(Archives!$AB$2:$AB$1048576,"L",Archives!$V$2:$V$1048576,$B5)+COUNTIFS(Archives!$AB$2:$AB$1048576,"L",Archives!$Y$2:$Y$1048576,$B5) -> 23 | F5: =COUNTIFS(Archives!$AB$2:$AB$1048576,"T",Archives!$V$2:$V$1048576,$B5)+COUNTIFS(Archives!$AB$2:$AB$1048576,"T",Archives!$Y$2:$Y$1048576,$B5) -> 9 | G5: =IF(H5=0,0,(D5+0.5*F5)/H5) -> 0.61267606 | H5: =D5+E5+F5 -> 71 | I5: =SUMPRODUCT(--((COUNTIFS(Archives!$D$2:$D$1048576,{1,2,3,4,5,6,7,8,9,10,11,12,13,14,15,16,17,18,19,20,21,22,23,24,25,26,27,28,29,30,31,32,33,34,35,36,37,38,39,40},Archives!$V$2:$V$1048576,$B5)+COUNTIFS(Archives!$D$2:$D$1048576,{1,2,3,4,5,6,7,8,9,10,11,12,13,14,15,16,17,18,19,20,21,22,23,24,25,26,27,28,29,30,31,32,33,34,35,36,37,38,39,40},Archives!$Y$2:$Y$1048576,$B5))>0)) -> 12 | J5: =IF(I5=0,0,C5/I5) -> 4.2083333
B6: Ferrin | C6: =SUMIFS(Archives!$AF$2:$AF$1048576,Archives!$V$2:$V$1048576,$B6)+SUMIFS(Archives!$AF$2:$AF$1048576,Archives!$Y$2:$Y$1048576,$B6) -> 46 | D6: =COUNTIFS(Archives!$AB$2:$AB$1048576,"W",Archives!$V$2:$V$1048576,$B6)+COUNTIFS(Archives!$AB$2:$AB$1048576,"W",Archives!$Y$2:$Y$1048576,$B6) -> 38 | E6: =COUNTIFS(Archives!$AB$2:$AB$1048576,"L",Archives!$V$2:$V$1048576,$B6)+COUNTIFS(Archives!$AB$2:$AB$1048576,"L",Archives!$Y$2:$Y$1048576,$B6) -> 26 | F6: =COUNTIFS(Archives!$AB$2:$AB$1048576,"T",Archives!$V$2:$V$1048576,$B6)+COUNTIFS(Archives!$AB$2:$AB$1048576,"T",Archives!$Y$2:$Y$1048576,$B6) -> 7 | G6: =IF(H6=0,0,(D6+0.5*F6)/H6) -> 0.58450704 | H6: =D6+E6+F6 -> 71 | I6: =SUMPRODUCT(--((COUNTIFS(Archives!$D$2:$D$1048576,{1,2,3,4,5,6,7,8,9,10,11,12,13,14,15,16,17,18,19,20,21,22,23,24,25,26,27,28,29,30,31,32,33,34,35,36,37,38,39,40},Archives!$V$2:$V$1048576,$B6)+COUNTIFS(Archives!$D$2:$D$1048576,{1,2,3,4,5,6,7,8,9,10,11,12,13,14,15,16,17,18,19,20,21,22,23,24,25,26,27,28,29,30,31,32,33,34,35,36,37,38,39,40},Archives!$Y$2:$Y$1048576,$B6))>0)) -> 12 | J6: =IF(I6=0,0,C6/I6) -> 3.8333333
B7: Jackson | C7: =SUMIFS(Archives!$AF$2:$AF$1048576,Archives!$V$2:$V$1048576,$B7)+SUMIFS(Archives!$AF$2:$AF$1048576,Archives!$Y$2:$Y$1048576,$B7) -> 46 | D7: =COUNTIFS(Archives!$AB$2:$AB$1048576,"W",Archives!$V$2:$V$1048576,$B7)+COUNTIFS(Archives!$AB$2:$AB$1048576,"W",Archives!$Y$2:$Y$1048576,$B7) -> 39 | E7: =COUNTIFS(Archives!$AB$2:$AB$1048576,"L",Archives!$V$2:$V$1048576,$B7)+COUNTIFS(Archives!$AB$2:$AB$1048576,"L",Archives!$Y$2:$Y$1048576,$B7) -> 24 | F7: =COUNTIFS(Archives!$AB$2:$AB$1048576,"T",Archives!$V$2:$V$1048576,$B7)+COUNTIFS(Archives!$AB$2:$AB$1048576,"T",Archives!$Y$2:$Y$1048576,$B7) -> 8 | G7: =IF(H7=0,0,(D7+0.5*F7)/H7) -> 0.6056338 | H7: =D7+E7+F7 -> 71 | I7: =SUMPRODUCT(--((COUNTIFS(Archives!$D$2:$D$1048576,{1,2,3,4,5,6,7,8,9,10,11,12,13,14,15,16,17,18,19,20,21,22,23,24,25,26,27,28,29,30,31,32,33,34,35,36,37,38,39,40},Archives!$V$2:$V$1048576,$B7)+COUNTIFS(Archives!$D$2:$D$1048576,{1,2,3,4,5,6,7,8,9,10,11,12,13,14,15,16,17,18,19,20,21,22,23,24,25,26,27,28,29,30,31,32,33,34,35,36,37,38,39,40},Archives!$Y$2:$Y$1048576,$B7))>0)) -> 12 | J7: =IF(I7=0,0,C7/I7) -> 3.8333333
B8: Grise | C8: =SUMIFS(Archives!$AF$2:$AF$1048576,Archives!$V$2:$V$1048576,$B8)+SUMIFS(Archives!$AF$2:$AF$1048576,Archives!$Y$2:$Y$1048576,$B8) -> 43 | D8: =COUNTIFS(Archives!$AB$2:$AB$1048576,"W",Archives!$V$2:$V$1048576,$B8)+COUNTIFS(Archives!$AB$2:$AB$1048576,"W",Archives!$Y$2:$Y$1048576,$B8) -> 36 | E8: =COUNTIFS(Archives!$AB$2:$AB$1048576,"L",Archives!$V$2:$V$1048576,$B8)+COUNTIFS(Archives!$AB$2:$AB$1048576,"L",Archives!$Y$2:$Y$1048576,$B8) -> 29 | F8: =COUNTIFS(Archives!$AB$2:$AB$1048576,"T",Archives!$V$2:$V$1048576,$B8)+COUNTIFS(Archives!$AB$2:$AB$1048576,"T",Archives!$Y$2:$Y$1048576,$B8) -> 6 | G8: =IF(H8=0,0,(D8+0.5*F8)/H8) -> 0.54929577 | H8: =D8+E8+F8 -> 71 | I8: =SUMPRODUCT(--((COUNTIFS(Archives!$D$2:$D$1048576,{1,2,3,4,5,6,7,8,9,10,11,12,13,14,15,16,17,18,19,20,21,22,23,24,25,26,27,28,29,30,31,32,33,34,35,36,37,38,39,40},Archives!$V$2:$V$1048576,$B8)+COUNTIFS(Archives!$D$2:$D$1048576,{1,2,3,4,5,6,7,8,9,10,11,12,13,14,15,16,17,18,19,20,21,22,23,24,25,26,27,28,29,30,31,32,33,34,35,36,37,38,39,40},Archives!$Y$2:$Y$1048576,$B8))>0)) -> 12 | J8: =IF(I8=0,0,C8/I8) -> 3.5833333
B9: Forster | C9: =SUMIFS(Archives!$AF$2:$AF$1048576,Archives!$V$2:$V$1048576,$B9)+SUMIFS(Archives!$AF$2:$AF$1048576,Archives!$Y$2:$Y$1048576,$B9) -> 42 | D9: =COUNTIFS(Archives!$AB$2:$AB$1048576,"W",Archives!$V$2:$V$1048576,$B9)+COUNTIFS(Archives!$AB$2:$AB$1048576,"W",Archives!$Y$2:$Y$1048576,$B9) -> 34 | E9: =COUNTIFS(Archives!$AB$2:$AB$1048576,"L",Archives!$V$2:$V$1048576,$B9)+COUNTIFS(Archives!$AB$2:$AB$1048576,"L",Archives!$Y$2:$Y$1048576,$B9) -> 24 | F9: =COUNTIFS(Archives!$AB$2:$AB$1048576,"T",Archives!$V$2:$V$1048576,$B9)+COUNTIFS(Archives!$AB$2:$AB$1048576,"T",Archives!$Y$2:$Y$1048576,$B9) -> 7 | G9: =IF(H9=0,0,(D9+0.5*F9)/H9) -> 0.57692308 | H9: =D9+E9+F9 -> 65 | I9: =SUMPRODUCT(--((COUNTIFS(Archives!$D$2:$D$1048576,{1,2,3,4,5,6,7,8,9,10,11,12,13,14,15,16,17,18,19,20,21,22,23,24,25,26,27,28,29,30,31,32,33,34,35,36,37,38,39,40},Archives!$V$2:$V$1048576,$B9)+COUNTIFS(Archives!$D$2:$D$1048576,{1,2,3,4,5,6,7,8,9,10,11,12,13,14,15,16,17,18,19,20,21,22,23,24,25,26,27,28,29,30,31,32,33,34,35,36,37,38,39,40},Archives!$Y$2:$Y$1048576,$B9))>0)) -> 11 | J9: =IF(I9=0,0,C9/I9) -> 3.8181818
B10: Lynch | C10: =SUMIFS(Archives!$AF$2:$AF$1048576,Archives!$V$2:$V$1048576,$B10)+SUMIFS(Archives!$AF$2:$AF$1048576,Archives!$Y$2:$Y$1048576,$B10) -> 41 | D10: =COUNTIFS(Archives!$AB$2:$AB$1048576,"W",Archives!$V$2:$V$1048576,$B10)+COUNTIFS(Archives!$AB$2:$AB$1048576,"W",Archives!$Y$2:$Y$1048576,$B10) -> 35 | E10: =COUNTIFS(Archives!$AB$2:$AB$1048576,"L",Archives!$V$2:$V$1048576,$B10)+COUNTIFS(Archives!$AB$2:$AB$1048576,"L",Archives!$Y$2:$Y$1048576,$B10) -> 29 | F10: =COUNTIFS(Archives!$AB$2:$AB$1048576,"T",Archives!$V$2:$V$1048576,$B10)+COUNTIFS(Archives!$AB$2:$AB$1048576,"T",Archives!$Y$2:$Y$1048576,$B10) -> 7 | G10: =IF(H10=0,0,(D10+0.5*F10)/H10) -> 0.54225352 | H10: =D10+E10+F10 -> 71 | I10: =SUMPRODUCT(--((COUNTIFS(Archives!$D$2:$D$1048576,{1,2,3,4,5,6,7,8,9,10,11,12,13,14,15,16,17,18,19,20,21,22,23,24,25,26,27,28,29,30,31,32,33,34,35,36,37,38,39,40},Archives!$V$2:$V$1048576,$B10)+COUNTIFS(Archives!$D$2:$D$1048576,{1,2,3,4,5,6,7,8,9,10,11,12,13,14,15,16,17,18,19,20,21,22,23,24,25,26,27,28,29,30,31,32,33,34,35,36,37,38,39,40},Archives!$Y$2:$Y$1048576,$B10))>0)) -> 12 | J10: =IF(I10=0,0,C10/I10) -> 3.4166667
B11: Flanders | C11: =SUMIFS(Archives!$AF$2:$AF$1048576,Archives!$V$2:$V$1048576,$B11)+SUMIFS(Archives!$AF$2:$AF$1048576,Archives!$Y$2:$Y$1048576,$B11) -> 36.5 | D11: =COUNTIFS(Archives!$AB$2:$AB$1048576,"W",Archives!$V$2:$V$1048576,$B11)+COUNTIFS(Archives!$AB$2:$AB$1048576,"W",Archives!$Y$2:$Y$1048576,$B11) -> 29 | E11: =COUNTIFS(Archives!$AB$2:$AB$1048576,"L",Archives!$V$2:$V$1048576,$B11)+COUNTIFS(Archives!$AB$2:$AB$1048576,"L",Archives!$Y$2:$Y$1048576,$B11) -> 34 | F11: =COUNTIFS(Archives!$AB$2:$AB$1048576,"T",Archives!$V$2:$V$1048576,$B11)+COUNTIFS(Archives!$AB$2:$AB$1048576,"T",Archives!$Y$2:$Y$1048576,$B11) -> 8 | G11: =IF(H11=0,0,(D11+0.5*F11)/H11) -> 0.46478873 | H11: =D11+E11+F11 -> 71 | I11: =SUMPRODUCT(--((COUNTIFS(Archives!$D$2:$D$1048576,{1,2,3,4,5,6,7,8,9,10,11,12,13,14,15,16,17,18,19,20,21,22,23,24,25,26,27,28,29,30,31,32,33,34,35,36,37,38,39,40},Archives!$V$2:$V$1048576,$B11)+COUNTIFS(Archives!$D$2:$D$1048576,{1,2,3,4,5,6,7,8,9,10,11,12,13,14,15,16,17,18,19,20,21,22,23,24,25,26,27,28,29,30,31,32,33,34,35,36,37,38,39,40},Archives!$Y$2:$Y$1048576,$B11))>0)) -> 12 | J11: =IF(I11=0,0,C11/I11) -> 3.0416667
B12: Hilts | C12: =SUMIFS(Archives!$AF$2:$AF$1048576,Archives!$V$2:$V$1048576,$B12)+SUMIFS(Archives!$AF$2:$AF$1048576,Archives!$Y$2:$Y$1048576,$B12) -> 37 | D12: =COUNTIFS(Archives!$AB$2:$AB$1048576,"W",Archives!$V$2:$V$1048576,$B12)+COUNTIFS(Archives!$AB$2:$AB$1048576,"W",Archives!$Y$2:$Y$1048576,$B12) -> 28 | E12: =COUNTIFS(Archives!$AB$2:$AB$1048576,"L",Archives!$V$2:$V$1048576,$B12)+COUNTIFS(Archives!$AB$2:$AB$1048576,"L",Archives!$Y$2:$Y$1048576,$B12) -> 30 | F12: =COUNTIFS(Archives!$AB$2:$AB$1048576,"T",Archives!$V$2:$V$1048576,$B12)+COUNTIFS(Archives!$AB$2:$AB$1048576,"T",Archives!$Y$2:$Y$1048576,$B12) -> 7 | G12: =IF(H12=0,0,(D12+0.5*F12)/H12) -> 0.48461538 | H12: =D12+E12+F12 -> 65 | I12: =SUMPRODUCT(--((COUNTIFS(Archives!$D$2:$D$1048576,{1,2,3,4,5,6,7,8,9,10,11,12,13,14,15,16,17,18,19,20,21,22,23,24,25,26,27,28,29,30,31,32,33,34,35,36,37,38,39,40},Archives!$V$2:$V$1048576,$B12)+COUNTIFS(Archives!$D$2:$D$1048576,{1,2,3,4,5,6,7,8,9,10,11,12,13,14,15,16,17,18,19,20,21,22,23,24,25,26,27,28,29,30,31,32,33,34,35,36,37,38,39,40},Archives!$Y$2:$Y$1048576,$B12))>0)) -> 11 | J12: =IF(I12=0,0,C12/I12) -> 3.3636364
B13: Zimmer | C13: =SUMIFS(Archives!$AF$2:$AF$1048576,Archives!$V$2:$V$1048576,$B13)+SUMIFS(Archives!$AF$2:$AF$1048576,Archives!$Y$2:$Y$1048576,$B13) -> 32.5 | D13: =COUNTIFS(Archives!$AB$2:$AB$1048576,"W",Archives!$V$2:$V$1048576,$B13)+COUNTIFS(Archives!$AB$2:$AB$1048576,"W",Archives!$Y$2:$Y$1048576,$B13) -> 25 | E13: =COUNTIFS(Archives!$AB$2:$AB$1048576,"L",Archives!$V$2:$V$1048576,$B13)+COUNTIFS(Archives!$AB$2:$AB$1048576,"L",Archives!$Y$2:$Y$1048576,$B13) -> 29 | F13: =COUNTIFS(Archives!$AB$2:$AB$1048576,"T",Archives!$V$2:$V$1048576,$B13)+COUNTIFS(Archives!$AB$2:$AB$1048576,"T",Archives!$Y$2:$Y$1048576,$B13) -> 7 | G13: =IF(H13=0,0,(D13+0.5*F13)/H13) -> 0.46721311 | H13: =D13+E13+F13 -> 61 | I13: =SUMPRODUCT(--((COUNTIFS(Archives!$D$2:$D$1048576,{1,2,3,4,5,6,7,8,9,10,11,12,13,14,15,16,17,18,19,20,21,22,23,24,25,26,27,28,29,30,31,32,33,34,35,36,37,38,39,40},Archives!$V$2:$V$1048576,$B13)+COUNTIFS(Archives!$D$2:$D$1048576,{1,2,3,4,5,6,7,8,9,10,11,12,13,14,15,16,17,18,19,20,21,22,23,24,25,26,27,28,29,30,31,32,33,34,35,36,37,38,39,40},Archives!$Y$2:$Y$1048576,$B13))>0)) -> 10 | J13: =IF(I13=0,0,C13/I13) -> 3.25
B14: Gray | C14: =SUMIFS(Archives!$AF$2:$AF$1048576,Archives!$V$2:$V$1048576,$B14)+SUMIFS(Archives!$AF$2:$AF$1048576,Archives!$Y$2:$Y$1048576,$B14) -> 31 | D14: =COUNTIFS(Archives!$AB$2:$AB$1048576,"W",Archives!$V$2:$V$1048576,$B14)+COUNTIFS(Archives!$AB$2:$AB$1048576,"W",Archives!$Y$2:$Y$1048576,$B14) -> 24 | E14: =COUNTIFS(Archives!$AB$2:$AB$1048576,"L",Archives!$V$2:$V$1048576,$B14)+COUNTIFS(Archives!$AB$2:$AB$1048576,"L",Archives!$Y$2:$Y$1048576,$B14) -> 11 | F14: =COUNTIFS(Archives!$AB$2:$AB$1048576,"T",Archives!$V$2:$V$1048576,$B14)+COUNTIFS(Archives!$AB$2:$AB$1048576,"T",Archives!$Y$2:$Y$1048576,$B14) -> 7 | G14: =IF(H14=0,0,(D14+0.5*F14)/H14) -> 0.6547619 | H14: =D14+E14+F14 -> 42 | I14: =SUMPRODUCT(--((COUNTIFS(Archives!$D$2:$D$1048576,{1,2,3,4,5,6,7,8,9,10,11,12,13,14,15,16,17,18,19,20,21,22,23,24,25,26,27,28,29,30,31,32,33,34,35,36,37,38,39,40},Archives!$V$2:$V$1048576,$B14)+COUNTIFS(Archives!$D$2:$D$1048576,{1,2,3,4,5,6,7,8,9,10,11,12,13,14,15,16,17,18,19,20,21,22,23,24,25,26,27,28,29,30,31,32,33,34,35,36,37,38,39,40},Archives!$Y$2:$Y$1048576,$B14))>0)) -> 7 | J14: =IF(I14=0,0,C14/I14) -> 4.4285714
B15: Fogan | C15: =SUMIFS(Archives!$AF$2:$AF$1048576,Archives!$V$2:$V$1048576,$B15)+SUMIFS(Archives!$AF$2:$AF$1048576,Archives!$Y$2:$Y$1048576,$B15) -> 30 | D15: =COUNTIFS(Archives!$AB$2:$AB$1048576,"W",Archives!$V$2:$V$1048576,$B15)+COUNTIFS(Archives!$AB$2:$AB$1048576,"W",Archives!$Y$2:$Y$1048576,$B15) -> 24 | E15: =COUNTIFS(Archives!$AB$2:$AB$1048576,"L",Archives!$V$2:$V$1048576,$B15)+COUNTIFS(Archives!$AB$2:$AB$1048576,"L",Archives!$Y$2:$Y$1048576,$B15) -> 38 | F15: =COUNTIFS(Archives!$AB$2:$AB$1048576,"T",Archives!$V$2:$V$1048576,$B15)+COUNTIFS(Archives!$AB$2:$AB$1048576,"T",Archives!$Y$2:$Y$1048576,$B15) -> 4 | G15: =IF(H15=0,0,(D15+0.5*F15)/H15) -> 0.39393939 | H15: =D15+E15+F15 -> 66 | I15: =SUMPRODUCT(--((COUNTIFS(Archives!$D$2:$D$1048576,{1,2,3,4,5,6,7,8,9,10,11,12,13,14,15,16,17,18,19,20,21,22,23,24,25,26,27,28,29,30,31,32,33,34,35,36,37,38,39,40},Archives!$V$2:$V$1048576,$B15)+COUNTIFS(Archives!$D$2:$D$1048576,{1,2,3,4,5,6,7,8,9,10,11,12,13,14,15,16,17,18,19,20,21,22,23,24,25,26,27,28,29,30,31,32,33,34,35,36,37,38,39,40},Archives!$Y$2:$Y$1048576,$B15))>0)) -> 11 | J15: =IF(I15=0,0,C15/I15) -> 2.7272727
B16: Cole | C16: =SUMIFS(Archives!$AF$2:$AF$1048576,Archives!$V$2:$V$1048576,$B16)+SUMIFS(Archives!$AF$2:$AF$1048576,Archives!$Y$2:$Y$1048576,$B16) -> 30 | D16: =COUNTIFS(Archives!$AB$2:$AB$1048576,"W",Archives!$V$2:$V$1048576,$B16)+COUNTIFS(Archives!$AB$2:$AB$1048576,"W",Archives!$Y$2:$Y$1048576,$B16) -> 23 | E16: =COUNTIFS(Archives!$AB$2:$AB$1048576,"L",Archives!$V$2:$V$1048576,$B16)+COUNTIFS(Archives!$AB$2:$AB$1048576,"L",Archives!$Y$2:$Y$1048576,$B16) -> 30 | F16: =COUNTIFS(Archives!$AB$2:$AB$1048576,"T",Archives!$V$2:$V$1048576,$B16)+COUNTIFS(Archives!$AB$2:$AB$1048576,"T",Archives!$Y$2:$Y$1048576,$B16) -> 6 | G16: =IF(H16=0,0,(D16+0.5*F16)/H16) -> 0.44067797 | H16: =D16+E16+F16 -> 59 | I16: =SUMPRODUCT(--((COUNTIFS(Archives!$D$2:$D$1048576,{1,2,3,4,5,6,7,8,9,10,11,12,13,14,15,16,17,18,19,20,21,22,23,24,25,26,27,28,29,30,31,32,33,34,35,36,37,38,39,40},Archives!$V$2:$V$1048576,$B16)+COUNTIFS(Archives!$D$2:$D$1048576,{1,2,3,4,5,6,7,8,9,10,11,12,13,14,15,16,17,18,19,20,21,22,23,24,25,26,27,28,29,30,31,32,33,34,35,36,37,38,39,40},Archives!$Y$2:$Y$1048576,$B16))>0)) -> 10 | J16: =IF(I16=0,0,C16/I16) -> 3
... B35: Macklin | C35: =SUMIFS(Archives!$AF$2:$AF$1048576,Archives!$V$2:$V$1048576,$B35)+SUMIFS(Archives!$AF$2:$AF$1048576,Archives!$Y$2:$Y$1048576,$B35) -> 1.5 | D35: =COUNTIFS(Archives!$AB$2:$AB$1048576,"W",Archives!$V$2:$V$1048576,$B35)+COUNTIFS(Archives!$AB$2:$AB$1048576,"W",Archives!$Y$2:$Y$1048576,$B35) -> 1 | E35: =COUNTIFS(Archives!$AB$2:$AB$1048576,"L",Archives!$V$2:$V$1048576,$B35)+COUNTIFS(Archives!$AB$2:$AB$1048576,"L",Archives!$Y$2:$Y$1048576,$B35) -> 3 | F35: =COUNTIFS(Archives!$AB$2:$AB$1048576,"T",Archives!$V$2:$V$1048576,$B35)+COUNTIFS(Archives!$AB$2:$AB$1048576,"T",Archives!$Y$2:$Y$1048576,$B35) -> 1 | G35: =IF(H35=0,0,(D35+0.5*F35)/H35) -> 0.3 | H35: =D35+E35+F35 -> 5 | I35: =SUMPRODUCT(--((COUNTIFS(Archives!$D$2:$D$1048576,{1,2,3,4,5,6,7,8,9,10,11,12,13,14,15,16,17,18,19,20,21,22,23,24,25,26,27,28,29,30,31,32,33,34,35,36,37,38,39,40},Archives!$V$2:$V$1048576,$B35)+COUNTIFS(Archives!$D$2:$D$1048576,{1,2,3,4,5,6,7,8,9,10,11,12,13,14,15,16,17,18,19,20,21,22,23,24,25,26,27,28,29,30,31,32,33,34,35,36,37,38,39,40},Archives!$Y$2:$Y$1048576,$B35))>0)) -> 1 | J35: =IF(I35=0,0,C35/I35) -> 1.5
B36: Grand Total | C36: =SUM(C5:C35) -> 761.5 | D36: =SUM(D5:D35) -> 601 | E36: =SUM(E5:E35) -> 601 | F36: =SUM(F5:F35) -> 166 | G36: =IF(H36=0,0,(D36+0.5*F36)/H36) -> 0.5 | H36: =SUM(H5:H35) -> 1368

Sheet Bounties
C3: W/L/T
C4: The Hunted
C5: Sum of W
D6: Bussiculo | E6: Cole | F6: Connolly | G6: R. Connolly | H6: Connors | I6: Delaney | J6: Delneky | K6: DeOteris | L6: Ferrin | M6: Flanders | N6: Fogan | O6: Forster | P6: Gray | Q6: Grise | R6: Hickerson | S6: Hilts | T6: Jackson | U6: Lynch | V6: Macklin | W6: Mangold | X6: McInerney | Y6: Norat | Z6: Perkins | AA6: Piegari | AB6: Poirier | AC6: Shively | AD6: Snyder | AE6: Weisberger | AF6: Welker | AG6: Zimmer | AH6: Grand Total
C7: Bussiculo | F7: 0 | T7: 1 | AF7: 0 | AG7: 0 | AH7: 1
C8: Cole | H8: 2 | L8: 0 | O8: 0 | Q8: 0 | U8: 0 | W8: 1 | Y8: 1 | AC8: 1 | AH8: 5
C9: Connolly | D9: 1 | I9: 1 | P9: 0 | Q9: 2 | T9: 1 | X9: 1 | AC9: 0 | AF9: 1 | AG9: 1 | AH9: 8
C10: R. Connolly | N10: 1 | AC10: 1 | AH10: 2
B11: Bounty | C11: Connors | E11: 0 | K11: 0 | N11: 1 | R11: 1 | W11: 0 | AC11: 0 | AH11: 2
B12: Hunters | C12: Delaney | F12: 0 | J12: 1 | N12: 0 | S12: 0 | T12: 0 | W12: 1 | AH12: 2
C13: Delneky | I13: 0 | S13: 1 | U13: 1 | W13: 1 | X13: 0 | AH13: 3
C14: DeOteris | H14: 0 | AD14: 0 | AH14: 0
C15: Ferrin | E15: 1 | M15: 1 | O15: 0 | Q15: 1 | S15: 0 | U15: 0 | W15: 0 | X15: 0 | AC15: 2 | AE15: 1 | AH15: 6
C16: Flanders | L16: 0 | P16: 0 | V16: 1 | X16: 0 | Y16: 0 | AA16: 1 | AB16: 0 | AF16: 2 | AH16: 4
C17: Fogan | G17: 0 | H17: 3 | I17: 1 | O17: 0 | S17: 1 | Y17: 1 | AH17: 6
C18: Forster | E18: 1 | L18: 1 | N18: 1 | Q18: 0 | R18: 1 | S18: 1 | U18: 1 | Z18: 0 | AC18: 1 | AF18: 0 | AG18: 0 | AH18: 7
C19: Gray | F19: 2 | M19: 2 | S19: 0 | AF19: 1 | AG19: 0 | AH19: 5
C20: Grise | E20: 1 | F20: 0 | L20: 1 | O20: 1 | W20: 1 | X20: 0 | AB20: 0 | AC20: 1 | AE20: 1 | AH20: 6
C21: Hickerson | H21: 0 | O21: 0 | U21: 0 | Y21: 0 | AH21: 0
C22: Hilts | I22: 1 | J22: 0 | L22: 1 | N22: 0 | O22: 0 | P22: 1 | W22: 2 | AB22: 1 | AG22: 0 | AH22: 6
C23: Jackson | D23: 1 | F23: 0 | I23: 1 | U23: 1 | X23: 1 | AB23: 0 | AG23: 1 | AH23: 5
C24: Lynch | E24: 1 | J24: 0 | L24: 1 | O24: 0 | R24: 0 | T24: 1 | AB24: 0 | AC24: 1 | AE24: 0 | AF24: 0 | AH24: 4
C25: Macklin | M25: 0 | AH25: 0
C26: Mangold | E26: 0 | H26: 1 | I26: 0 | J26: 0 | L26: 0 | Q26: 0 | S26: 1 | AG26: 0 | AH26: 2
C27: McInerney | F27: 0 | J27: 1 | L27: 1 | M27: 1 | Q27: 1 | T27: 1 | Z27: 1 | AH27: 6
C28: Norat | E28: 0 | M28: 1 | N28: 2 | R28: 0 | AH28: 3
C29: Perkins | O29: 1 | X29: 0 | AA29: 1 | AG29: 1 | AH29: 3
C30: Piegari | M30: 0 | Z30: 0 | AH30: 0
C31: Poirier | M31: 1 | Q31: 2 | S31: 0 | T31: 1 | U31: 1 | AH31: 5
C32: Shively | E32: 0 | F32: 1 | G32: 0 | H32: 1 | L32: 0 | O32: 0 | Q32: 0 | U32: 1 | AG32: 0 | AH32: 3
C33: Snyder | K33: 1 | AH33: 1
C34: Weisberger | L34: 0 | Q34: 0 | U34: 1 | AH34: 1
C35: Welker | D35: 1 | F35: 1 | M35: 0 | O35: 1 | P35: 0 | U35: 1 | AH35: 4
C36: Zimmer | D36: 1 | F36: 0 | O36: 1 | P36: 0 | S36: 1 | T36: 1 | W36: 1 | Z36: 0 | AC36: 1 | AH36: 6
C37: Grand Total | D37: 4 | E37: 4 | F37: 4 | G37: 0 | H37: 7 | I37: 4 | J37: 2 | K37: 1 | L37: 5 | M37: 6 | N37: 5 | O37: 4 | P37: 1 | Q37: 6 | R37: 2 | S37: 5 | T37: 6 | U37: 7 | V37: 1 | W37: 7 | X37: 2 | Y37: 2 | Z37: 1 | AA37: 2 | AB37: 1 | AC37: 8 | AD37: 0 | AE37: 2 | AF37: 4 | AG37: 3 | AH37: 106

Sheet CAPA PPC
B1: CAPA PPC — Competitor-Adjusted, Partner-Adjusted Points Per Cup
B3: What it measures | C3: Expected points in a standard FBC 13-format cup (four 1-pt doubles matches, one 2-pt singles match, FTAS) with an average partner against average opponents. Through FBC13.
B4: Model | C4: Joint rating fit to all 401 head-to-head matches (FTAS excluded): side A share − 0.5 = mean(A ratings) − mean(B ratings), weighted by points at stake, ridge-regularized (λ=30, chosen by leave-one-cup-out cross-validation). CAPA = 3.25 + 4 × rating.
B5: Columns | C5: Raw = own results only, in standard-cup points. Partner / Opponent Adj = removes the help or hurt from partners’ and opponents’ ratings. Shrinkage = pull toward average for players with fewer matches. CAPA = Raw + Partner + Opponent + Shrinkage.
B6: Handicaps | C6: No separate handicap term. Strokes already level matches: adding an opponent-minus-own index term made out-of-sample predictions worse, so it was dropped (Oct 2026 revision).
B7: Precision | C7: The signal is weak: the model predicts match results about 2% better than a coin flip (the previous win%-based CAPA was worse than a coin flip at predicting the next cup). ± = one standard deviation; gaps smaller than that are noise. Min 24 matches.
B9: Player | C9: Cups | D9: Matches | E9: Raw PPC | F9: Partner Adj | G9: Opponent Adj | H9: Shrinkage | I9: CAPA PPC | J9: ± (1 SD)
B10: Gray | C10: 8 | D10: 48 | E10: 4.27 | F10: -0.03 | G10: 0.18 | H10: -0.64 | I10: =E10+F10+G10+H10 | J10: 0.25
B11: Connolly | C11: 13 | D11: 77 | E11: 3.9 | F11: 0 | G11: 0.11 | H11: -0.33 | I11: =E11+F11+G11+H11 | J11: 0.22
B12: Forster | C12: 12 | D12: 71 | E12: 3.85 | F12: -0.04 | G12: -0.02 | H12: -0.25 | I12: =E12+F12+G12+H12 | J12: 0.22
B13: Perkins | C13: 5 | D13: 31 | E13: 3.95 | F13: 0.05 | G13: 0.09 | H13: -0.55 | I13: =E13+F13+G13+H13 | J13: 0.27
B14: Ferrin | C14: 13 | D14: 77 | E14: 3.73 | F14: -0.01 | G14: 0.01 | H14: -0.2 | I14: =E14+F14+G14+H14 | J14: 0.22
B15: Welker | C15: 9 | D15: 55 | E15: 3.65 | F15: 0.03 | G15: 0.1 | H15: -0.28 | I15: =E15+F15+G15+H15 | J15: 0.24
B16: Jackson | C16: 13 | D16: 77 | E16: 3.62 | F16: -0.03 | G16: 0.07 | H16: -0.18 | I16: =E16+F16+G16+H16 | J16: 0.22
B17: McInerney | C17: 9 | D17: 54 | E17: 3.46 | F17: 0.02 | G17: 0.22 | H17: -0.23 | I17: =E17+F17+G17+H17 | J17: 0.24
B18: Delneky | C18: 6 | D18: 36 | E18: 3.91 | F18: -0.03 | G18: -0.06 | H18: -0.35 | I18: =E18+F18+G18+H18 | J18: 0.26
B19: Poirier | C19: 8 | D19: 49 | E19: 3.69 | F19: 0.01 | G19: -0.01 | H19: -0.24 | I19: =E19+F19+G19+H19 | J19: 0.24
B20: Grise | C20: 13 | D20: 77 | E20: 3.45 | F20: 0 | G20: 0.08 | H20: -0.12 | I20: =E20+F20+G20+H20 | J20: 0.22
B21: Norat | C21: 7 | D21: 42 | E21: 3.72 | F21: -0.05 | G21: -0.19 | H21: -0.13 | I21: =E21+F21+G21+H21 | J21: 0.25
... B33: Connors | C33: 10 | D33: 59 | E33: 2.27 | F33: -0.02 | G33: -0.22 | H33: 0.61 | I33: =E33+F33+G33+H33 | J33: 0.23
B35: Belts (through FBC13)
B36: 🐉 DragonSlayer | C36: McInerney | D36: Toughest opponents (largest opponent-skill boost)
B37: 🥄 Silver Spoon | C37: Norat | D37: Best partners — born on third base, thinks he hit a triple
B38: 🪨 Sisyphus | C38: Bussiculo | D38: Worst partners — pushing a rock uphill for eternity
B39: 🎒 Billy Madison | C39: Connors | D39: Easiest opponents — beating up on gradeschoolers

Sheet Sandbagger Index
B1: Sandbagger Index | I1: Beats-Card Model
B2: Who plays above their card. Sandbag Score = (Win% − 50%) × Avg Handicap. High = wins well despite a high handicap; negative = struggles despite getting strokes. Computed from Archives; min 10 matches. | I2: Win-probability points per match versus what the handicaps imply, using recorded match handicaps and correcting for the league-wide edge of the stroke-giving side. 90% range from bootstrap; min 15 matches.
B4: Player | C4: Avg Hcp | D4: Matches | E4: Win % | F4: Beats Card | G4: Sandbag Score | I4: Player | J4: Matches | K4: vs Card | L4: 90% Low | M4: 90% High | N4: Chance Above
B5: Delneky | C5: 17.7 | D5: 36 | E5: 0.625 | F5: 0.125 | G5: 2.21 | I5: Gray | J5: 42 | K5: 0.0556 | L5: 0.012 | M5: 0.0919 | N5: 0.985
B6: Forster | C6: 17.1 | D6: 71 | E6: 0.5845 | F6: 0.0845 | G6: 1.45 | I6: Connolly | J6: 65 | K6: 0.0542 | L6: 0.0078 | M6: 0.0988 | N6: 0.97
B7: Ferrin | C7: 15.4 | D7: 77 | E7: 0.5844 | F7: 0.0844 | G7: 1.3 | I7: Ferrin | J7: 67 | K7: 0.0527 | L7: 0.0054 | M7: 0.0983 | N7: 0.97
B8: Norat | C8: 17.8 | D8: 42 | E8: 0.5714 | F8: 0.0714 | G8: 1.27 | I8: Delneky | J8: 31 | K8: 0.0513 | L8: 0.0076 | M8: 0.0884 | N8: 0.975
B9: Jackson | C9: 10.8 | D9: 77 | E9: 0.6104 | F9: 0.1104 | G9: 1.2 | I9: Welker | J9: 47 | K9: 0.0431 | L9: -0.0062 | M9: 0.0927 | N9: 0.915
B10: Gray | C10: 8.5 | D10: 48 | E10: 0.625 | F10: 0.125 | G10: 1.06 | I10: Perkins | J10: 27 | K10: 0.0398 | L10: -0.0015 | M10: 0.0792 | N10: 0.9375
B11: Connolly | C11: 10.5 | D11: 77 | E11: 0.5974 | F11: 0.0974 | G11: 1.02 | I11: Forster | J11: 60 | K11: 0.0374 | L11: -0.0077 | M11: 0.0838 | N11: 0.91
B12: Perkins | C12: 7.9 | D12: 31 | E12: 0.5806 | F12: 0.0806 | G12: 0.64 | I12: Jackson | J12: 64 | K12: 0.0344 | L12: -0.0144 | M12: 0.0812 | N12: 0.8825
B13: Grise | C13: 12.4 | D13: 77 | E13: 0.5455 | F13: 0.0455 | G13: 0.56 | I13: Norat | J13: 36 | K13: 0.0179 | L13: -0.0228 | M13: 0.0577 | N13: 0.7325
B14: Lynch | C14: 12.3 | D14: 77 | E14: 0.5195 | F14: 0.0195 | G14: 0.24 | I14: Grise | J14: 67 | K14: 0.0118 | L14: -0.0404 | M14: 0.0587 | N14: 0.6325
B15: Welker | C15: 11.8 | D15: 55 | E15: 0.5182 | F15: 0.0182 | G15: 0.21 | I15: McInerney | J15: 47 | K15: 0.0102 | L15: -0.032 | M15: 0.0539 | N15: 0.6575
B16: Poirier | C16: 6.8 | D16: 49 | E16: 0.5204 | F16: 0.0204 | G16: 0.14 | I16: Hilts | J16: 60 | K16: 0.0099 | L16: -0.0404 | M16: 0.0593 | N16: 0.62
... B30: Hickerson | C30: 20 | D30: 21 | E30: 0.3571 | F30: -0.1429 | G30: -2.86 | I30: Shively | J30: 61 | K30: -0.0618 | L30: -0.1091 | M30: -0.0114 | N30: 0.02
I31: Connors | J31: 51 | K31: -0.0824 | L31: -0.1244 | M31: -0.0363 | N31: 0

Sheet Stroke Data
A1: FBC | B1: UniqueMatchID | C1: Format | D1: Format Group | E1: Holes | F1: Points at Stake | G1: Team | H1: Player 1 | I1: Player 2 | J1: Opponent 1 | K1: Opponent 2 | L1: Strokes Received (18) | M1: Strokes Received (Match) | N1: Stroke Status | O1: Points Earned | P1: Expected Points | Q1: Points vs Expected | R1: Stroke Source
A2: 1 | B2: FBC1-D1 | C2: Best Ball | D2: Four-ball | E2: 9 | F2: 1 | G2: Jackson | H2: Grise | I2: Hickerson | J2: Hilts | K2: Lynch | L2: -1.73 | M2: -0.86 | N2: Giving | O2: 1 | P2: 0.575 | Q2: 0.425 | R2: Index x slope (Handicaps tab)
A3: 1 | B3: FBC1-D1 | C3: Best Ball | D3: Four-ball | E3: 9 | F3: 1 | G3: Hilts | H3: Hilts | I3: Lynch | J3: Grise | K3: Hickerson | L3: 1.73 | M3: 0.86 | N3: Getting | O3: 0 | P3: 0.425 | Q3: -0.425 | R3: Index x slope (Handicaps tab)
A4: 1 | B4: FBC1-D2 | C4: Best Ball | D4: Four-ball | E4: 9 | F4: 1 | G4: Jackson | H4: Ferrin | I4: Jackson | J4: Macklin | K4: Poirier | L4: 10.35 | M4: 5.18 | N4: Getting | O4: 1 | P4: 0.453 | Q4: 0.547 | R4: Index x slope (Handicaps tab)
A5: 1 | B5: FBC1-D2 | C5: Best Ball | D5: Four-ball | E5: 9 | F5: 1 | G5: Hilts | H5: Macklin | I5: Poirier | J5: Ferrin | K5: Jackson | L5: -10.35 | M5: -5.18 | N5: Giving | O5: 0 | P5: 0.547 | Q5: -0.547 | R5: Index x slope (Handicaps tab)
A6: 1 | B6: FBC1-D3 | C6: Best Ball | D6: Four-ball | E6: 9 | F6: 1 | G6: Jackson | H6: Flanders | I6: Mangold | J6: Connolly | K6: Shively | L6: -8.63 | M6: -4.31 | N6: Giving | O6: 0 | P6: 0.553 | Q6: -0.553 | R6: Index x slope (Handicaps tab)
A7: 1 | B7: FBC1-D3 | C7: Best Ball | D7: Four-ball | E7: 9 | F7: 1 | G7: Hilts | H7: Connolly | I7: Shively | J7: Flanders | K7: Mangold | L7: 8.63 | M7: 4.31 | N7: Getting | O7: 1 | P7: 0.447 | Q7: 0.553 | R7: Index x slope (Handicaps tab)
A8: 1 | B8: FBC1-D4 | C8: Scramble | D8: Scramble | E8: 9 | F8: 1 | G8: Jackson | H8: Grise | I8: Hickerson | J8: Hilts | K8: Lynch | L8: 0 | M8: 0 | N8: Even | O8: 0.5 | P8: 0.5 | Q8: 0 | R8: Index x slope (Handicaps tab)
A9: 1 | B9: FBC1-D4 | C9: Scramble | D9: Scramble | E9: 9 | F9: 1 | G9: Hilts | H9: Hilts | I9: Lynch | J9: Grise | K9: Hickerson | L9: 0 | M9: 0 | N9: Even | O9: 0.5 | P9: 0.5 | Q9: 0 | R9: Index x slope (Handicaps tab)
A10: 1 | B10: FBC1-D5 | C10: Scramble | D10: Scramble | E10: 9 | F10: 1 | G10: Jackson | H10: Ferrin | I10: Jackson | J10: Macklin | K10: Poirier | L10: 0 | M10: 0 | N10: Even | O10: 0.5 | P10: 0.5 | Q10: 0 | R10: Index x slope (Handicaps tab)
A11: 1 | B11: FBC1-D5 | C11: Scramble | D11: Scramble | E11: 9 | F11: 1 | G11: Hilts | H11: Macklin | I11: Poirier | J11: Ferrin | K11: Jackson | L11: 0 | M11: 0 | N11: Even | O11: 0.5 | P11: 0.5 | Q11: 0 | R11: Index x slope (Handicaps tab)
A12: 1 | B12: FBC1-D6 | C12: Scramble | D12: Scramble | E12: 9 | F12: 1 | G12: Jackson | H12: Flanders | I12: Mangold | J12: Connolly | K12: Shively | L12: 0 | M12: 0 | N12: Even | O12: 0 | P12: 0.5 | Q12: -0.5 | R12: Index x slope (Handicaps tab)
A13: 1 | B13: FBC1-D6 | C13: Scramble | D13: Scramble | E13: 9 | F13: 1 | G13: Hilts | H13: Connolly | I13: Shively | J13: Flanders | K13: Mangold | L13: 0 | M13: 0 | N13: Even | O13: 1 | P13: 0.5 | Q13: 0.5 | R13: Index x slope (Handicaps tab)
... A25: 1 | B25: FBC1-D12 | C25: Best Ball | D25: Four-ball | E25: 9 | F25: 1 | G25: Jackson | H25: Flanders | I25: Mangold | J25: Connolly | K25: Shively | L25: -8.63 | M25: -4.31 | N25: Giving | O25: 0 | P25: 0.553 | Q25: -0.553 | R25: Index x slope (Handicaps tab)
A26: 1 | B26: FBC1-S-Connolly-Jackson | C26: Match Play | D26: Singles | E26: 18 | F26: 2 | G26: Hilts | H26: Connolly | J26: Jackson | L26: 0 | M26: 0 | N26: Even | O26: 2 | P26: 1 | Q26: 1 | R26: Index x slope (Handicaps tab)
A27: 1 | B27: FBC1-S-Connolly-Jackson | C27: Match Play | D27: Singles | E27: 18 | F27: 2 | G27: Jackson | H27: Jackson | J27: Connolly | L27: 0 | M27: 0 | N27: Even | O27: 0 | P27: 1 | Q27: -1 | R27: Index x slope (Handicaps tab)
A28: 1 | B28: FBC1-S-Ferrin-Shively | C28: Match Play | D28: Singles | E28: 18 | F28: 2 | G28: Hilts | H28: Shively | J28: Ferrin | L28: 2.27 | M28: 2.27 | N28: Getting | O28: 0 | P28: 0.883 | Q28: -0.883 | R28: Index x slope (Handicaps tab)
A29: 1 | B29: FBC1-S-Ferrin-Shively | C29: Match Play | D29: Singles | E29: 18 | F29: 2 | G29: Jackson | H29: Ferrin | J29: Shively | L29: -2.27 | M29: -2.27 | N29: Giving | O29: 2 | P29: 1.117 | Q29: 0.883 | R29: Index x slope (Handicaps tab)
A30: 1 | B30: FBC1-S-Flanders-Macklin | C30: Match Play | D30: Singles | E30: 18 | F30: 2 | G30: Jackson | H30: Flanders | J30: Macklin | L30: 0 | M30: 0 | N30: Even | O30: 2 | P30: 1 | Q30: 1 | R30: Index x slope (Handicaps tab)
A31: 1 | B31: FBC1-S-Flanders-Macklin | C31: Match Play | D31: Singles | E31: 18 | F31: 2 | G31: Hilts | H31: Macklin | J31: Flanders | L31: 0 | M31: 0 | N31: Even | O31: 0 | P31: 1 | Q31: -1 | R31: Index x slope (Handicaps tab)
A32: 1 | B32: FBC1-S-Grise-Poirier | C32: Match Play | D32: Singles | E32: 18 | F32: 2 | G32: Jackson | H32: Grise | J32: Poirier | L32: 5.66 | M32: 5.66 | N32: Getting | O32: 0 | P32: 0.949 | Q32: -0.949 | R32: Index x slope (Handicaps tab)
A33: 1 | B33: FBC1-S-Grise-Poirier | C33: Match Play | D33: Singles | E33: 18 | F33: 2 | G33: Hilts | H33: Poirier | J33: Grise | L33: -5.66 | M33: -5.66 | N33: Giving | O33: 2 | P33: 1.051 | Q33: 0.949 | R33: Index x slope (Handicaps tab)
A34: 1 | B34: FBC1-S-Hickerson-Lynch | C34: Match Play | D34: Singles | E34: 18 | F34: 2 | G34: Jackson | H34: Hickerson | J34: Lynch | L34: 0 | M34: 0 | N34: Even | O34: 1 | P34: 1 | Q34: 0 | R34: Index x slope (Handicaps tab)
A35: 1 | B35: FBC1-S-Hickerson-Lynch | C35: Match Play | D35: Singles | E35: 18 | F35: 2 | G35: Hilts | H35: Lynch | J35: Hickerson | L35: 0 | M35: 0 | N35: Even | O35: 1 | P35: 1 | Q35: 0 | R35: Index x slope (Handicaps tab)
A36: 1 | B36: FBC1-S-Hilts-Mangold | C36: Match Play | D36: Singles | E36: 18 | F36: 2 | G36: Hilts | H36: Hilts | J36: Mangold | L36: 3.4 | M36: 3.4 | N36: Getting | O36: 2 | P36: 0.905 | Q36: 1.095 | R36: Index x slope (Handicaps tab)
A37: 1 | B37: FBC1-S-Hilts-Mangold | C37: Match Play | D37: Singles | E37: 18 | F37: 2 | G37: Jackson | H37: Mangold | J37: Hilts | L37: -3.4 | M37: -3.4 | N37: Giving | O37: 0 | P37: 1.095 | Q37: -1.095 | R37: Index x slope (Handicaps tab)
A38: 2 | B38: FBC2-D3 | C38: Best Ball | D38: Four-ball | E38: 9 | F38: 1 | G38: Connolly | H38: Connolly | I38: Connors | J38: Cole | K38: Mangold | L38: -9.8 | M38: -4.9 | N38: Giving | O38: 0.5 | P38: 0.549 | Q38: -0.049 | R38: Index x slope (Handicaps tab)
A39: 2 | B39: FBC2-D3 | C39: Best Ball | D39: Four-ball | E39: 9 | F39: 1 | G39: Ferrin | H39: Cole | I39: Mangold | J39: Connolly | K39: Connors | L39: 9.8 | M39: 4.9 | N39: Getting | O39: 0.5 | P39: 0.451 | Q39: 0.049 | R39: Index x slope (Handicaps tab)
A40: 2 | B40: FBC2-D9 | C40: Hi-Lo | D40: Four-ball | E40: 9 | F40: 1 | G40: Connolly | H40: Forster | I40: Lynch | J40: Cole | K40: Ferrin | L40: -3.47 | M40: -1.74 | N40: Giving | O40: 1 | P40: 0.569 | Q40: 0.431 | R40: Index x slope (Handicaps tab)
A41: 2 | B41: FBC2-D9 | C41: Hi-Lo | D41: Four-ball | E41: 9 | F41: 1 | G41: Ferrin | H41: Cole | I41: Ferrin | J41: Forster | K41: Lynch | L41: 3.47 | M41: 1.74 | N41: Getting | O41: 0 | P41: 0.431 | Q41: -0.431 | R41: Index x slope (Handicaps tab)
A42: 2 | B42: FBC2-D12 | C42: Hi-Lo | D42: Four-ball | E42: 9 | F42: 1 | G42: Ferrin | H42: Mangold | I42: Shively | J42: Connors | K42: Grise | L42: 2.71 | M42: 1.35 | N42: Getting | O42: 1 | P42: 0.428 | Q42: 0.572 | R42: Index x slope (Handicaps tab)
A43: 2 | B43: FBC2-D12 | C43: Hi-Lo | D43: Four-ball | E43: 9 | F43: 1 | G43: Connolly | H43: Connors | I43: Grise | J43: Mangold | K43: Shively | L43: -2.71 | M43: -1.35 | N43: Giving | O43: 0 | P43: 0.572 | Q43: -0.572 | R43: Index x slope (Handicaps tab)
A44: 2 | B44: FBC2-D13 | C44: Scramble-Stableford | D44: Scramble | E44: 9 | F44: 1 | G44: Connolly | H44: Forster | I44: Lynch | J44: Cole | K44: Ferrin | L44: 0 | M44: 0 | N44: Even | O44: 1 | P44: 0.5 | Q44: 0.5 | R44: Index x slope (Handicaps tab)
A45: 2 | B45: FBC2-D13 | C45: Scramble-Stableford | D45: Scramble | E45: 9 | F45: 1 | G45: Ferrin | H45: Cole | I45: Ferrin | J45: Forster | K45: Lynch | L45: 0 | M45: 0 | N45: Even | O45: 0 | P45: 0.5 | Q45: -0.5 | R45: Index x slope (Handicaps tab)
A46: 2 | B46: FBC2-D16 | C46: Scramble-Stableford | D46: Scramble | E46: 9 | F46: 1 | G46: Ferrin | H46: Mangold | I46: Shively | J46: Connors | K46: Grise | L46: 0 | M46: 0 | N46: Even | O46: 0 | P46: 0.5 | Q46: -0.5 | R46: Index x slope (Handicaps tab)
A47: 2 | B47: FBC2-D16 | C47: Scramble-Stableford | D47: Scramble | E47: 9 | F47: 1 | G47: Connolly | H47: Connors | I47: Grise | J47: Mangold | K47: Shively | L47: 0 | M47: 0 | N47: Even | O47: 1 | P47: 0.5 | Q47: 0.5 | R47: Index x slope (Handicaps tab)
A48: 2 | B48: FBC2-S-Cole-Grise | C48: Match Play | D48: Singles | E48: 18 | F48: 2 | G48: Connolly | H48: Grise | J48: Cole | L48: -21.38 | M48: -21.38 | N48: Giving | O48: 2 | P48: 0.749 | Q48: 1.251 | R48: Index x slope (Handicaps tab)
A49: 2 | B49: FBC2-S-Cole-Grise | C49: Match Play | D49: Singles | E49: 18 | F49: 2 | G49: Ferrin | H49: Cole | J49: Grise | L49: 21.38 | M49: 21.38 | N49: Getting | O49: 0 | P49: 1.251 | Q49: -1.251 | R49: Index x slope (Handicaps tab)
A50: 2 | B50: FBC2-S-Connolly-Shively | C50: Match Play | D50: Singles | E50: 18 | F50: 2 | G50: Connolly | H50: Connolly | J50: Shively | L50: -10.98 | M50: -10.98 | N50: Giving | O50: 0 | P50: 0.947 | Q50: -0.947 | R50: Index x slope (Handicaps tab)
A51: 2 | B51: FBC2-S-Connolly-Shively | C51: Match Play | D51: Singles | E51: 18 | F51: 2 | G51: Ferrin | H51: Shively | J51: Connolly | L51: 10.98 | M51: 10.98 | N51: Getting | O51: 2 | P51: 1.053 | Q51: 0.947 | R51: Index x slope (Handicaps tab)
A52: 2 | B52: FBC2-S-Connors-Fogan | C52: Match Play | D52: Singles | E52: 18 | F52: 2 | G52: Connolly | H52: Connors | J52: Fogan | L52: -14.72 | M52: -14.72 | N52: Giving | O52: 0 | P52: 0.874 | Q52: -0.874 | R52: Index x slope (Handicaps tab)
A53: 2 | B53: FBC2-S-Connors-Fogan | C53: Match Play | D53: Singles | E53: 18 | F53: 2 | G53: Ferrin | H53: Fogan | J53: Connors | L53: 14.72 | M53: 14.72 | N53: Getting | O53: 2 | P53: 1.126 | Q53: 0.874 | R53: Index x slope (Handicaps tab)
A54: 2 | B54: FBC2-S-Ferrin-Flanders | C54: Match Play | D54: Singles | E54: 18 | F54: 2 | G54: Connolly | H54: Flanders | J54: Ferrin | L54: -6.42 | M54: -6.42 | N54: Giving | O54: 0 | P54: 1.036 | Q54: -1.036 | R54: Index x slope (Handicaps tab)
A55: 2 | B55: FBC2-S-Ferrin-Flanders | C55: Match Play | D55: Singles | E55: 18 | F55: 2 | G55: Ferrin | H55: Ferrin | J55: Flanders | L55: 6.42 | M55: 6.42 | N55: Getting | O55: 2 | P55: 0.964 | Q55: 1.036 | R55: Index x slope (Handicaps tab)
A56: 2 | B56: FBC2-S-Hilts-Mangold | C56: Match Play | D56: Singles | E56: 18 | F56: 2 | G56: Connolly | H56: Hilts | J56: Mangold | L56: 3.15 | M56: 3.15 | N56: Getting | O56: 0 | P56: 0.9 | Q56: -0.9 | R56: Index x slope (Handicaps tab)
A57: 2 | B57: FBC2-S-Hilts-Mangold | C57: Match Play | D57: Singles | E57: 18 | F57: 2 | G57: Ferrin | H57: Mangold | J57: Hilts | L57: -3.15 | M57: -3.15 | N57: Giving | O57: 2 | P57: 1.1 | Q57: 0.9 | R57: Index x slope (Handicaps tab)
A58: 3 | B58: FBC3-D1 | C58: Best Ball | D58: Four-ball | E58: 9 | F58: 1 | G58: Shively | H58: Ferrin | I58: Shively | J58: Connolly | K58: Hilts | L58: 6.5 | M58: 3.25 | N58: Getting | O58: 1 | P58: 0.441 | Q58: 0.559 | R58: FBC 8/Handicaps (FBC 8) (Final).xlsx [3 Results]
A59: 3 | B59: FBC3-D1 | C59: Best Ball | D59: Four-ball | E59: 9 | F59: 1 | G59: Lynch | H59: Connolly | I59: Hilts | J59: Ferrin | K59: Shively | L59: -6.5 | M59: -3.25 | N59: Giving | O59: 0 | P59: 0.559 | Q59: -0.559 | R59: FBC 8/Handicaps (FBC 8) (Final).xlsx [3 Results]
A60: 3 | B60: FBC3-D2 | C60: Best Ball | D60: Four-ball | E60: 9 | F60: 1 | G60: Lynch | H60: Fogan | I60: Weisberger | J60: Grise | K60: Jackson | L60: 8.5 | M60: 4.25 | N60: Getting | O60: 1 | P60: 0.447 | Q60: 0.553 | R60: FBC 8/Handicaps (FBC 8) (Final).xlsx [3 Results]
A61: 3 | B61: FBC3-D2 | C61: Best Ball | D61: Four-ball | E61: 9 | F61: 1 | G61: Shively | H61: Grise | I61: Jackson | J61: Fogan | K61: Weisberger | L61: -8.5 | M61: -4.25 | N61: Giving | O61: 0 | P61: 0.553 | Q61: -0.553 | R61: FBC 8/Handicaps (FBC 8) (Final).xlsx [3 Results]
A62: 3 | B62: FBC3-D3 | C62: Best Ball | D62: Four-ball | E62: 9 | F62: 1 | G62: Shively | H62: Flanders | I62: Forster | J62: Gray | K62: Zimmer | L62: 8 | M62: 4 | N62: Getting | O62: 0 | P62: 0.445 | Q62: -0.445 | R62: FBC 8/Handicaps (FBC 8) (Final).xlsx [3 Results]
A63: 3 | B63: FBC3-D3 | C63: Best Ball | D63: Four-ball | E63: 9 | F63: 1 | G63: Lynch | H63: Gray | I63: Zimmer | J63: Flanders | K63: Forster | L63: -8 | M63: -4 | N63: Giving | O63: 1 | P63: 0.555 | Q63: 0.445 | R63: FBC 8/Handicaps (FBC 8) (Final).xlsx [3 Results]
A64: 3 | B64: FBC3-D4 | C64: Best Ball | D64: Four-ball | E64: 9 | F64: 1 | G64: Lynch | H64: Hickerson | I64: Lynch | J64: Bussiculo | K64: Mangold | L64: 3 | M64: 1.5 | N64: Getting | O64: 1 | P64: 0.429 | Q64: 0.571 | R64: FBC 8/Handicaps (FBC 8) (Final).xlsx [3 Results]
A65: 3 | B65: FBC3-D4 | C65: Best Ball | D65: Four-ball | E65: 9 | F65: 1 | G65: Shively | H65: Bussiculo | I65: Mangold | J65: Hickerson | K65: Lynch | L65: -3 | M65: -1.5 | N65: Giving | O65: 0 | P65: 0.571 | Q65: -0.571 | R65: FBC 8/Handicaps (FBC 8) (Final).xlsx [3 Results]
A66: 3 | B66: FBC3-D5 | C66: Best Ball | D66: Four-ball | E66: 9 | F66: 1 | G66: Shively | H66: Connors | I66: Norat | J66: Cole | K66: McInerney | L66: 1 | M66: 0.5 | N66: Getting | O66: 0 | P66: 0.423 | Q66: -0.423 | R66: FBC 8/Handicaps (FBC 8) (Final).xlsx [3 Results]
A67: 3 | B67: FBC3-D5 | C67: Best Ball | D67: Four-ball | E67: 9 | F67: 1 | G67: Lynch | H67: Cole | I67: McInerney | J67: Connors | K67: Norat | L67: -1 | M67: -0.5 | N67: Giving | O67: 1 | P67: 0.577 | Q67: 0.423 | R67: FBC 8/Handicaps (FBC 8) (Final).xlsx [3 Results]
A68: 3 | B68: FBC3-D6 | C68: Hi-Lo | D68: Four-ball | E68: 9 | F68: 1 | G68: Shively | H68: Ferrin | I68: Shively | J68: Connolly | K68: Hilts | L68: 6.5 | M68: 3.25 | N68: Getting | O68: 0 | P68: 0.441 | Q68: -0.441 | R68: FBC 8/Handicaps (FBC 8) (Final).xlsx [3 Results]
A69: 3 | B69: FBC3-D6 | C69: Hi-Lo | D69: Four-ball | E69: 9 | F69: 1 | G69: Lynch | H69: Connolly | I69: Hilts | J69: Ferrin | K69: Shively | L69: -6.5 | M69: -3.25 | N69: Giving | O69: 1 | P69: 0.559 | Q69: 0.441 | R69: FBC 8/Handicaps (FBC 8) (Final).xlsx [3 Results]
... A97: 3 | B97: FBC3-D20 | C97: Scramble-Stableford | D97: Scramble | E97: 9 | F97: 1 | G97: Lynch | H97: Cole | I97: McInerney | J97: Forster | K97: Norat | L97: 0 | M97: 0 | N97: Even | O97: 0.5 | P97: 0.5 | Q97: 0 | R97: FBC 8/Handicaps (FBC 8) (Final).xlsx [3 Results]
A98: 3 | B98: FBC3-S-Bussiculo-Zimmer | C98: Match Play | D98: Singles | E98: 18 | F98: 2 | G98: Shively | H98: Bussiculo | J98: Zimmer | L98: -1 | M98: -1 | N98: Giving | O98: 0 | P98: 1.141 | Q98: -1.141 | R98: FBC 8/Handicaps (FBC 8) (Final).xlsx [3 Results]
A99: 3 | B99: FBC3-S-Bussiculo-Zimmer | C99: Match Play | D99: Singles | E99: 18 | F99: 2 | G99: Lynch | H99: Zimmer | J99: Bussiculo | L99: 1 | M99: 1 | N99: Getting | O99: 2 | P99: 0.859 | Q99: 1.141 | R99: FBC 8/Handicaps (FBC 8) (Final).xlsx [3 Results]
A100: 3 | B100: FBC3-S-Cole-Mangold | C100: Match Play | D100: Singles | E100: 18 | F100: 2 | G100: Shively | H100: Mangold | J100: Cole | L100: -10 | M100: -10 | N100: Giving | O100: 1 | P100: 0.966 | Q100: 0.034 | R100: FBC 8/Handicaps (FBC 8) (Final).xlsx [3 Results]
A101: 3 | B101: FBC3-S-Cole-Mangold | C101: Match Play | D101: Singles | E101: 18 | F101: 2 | G101: Lynch | H101: Cole | J101: Mangold | L101: 10 | M101: 10 | N101: Getting | O101: 1 | P101: 1.034 | Q101: -0.034 | R101: FBC 8/Handicaps (FBC 8) (Final).xlsx [3 Results]
A102: 3 | B102: FBC3-S-Connolly-Grise | C102: Match Play | D102: Singles | E102: 18 | F102: 2 | G102: Shively | H102: Grise | J102: Connolly | L102: 6 | M102: 6 | N102: Getting | O102: 0 | P102: 0.956 | Q102: -0.956 | R102: FBC 8/Handicaps (FBC 8) (Final).xlsx [3 Results]
A103: 3 | B103: FBC3-S-Connolly-Grise | C103: Match Play | D103: Singles | E103: 18 | F103: 2 | G103: Lynch | H103: Connolly | J103: Grise | L103: -6 | M103: -6 | N103: Giving | O103: 2 | P103: 1.044 | Q103: 0.956 | R103: FBC 8/Handicaps (FBC 8) (Final).xlsx [3 Results]
A104: 3 | B104: FBC3-S-Connors-Fogan | C104: Match Play | D104: Singles | E104: 18 | F104: 2 | G104: Shively | H104: Connors | J104: Fogan | L104: -10 | M104: -10 | N104: Giving | O104: 2 | P104: 0.966 | Q104: 1.034 | R104: FBC 8/Handicaps (FBC 8) (Final).xlsx [3 Results]
A105: 3 | B105: FBC3-S-Connors-Fogan | C105: Match Play | D105: Singles | E105: 18 | F105: 2 | G105: Lynch | H105: Fogan | J105: Connors | L105: 10 | M105: 10 | N105: Getting | O105: 0 | P105: 1.034 | Q105: -1.034 | R105: FBC 8/Handicaps (FBC 8) (Final).xlsx [3 Results]
A106: 3 | B106: FBC3-S-Ferrin-Weisberger | C106: Match Play | D106: Singles | E106: 18 | F106: 2 | G106: Shively | H106: Ferrin | J106: Weisberger | L106: 5 | M106: 5 | N106: Getting | O106: 2 | P106: 0.936 | Q106: 1.064 | R106: FBC 8/Handicaps (FBC 8) (Final).xlsx [3 Results]
A107: 3 | B107: FBC3-S-Ferrin-Weisberger | C107: Match Play | D107: Singles | E107: 18 | F107: 2 | G107: Lynch | H107: Weisberger | J107: Ferrin | L107: -5 | M107: -5 | N107: Giving | O107: 0 | P107: 1.064 | Q107: -1.064 | R107: FBC 8/Handicaps (FBC 8) (Final).xlsx [3 Results]
A108: 3 | B108: FBC3-S-Flanders-Gray | C108: Match Play | D108: Singles | E108: 18 | F108: 2 | G108: Shively | H108: Flanders | J108: Gray | L108: 3 | M108: 3 | N108: Getting | O108: 0 | P108: 0.897 | Q108: -0.897 | R108: FBC 8/Handicaps (FBC 8) (Final).xlsx [3 Results]
A109: 3 | B109: FBC3-S-Flanders-Gray | C109: Match Play | D109: Singles | E109: 18 | F109: 2 | G109: Lynch | H109: Gray | J109: Flanders | L109: -3 | M109: -3 | N109: Giving | O109: 2 | P109: 1.103 | Q109: 0.897 | R109: FBC 8/Handicaps (FBC 8) (Final).xlsx [3 Results]
... A117: 3 | B117: FBC3-S-Lynch-Shively | C117: Match Play | D117: Singles | E117: 18 | F117: 2 | G117: Lynch | H117: Lynch | J117: Shively | L117: -2 | M117: -2 | N117: Giving | O117: 2 | P117: 1.122 | Q117: 0.878 | R117: FBC 8/Handicaps (FBC 8) (Final).xlsx [3 Results]
A118: 4 | B118: FBC4-D1 | C118: Best Ball | D118: Four-ball | E118: 9 | F118: 1 | G118: Mangold | H118: Ferrin | I118: Jackson | J118: Grise | K118: Welker | L118: 2 | M118: 1 | N118: Getting | O118: 0 | P118: 0.426 | Q118: -0.426 | R118: FBC 8/Handicaps (FBC 8) (Final).xlsx [4 Results]
A119: 4 | B119: FBC4-D1 | C119: Best Ball | D119: Four-ball | E119: 9 | F119: 1 | G119: Grise | H119: Grise | I119: Welker | J119: Ferrin | K119: Jackson | L119: -2 | M119: -1 | N119: Giving | O119: 1 | P119: 0.574 | Q119: 0.426 | R119: FBC 8/Handicaps (FBC 8) (Final).xlsx [4 Results]
A120: 4 | B120: FBC4-D2 | C120: Best Ball | D120: Four-ball | E120: 9 | F120: 1 | G120: Grise | H120: Bussiculo | I120: Shively | J120: Mangold | K120: Weisberger | L120: 0.5 | M120: 0.25 | N120: Even | O120: 1 | P120: 0.502 | Q120: 0.498 | R120: FBC 8/Handicaps (FBC 8) (Final).xlsx [4 Results]
A121: 4 | B121: FBC4-D2 | C121: Best Ball | D121: Four-ball | E121: 9 | F121: 1 | G121: Mangold | H121: Mangold | I121: Weisberger | J121: Bussiculo | K121: Shively | L121: -0.5 | M121: -0.25 | N121: Even | O121: 0 | P121: 0.498 | Q121: -0.498 | R121: FBC 8/Handicaps (FBC 8) (Final).xlsx [4 Results]
A122: 4 | B122: FBC4-D3 | C122: Best Ball | D122: Four-ball | E122: 9 | F122: 1 | G122: Mangold | H122: Flanders | I122: Forster | J122: Hickerson | K122: McInerney | L122: 0.5 | M122: 0.25 | N122: Even | O122: 1 | P122: 0.502 | Q122: 0.498 | R122: FBC 8/Handicaps (FBC 8) (Final).xlsx [4 Results]
A123: 4 | B123: FBC4-D3 | C123: Best Ball | D123: Four-ball | E123: 9 | F123: 1 | G123: Grise | H123: Hickerson | I123: McInerney | J123: Flanders | K123: Forster | L123: -0.5 | M123: -0.25 | N123: Even | O123: 0 | P123: 0.498 | Q123: -0.498 | R123: FBC 8/Handicaps (FBC 8) (Final).xlsx [4 Results]
A124: 4 | B124: FBC4-D4 | C124: Best Ball | D124: Four-ball | E124: 9 | F124: 1 | G124: Grise | H124: Connolly | I124: Zimmer | J124: Cole | K124: Connors | L124: -9.5 | M124: -4.75 | N124: Giving | O124: 1 | P124: 0.55 | Q124: 0.45 | R124: FBC 8/Handicaps (FBC 8) (Final).xlsx [4 Results]
A125: 4 | B125: FBC4-D4 | C125: Best Ball | D125: Four-ball | E125: 9 | F125: 1 | G125: Mangold | H125: Cole | I125: Connors | J125: Connolly | K125: Zimmer | L125: 9.5 | M125: 4.75 | N125: Getting | O125: 0 | P125: 0.45 | Q125: -0.45 | R125: FBC 8/Handicaps (FBC 8) (Final).xlsx [4 Results]
A126: 4 | B126: FBC4-D5 | C126: Best Ball | D126: Four-ball | E126: 9 | F126: 1 | G126: Mangold | H126: Gray | I126: Norat | J126: Fogan | K126: Lynch | L126: -7.5 | M126: -3.75 | N126: Giving | O126: 0 | P126: 0.556 | Q126: -0.556 | R126: FBC 8/Handicaps (FBC 8) (Final).xlsx [4 Results]
A127: 4 | B127: FBC4-D5 | C127: Best Ball | D127: Four-ball | E127: 9 | F127: 1 | G127: Grise | H127: Fogan | I127: Lynch | J127: Gray | K127: Norat | L127: 7.5 | M127: 3.75 | N127: Getting | O127: 1 | P127: 0.444 | Q127: 0.556 | R127: FBC 8/Handicaps (FBC 8) (Final).xlsx [4 Results]
A128: 4 | B128: FBC4-D6 | C128: Hi-Lo | D128: Four-ball | E128: 9 | F128: 1 | G128: Mangold | H128: Ferrin | I128: Jackson | J128: Grise | K128: Welker | L128: 2 | M128: 1 | N128: Getting | O128: 0 | P128: 0.426 | Q128: -0.426 | R128: FBC 8/Handicaps (FBC 8) (Final).xlsx [4 Results]
A129: 4 | B129: FBC4-D6 | C129: Hi-Lo | D129: Four-ball | E129: 9 | F129: 1 | G129: Grise | H129: Grise | I129: Welker | J129: Ferrin | K129: Jackson | L129: -2 | M129: -1 | N129: Giving | O129: 1 | P129: 0.574 | Q129: 0.426 | R129: FBC 8/Handicaps (FBC 8) (Final).xlsx [4 Results]
... A157: 4 | B157: FBC4-D20 | C157: Scramble-Stableford | D157: Scramble | E157: 9 | F157: 1 | G157: Grise | H157: Fogan | I157: Hickerson | J157: Cole | K157: Weisberger | L157: 0 | M157: 0 | N157: Even | O157: 0 | P157: 0.5 | Q157: -0.5 | R157: FBC 8/Handicaps (FBC 8) (Final).xlsx [4 Results]
A158: 4 | B158: FBC4-S-Bussiculo-Jackson | C158: Match Play | D158: Singles | E158: 18 | F158: 2 | G158: Mangold | H158: Jackson | J158: Bussiculo | L158: 1 | M158: 1 | N158: Getting | O158: 0 | P158: 0.859 | Q158: -0.859 | R158: FBC 8/Handicaps (FBC 8) (Final).xlsx [4 Results]
A159: 4 | B159: FBC4-S-Bussiculo-Jackson | C159: Match Play | D159: Singles | E159: 18 | F159: 2 | G159: Grise | H159: Bussiculo | J159: Jackson | L159: -1 | M159: -1 | N159: Giving | O159: 2 | P159: 1.141 | Q159: 0.859 | R159: FBC 8/Handicaps (FBC 8) (Final).xlsx [4 Results]
A160: 4 | B160: FBC4-S-Cole-Lynch | C160: Match Play | D160: Singles | E160: 18 | F160: 2 | G160: Mangold | H160: Cole | J160: Lynch | L160: 10 | M160: 10 | N160: Getting | O160: 0 | P160: 1.034 | Q160: -1.034 | R160: FBC 8/Handicaps (FBC 8) (Final).xlsx [4 Results]
A161: 4 | B161: FBC4-S-Cole-Lynch | C161: Match Play | D161: Singles | E161: 18 | F161: 2 | G161: Grise | H161: Lynch | J161: Cole | L161: -10 | M161: -10 | N161: Giving | O161: 2 | P161: 0.966 | Q161: 1.034 | R161: FBC 8/Handicaps (FBC 8) (Final).xlsx [4 Results]
A162: 4 | B162: FBC4-S-Connolly-Gray | C162: Match Play | D162: Singles | E162: 18 | F162: 2 | G162: Mangold | H162: Gray | J162: Connolly | L162: -1 | M162: -1 | N162: Giving | O162: 2 | P162: 1.141 | Q162: 0.859 | R162: FBC 8/Handicaps (FBC 8) (Final).xlsx [4 Results]
A163: 4 | B163: FBC4-S-Connolly-Gray | C163: Match Play | D163: Singles | E163: 18 | F163: 2 | G163: Grise | H163: Connolly | J163: Gray | L163: 1 | M163: 1 | N163: Getting | O163: 0 | P163: 0.859 | Q163: -0.859 | R163: FBC 8/Handicaps (FBC 8) (Final).xlsx [4 Results]
A164: 4 | B164: FBC4-S-Connors-Hickerson | C164: Match Play | D164: Singles | E164: 18 | F164: 2 | G164: Mangold | H164: Connors | J164: Hickerson | L164: -5 | M164: -5 | N164: Giving | O164: 2 | P164: 1.064 | Q164: 0.936 | R164: FBC 8/Handicaps (FBC 8) (Final).xlsx [4 Results]
A165: 4 | B165: FBC4-S-Connors-Hickerson | C165: Match Play | D165: Singles | E165: 18 | F165: 2 | G165: Grise | H165: Hickerson | J165: Connors | L165: 5 | M165: 5 | N165: Getting | O165: 0 | P165: 0.936 | Q165: -0.936 | R165: FBC 8/Handicaps (FBC 8) (Final).xlsx [4 Results]
A166: 4 | B166: FBC4-S-Ferrin-McInerney | C166: Match Play | D166: Singles | E166: 18 | F166: 2 | G166: Mangold | H166: Ferrin | J166: McInerney | L166: 10 | M166: 10 | N166: Getting | O166: 0 | P166: 1.034 | Q166: -1.034 | R166: FBC 8/Handicaps (FBC 8) (Final).xlsx [4 Results]
A167: 4 | B167: FBC4-S-Ferrin-McInerney | C167: Match Play | D167: Singles | E167: 18 | F167: 2 | G167: Grise | H167: McInerney | J167: Ferrin | L167: -10 | M167: -10 | N167: Giving | O167: 2 | P167: 0.966 | Q167: 1.034 | R167: FBC 8/Handicaps (FBC 8) (Final).xlsx [4 Results]
A168: 4 | B168: FBC4-S-Flanders-Welker | C168: Match Play | D168: Singles | E168: 18 | F168: 2 | G168: Mangold | H168: Flanders | J168: Welker | L168: -6 | M168: -6 | N168: Giving | O168: 2 | P168: 1.044 | Q168: 0.956 | R168: FBC 8/Handicaps (FBC 8) (Final).xlsx [4 Results]
A169: 4 | B169: FBC4-S-Flanders-Welker | C169: Match Play | D169: Singles | E169: 18 | F169: 2 | G169: Grise | H169: Welker | J169: Flanders | L169: 6 | M169: 6 | N169: Getting | O169: 0 | P169: 0.956 | Q169: -0.956 | R169: FBC 8/Handicaps (FBC 8) (Final).xlsx [4 Results]
... A177: 4 | B177: FBC4-S-Mangold-Zimmer | C177: Match Play | D177: Singles | E177: 18 | F177: 2 | G177: Grise | H177: Zimmer | J177: Mangold | L177: -5 | M177: -5 | N177: Giving | O177: 2 | P177: 1.064 | Q177: 0.936 | R177: FBC 8/Handicaps (FBC 8) (Final).xlsx [4 Results]
A178: 5 | B178: FBC5-D1 | C178: Best Ball | D178: Four-ball | E178: 9 | F178: 1 | G178: Poirier | H178: Gray | I178: Poirier | J178: Delaney | K178: Mangold | L178: -7 | M178: -3.5 | N178: Giving | O178: 0 | P178: 0.558 | Q178: -0.558 | R178: FBC 8/Handicaps (FBC 8) (Final).xlsx [5 Results]
A179: 5 | B179: FBC5-D1 | C179: Best Ball | D179: Four-ball | E179: 9 | F179: 1 | G179: Forster | H179: Delaney | I179: Mangold | J179: Gray | K179: Poirier | L179: 7 | M179: 3.5 | N179: Getting | O179: 1 | P179: 0.442 | Q179: 0.558 | R179: FBC 8/Handicaps (FBC 8) (Final).xlsx [5 Results]
...

Sheet Chemistry Index
B1: Chemistry Index
B2: Doubles pairings that beat (or fall short of) their combined talent. Chemistry = tandem win% − the average of the two partners’ individual career win%. Min 4 matches together.
B4: Tandem | C4: Matches | D4: Tandem Win % | E4: Expected | F4: Chemistry
B5: Mangold / Perkins | C5: 4 | D5: 0.875 | E5: 0.4945 | F5: 0.3805
B6: Ferrin / Flanders | C6: 8 | D6: 0.875 | E6: 0.5357 | F6: 0.3393
B7: Delaney / Perkins | C7: 4 | D7: 0.875 | E7: 0.5403 | F7: 0.3347
B8: Connolly / Jackson | C8: 4 | D8: 0.875 | E8: 0.6039 | F8: 0.2711
B9: Connolly / R. Connolly | C9: 4 | D9: 0.75 | E9: 0.5355 | F9: 0.2145
B10: Bussiculo / Shively | C10: 4 | D10: 0.625 | E10: 0.4213 | F10: 0.2037
B11: Connors / Welker | C11: 4 | D11: 0.625 | E11: 0.4328 | F11: 0.1922
B12: DeOteris / Ferrin | C12: 6 | D12: 0.6667 | E12: 0.4797 | F12: 0.187
B13: Hilts / Lynch | C13: 11 | D13: 0.6818 | E13: 0.5027 | F13: 0.1791
B14: Connolly / Grise | C14: 4 | D14: 0.75 | E14: 0.5714 | F14: 0.1786
B15: Grise / Hickerson | C15: 4 | D15: 0.625 | E15: 0.4513 | F15: 0.1737
B16: Grise / Jackson | C16: 10 | D16: 0.75 | E16: 0.5779 | F16: 0.1721
... B65: Fogan / McInerney | C65: 4 | D65: 0 | E65: 0.4421 | F65: -0.4421

Sheet Clutch Rating
B1: Clutch Rating
B2: Performance weighted by what’s at stake (Saturday singles = 2 pts, Friday = 1, FTAS = 0.5). Clutch Δ = stakes-weighted win% − flat win%. Positive = raises their game when more is on the line. Min 10 matches.
B4: Player | C4: Matches | D4: Win % | E4: High-Leverage Win % | F4: Clutch Δ
B5: Welker | C5: 55 | D5: 0.5182 | E5: 0.55 | F5: 0.0318
B6: Perkins | C6: 31 | D6: 0.5806 | E6: 0.6087 | F6: 0.0281
B7: Gray | C7: 48 | D7: 0.625 | E7: 0.6509 | F7: 0.0259
B8: Poirier | C8: 49 | D8: 0.5204 | E8: 0.5463 | F8: 0.0259
B9: Hilts | C9: 71 | D9: 0.4859 | E9: 0.5094 | F9: 0.0235
B10: McInerney | C10: 54 | D10: 0.4815 | E10: 0.5042 | F10: 0.0227
B11: Cole | C11: 65 | D11: 0.4538 | E11: 0.4722 | F11: 0.0184
B12: R. Connolly | C12: 19 | D12: 0.4737 | E12: 0.4884 | F12: 0.0147
B13: Connolly | C13: 77 | D13: 0.5974 | E13: 0.6105 | F13: 0.0131
B14: Forster | C14: 71 | D14: 0.5845 | E14: 0.5962 | F14: 0.0116
B15: Fogan | C15: 72 | D15: 0.4028 | E15: 0.4125 | F15: 0.0097
B16: Zimmer | C16: 67 | D16: 0.4478 | E16: 0.4527 | F16: 0.0049
... B32: Bussiculo | C32: 29 | D32: 0.4483 | E32: 0.4 | F32: -0.0483

Sheet Pythagorean Luck
B1: Pythagorean Luck
B2: Cups won vs. cups deserved. Expected wins from each cup’s team points for/against (Pythagorean expectation, exp. 2). Luck = actual − expected. Positive = won more cups than margins predict (clutch/fortunate in tight cups); negative = strong margins, unlucky finishes. Min 4 cups.
B4: Player | C4: Cups | D4: Cups Won | E4: Expected | F4: Luck
B5: Lynch | C5: 13 | D5: 10 | E5: 7.03 | F5: 2.97
B6: Connolly | C6: 13 | D6: 10 | E6: 7.28 | F6: 2.72
B7: Hilts | C7: 12 | D7: 9 | E7: 6.52 | F7: 2.48
B8: Grise | C8: 13 | D8: 9 | E8: 6.85 | F8: 2.15
B9: Delaney | C9: 7 | D9: 5 | E9: 3.69 | F9: 1.31
B10: Zimmer | C10: 11 | D10: 7 | E10: 5.91 | F10: 1.09
B11: Perkins | C11: 5 | D11: 4 | E11: 2.98 | F11: 1.02
B12: Shively | C12: 12 | D12: 7 | E12: 6.27 | F12: 0.73
B13: McInerney | C13: 9 | D13: 5 | E13: 4.69 | F13: 0.31
B14: Bussiculo | C14: 6 | D14: 3 | E14: 2.92 | F14: 0.08
B15: Hickerson | C15: 4 | D15: 2 | E15: 1.98 | F15: 0.02
B16: Poirier | C16: 8 | D16: 4 | E16: 3.99 | F16: 0.01
... B29: Jackson | C29: 13 | D29: 3 | E29: 5.73 | F29: -2.73

Sheet Form Guide
B1: Form Guide
B2: Who’s heating up going into FBC 14. PPC = points per cup. Last 3 = the three most recent cups each player appeared in. Form = recent − career. Sorted by current form. Min 4 cups.
B4: Player | C4: Cups | D4: Career PPC | E4: Last 3 PPC | F4: Form Δ | G4: Trend
B5: Connolly | C5: 13 | D5: 4.04 | E5: 4.5 | F5: 0.46 | G5: — Steady
B6: Delneky | C6: 6 | D6: 4.08 | E6: 4.5 | F6: 0.42 | G6: — Steady
B7: Hilts | C7: 12 | D7: 3.38 | E7: 4.5 | F7: 1.12 | G7: ▲ Hot
B8: Poirier | C8: 8 | D8: 3.69 | E8: 4.5 | F8: 0.81 | G8: ▲ Hot
B9: Welker | C9: 9 | D9: 3.67 | E9: 4.5 | F9: 0.83 | G9: ▲ Hot
B10: Ferrin | C10: 13 | D10: 3.88 | E10: 4.33 | F10: 0.45 | G10: — Steady
B11: Flanders | C11: 13 | D11: 3.19 | E11: 4.33 | F11: 1.14 | G11: ▲ Hot
B12: Norat | C12: 7 | D12: 3.79 | E12: 4.17 | F12: 0.38 | G12: — Steady
B13: Cole | C13: 11 | D13: 3.09 | E13: 4 | F13: 0.91 | G13: ▲ Hot
B14: Forster | C14: 12 | D14: 3.88 | E14: 4 | F14: 0.12 | G14: — Steady
B15: Fogan | C15: 12 | D15: 2.75 | E15: 3.83 | F15: 1.08 | G15: ▲ Hot
B16: Gray | C16: 8 | D16: 4.31 | E16: 3.83 | F16: -0.48 | G16: — Steady
... B29: Zimmer | C29: 11 | D29: 3.05 | E29: 1.67 | F29: -1.38 | G29: ▼ Cold

Sheet MVP Hall of Fame
B1: MVP Hall of Fame
B2: Every undefeated individual cup in FBC history — zero match losses, ties allowed (min 3 matches). Ranked by points earned.
B4: Rank | C4: Player | D4: Cup | E4: W | F4: L | G4: T | H4: Points
B5: 1 | C5: Gray | D5: FBC 7 | E5: 6 | F5: 0 | G5: 1 | H5: 7
B6: 2 | C6: Jackson | D6: FBC 6 | E6: 6 | F6: 0 | G6: 0 | H6: 6.5
B7: 3 | C7: Connolly | D7: FBC 1 | E7: 5 | F7: 0 | G7: 0 | H7: 6
B8: 4 | C8: Jackson | D8: FBC 2 | E8: 5 | F8: 0 | G8: 0 | H8: 6
B9: 5 | C9: Connolly | D9: FBC 10 | E9: 4 | F9: 0 | G9: 2 | H9: 6
B10: 6 | C10: McInerney | D10: FBC 6 | E10: 5 | F10: 0 | G10: 1 | H10: 5.5
B11: 7 | C11: Ferrin | D11: FBC 1 | E11: 4 | F11: 0 | G11: 1 | H11: 5.5
B12: 8 | C12: Forster | D12: FBC 2 | E12: 4 | F12: 0 | G12: 1 | H12: 5.5
B13: 9 | C13: Gray | D13: FBC 10 | E13: 3 | F13: 0 | G13: 3 | H13: 5.5

Sheet Nemesis & Patsy
B1: Nemesis & Patsy
B2: Head-to-head ownership across singles and as doubles opponents. Patsy = the opponent each player owns most (best W–L–T against); Nemesis = the opponent who owns them. Records from the player’s perspective; min 3 meetings.
B4: Player | C4: Biggest Patsy | D4: Record | E4: Biggest Nemesis | F4: Record
B5: Bussiculo | C5: Flanders | D5: 3–1–0 | E5: Jackson | F5: 1–3–0
B6: Cole | C6: Connors | D6: 5–1–2 | E6: Forster | F6: 1–5–1
B7: Connolly | C7: Fogan | D7: 6–0–0 | E7: Gray | F7: 2–6–3
B8: Connors | C8: Bussiculo | D8: 2–1–1 | E8: Fogan | F8: 2–7–1
B9: Delaney | C9: Mangold | D9: 5–3–1 | E9: Jackson | F9: 0–2–1
B10: Delneky | C10: Connors | D10: 5–1–0 | E10: Delaney | F10: 1–3–1
B11: DeOteris | C11: — | E11: Delaney | F11: 1–3–0
B12: Ferrin | C12: Zimmer | D12: 8–1–1 | E12: Perkins | F12: 0–4–0
B13: Flanders | C13: Welker | D13: 4–0–0 | E13: Gray | F13: 2–7–0
B14: Fogan | C14: Connors | D14: 7–2–1 | E14: Lynch | F14: 0–8–0
B15: Forster | C15: McInerney | D15: 5–0–1 | E15: Flanders | F15: 2–5–1
B16: Gray | C16: Flanders | D16: 7–2–0 | E16: Hilts | F16: 0–3–0
B17: Grise | C17: Mangold | D17: 6–2–1 | E17: Poirier | F17: 2–6–0
B18: Hickerson | C18: Hilts | D18: 3–2–1 | E18: Forster | F18: 0–3–0
B19: Hilts | C19: Shively | D19: 7–3–2 | E19: Jackson | F19: 1–5–1
B20: Jackson | C20: Zimmer | D20: 8–1–1 | E20: Perkins | F20: 1–3–0
B21: Lynch | C21: Fogan | D21: 8–0–0 | E21: Jackson | F21: 4–6–2
B22: Mangold | C22: Piegari | D22: 3–0–1 | E22: Shively | F22: 1–6–1
B23: McInerney | C23: Norat | D23: 5–1–2 | E23: Forster | F23: 0–5–1
... B32: Zimmer | C32: Connors | D32: 5–1–0 | E32: Ferrin | F32: 1–8–1

Sheet Streak Tracker
B1: Streak Tracker
B2: Longest consecutive runs in head-to-head matches (singles + doubles), in chronological order across all cups. A tie breaks a streak. Current = the active run as of each player’s most recent cup. Min 10 matches.
B4: Player | C4: Matches | D4: Longest Win Streak | E4: Longest Loss Streak | F4: Current
B5: Jackson | C5: 69 | D5: 8 | E5: 4 | F5: W4
B6: Perkins | C6: 28 | D6: 7 | E6: 4 | F6: L1
B7: Delneky | C7: 32 | D7: 5 | E7: 2 | F7: T2
B8: Grise | C8: 69 | D8: 5 | E8: 3 | F8: W1
B9: McInerney | C9: 47 | D9: 5 | E9: 4 | F9: L1
B10: Connolly | C10: 69 | D10: 5 | E10: 6 | F10: L2
B11: Gray | C11: 42 | D11: 4 | E11: 3 | F11: W1
B12: Delaney | C12: 38 | D12: 4 | E12: 3 | F12: L1
B13: Norat | C13: 36 | D13: 4 | E13: 3 | F13: W1
B14: Lynch | C14: 69 | D14: 4 | E14: 4 | F14: L1
B15: Hilts | C15: 64 | D15: 4 | E15: 4 | F15: W1
B16: Welker | C16: 47 | D16: 4 | E16: 4 | F16: W1
... B32: Hickerson | C32: 20 | D32: 2 | E32: 5 | F32: L5

Sheet RecordBook
E4: Record Book
E6: All Time Records
E7: Most Cups | F7: =MAX(Cups!$P$3:$P$33) -> 10 | H7: =INDEX(Cups!$B$3:$B$33,MATCH(F7,Cups!$P$3:$P$33,0)) -> Lynch
E8: Highest Cup Win % | F8: 1 | H8: Perkins
E9: Lowest Cup Win % (>1 tourney) | F9: 0 | H9: Piegari
E10: Most Total Points | F10: =MAX(LifetimeLeaderboard!$C$5:$C$35) -> 50.5 | H10: =INDEX(LifetimeLeaderboard!$B$5:$B$35,MATCH(F10,LifetimeLeaderboard!$C$5:$C$35,0)) -> Connolly
E11: Highest Points per Cup (>3 FBCs) | F11: 4.6 | H11: Perkins
E12: Highest Tandem Win % (>2 matches) | F12: =SUMPRODUCT(MAX(('Singles_Doubles records'!$N$5:$N$168>=3)*'Singles_Doubles records'!$M$5:$M$168)) -> 0.875 | H12: =INDEX('Singles_Doubles records'!$I$5:$I$168,MATCH(F12,INDEX(('Singles_Doubles records'!$N$5:$N$168>=3)*'Singles_Doubles records'!$M$5:$M$168,0,1),0)) -> Ferrin / Flanders
E13: Largest Margin of Victory | F13: 9.5 | H13: Team Welker over Team Flanders (FBC VIII)
E15: Largest Margin of Victory
E16: Singles | F16: 8&7 | H16: Cole def. Mangold (FBC VI) Delneky def. Hilts (FBC X)
E17: Best Ball | F17: 5&4 | H17: ConnollyShively def. FlandersMangold (FBC I) FoganLynch def. GrayNorat (FBC IV)
E18: Vegas | F18: 5&4 | H18: DeOterisFerrin def FlandersForster (FBC VIII) HiltsWelker def ColeFogan (FBC VIII)
E19: Hi Lo | F19: 7&3 | H19: ForsterLynch def. ColeFerrin (FBC II) GrayNorat def. LynchFogan (FBC IV)
E20: Pinehurst | F20: 5&4 | H20: ConnollyShively def. FlandersMangold (FBCI) ConnollyForster def. FerrinJackson (FBC V) NoratZimmer def. ColeConnors (FBC V)
E21: Scramble-Stableford | F21: 12.5 | H21: ConnollyJackson def. FoganWeisberger
E23: Most Scramble Points | F23: 24 | H23: ConnollyMcInerney (FBC IV)
E24: Most Consecutive Craps Points | F24: 6 | H24: Fogan (FBC VI)
E26: Live records (Most Cups, Most Total Points, Highest Tandem) update from Archives. Margin records below are entered manually.

Sheet NHI
D3: Nerd-Hooligan Index | H3: Nerd-Hooligan Index | K3: Lifetime Dunkaroos + Times Arrested + [Table Dives / 2] + [0.5*Legitimate Children + 1.5*Illegitimate Children] -
K4: Divided by
D5: CB | E5: 0 | H5: Bussiculo | I5: 5 | K5: [Advanced degrees + Books read in last 5 years] + Sq Rt(New Sabermetrics Created)
D6: Cole | E6: 5 | H6: Fogan | I6: 4
D7: Connolly | E7: 2 | H7: Gray | I7: 5
D8: Connors | E8: 9 | H8: Grise | I8: 4
D9: DB | E9: 10 | H9: Hilts | I9: 1
D10: Flanders | E10: 10 | H10: Jackson | I10: 2
D11: Forster | E11: 3 | H11: Lynch | I11: 2
D12: Norat | E12: 11 | H12: Mangold | I12: 5
D13: Poirier | E13: 10 | H13: McInerney | I13: 1
D14: Welker | E14: 9 | H14: Shively | I14: 4
D15: Zimmer | E15: 7
H16: Average | I16: 3.3
D17: Average | E17: 7.6
E25: 2018 | F25: 2019
D26: CB | E26: 0 | F26: 0
D27: Cole | E27: 5 | F27: 5
D28: Connolly | E28: 2 | F28: 2
D29: Connors | E29: 9 | F29: 9
D30: DB | E30: 10 | F30: 10
D31: Flanders | E31: 10 | F31: 9
D32: Forster | E32: 3 | F32: 2
D33: Norat | E33: 11 | F33: 11
D34: Poirier | E34: 10 | F34: 10
D35: Welker | E35: 9 | F35: 5
D36: Zimmer | E36: 7 | F36: 7
D37: Bussiculo | E37: 5 | F37: 5
... D46: Shively | E46: 4 | F46: 3

Sheet Singles_Doubles records
B1: Singles & Doubles Records
B2: Live from Archives — recomputes automatically, including future cups. Win % = (W + ½T) ÷ matches. Through FBC 12.
B4: Player | C4: W | D4: L | E4: T | F4: Win % | G4: Matches | I4: Tandem | J4: W | K4: L | L4: T | M4: Win % | N4: Matches
B5: R. Connolly | C5: =COUNTIFS(Archives!$S$2:$S$1048576,"Singles",Archives!$V$2:$V$1048576,$B5,Archives!$AB$2:$AB$1048576,"W") -> 2 | D5: =COUNTIFS(Archives!$S$2:$S$1048576,"Singles",Archives!$V$2:$V$1048576,$B5,Archives!$AB$2:$AB$1048576,"L") -> 0 | E5: =COUNTIFS(Archives!$S$2:$S$1048576,"Singles",Archives!$V$2:$V$1048576,$B5,Archives!$AB$2:$AB$1048576,"T") -> 0 | F5: =IF(G5=0,0,(C5+0.5*E5)/G5) -> 1 | G5: =C5+D5+E5 -> 2 | I5: Bussiculo / Hickerson | J5: =COUNTIFS(Archives!$S$2:$S$1048576,"Doubles",Archives!$V$2:$V$1048576,"Bussiculo",Archives!$Y$2:$Y$1048576,"Hickerson",Archives!$AB$2:$AB$1048576,"W")+COUNTIFS(Archives!$S$2:$S$1048576,"Doubles",Archives!$V$2:$V$1048576,"Hickerson",Archives!$Y$2:$Y$1048576,"Bussiculo",Archives!$AB$2:$AB$1048576,"W") -> 2 | K5: =COUNTIFS(Archives!$S$2:$S$1048576,"Doubles",Archives!$V$2:$V$1048576,"Bussiculo",Archives!$Y$2:$Y$1048576,"Hickerson",Archives!$AB$2:$AB$1048576,"L")+COUNTIFS(Archives!$S$2:$S$1048576,"Doubles",Archives!$V$2:$V$1048576,"Hickerson",Archives!$Y$2:$Y$1048576,"Bussiculo",Archives!$AB$2:$AB$1048576,"L") -> 0 | L5: =COUNTIFS(Archives!$S$2:$S$1048576,"Doubles",Archives!$V$2:$V$1048576,"Bussiculo",Archives!$Y$2:$Y$1048576,"Hickerson",Archives!$AB$2:$AB$1048576,"T")+COUNTIFS(Archives!$S$2:$S$1048576,"Doubles",Archives!$V$2:$V$1048576,"Hickerson",Archives!$Y$2:$Y$1048576,"Bussiculo",Archives!$AB$2:$AB$1048576,"T") -> 0 | M5: =IF(N5=0,0,(J5+0.5*L5)/N5) -> 1 | N5: =J5+K5+L5 -> 2
B6: Snyder | C6: =COUNTIFS(Archives!$S$2:$S$1048576,"Singles",Archives!$V$2:$V$1048576,$B6,Archives!$AB$2:$AB$1048576,"W") -> 1 | D6: =COUNTIFS(Archives!$S$2:$S$1048576,"Singles",Archives!$V$2:$V$1048576,$B6,Archives!$AB$2:$AB$1048576,"L") -> 0 | E6: =COUNTIFS(Archives!$S$2:$S$1048576,"Singles",Archives!$V$2:$V$1048576,$B6,Archives!$AB$2:$AB$1048576,"T") -> 0 | F6: =IF(G6=0,0,(C6+0.5*E6)/G6) -> 1 | G6: =C6+D6+E6 -> 1 | I6: Cole / Weisberger | J6: =COUNTIFS(Archives!$S$2:$S$1048576,"Doubles",Archives!$V$2:$V$1048576,"Cole",Archives!$Y$2:$Y$1048576,"Weisberger",Archives!$AB$2:$AB$1048576,"W")+COUNTIFS(Archives!$S$2:$S$1048576,"Doubles",Archives!$V$2:$V$1048576,"Weisberger",Archives!$Y$2:$Y$1048576,"Cole",Archives!$AB$2:$AB$1048576,"W") -> 2 | K6: =COUNTIFS(Archives!$S$2:$S$1048576,"Doubles",Archives!$V$2:$V$1048576,"Cole",Archives!$Y$2:$Y$1048576,"Weisberger",Archives!$AB$2:$AB$1048576,"L")+COUNTIFS(Archives!$S$2:$S$1048576,"Doubles",Archives!$V$2:$V$1048576,"Weisberger",Archives!$Y$2:$Y$1048576,"Cole",Archives!$AB$2:$AB$1048576,"L") -> 0 | L6: =COUNTIFS(Archives!$S$2:$S$1048576,"Doubles",Archives!$V$2:$V$1048576,"Cole",Archives!$Y$2:$Y$1048576,"Weisberger",Archives!$AB$2:$AB$1048576,"T")+COUNTIFS(Archives!$S$2:$S$1048576,"Doubles",Archives!$V$2:$V$1048576,"Weisberger",Archives!$Y$2:$Y$1048576,"Cole",Archives!$AB$2:$AB$1048576,"T") -> 0 | M6: =IF(N6=0,0,(J6+0.5*L6)/N6) -> 1 | N6: =J6+K6+L6 -> 2
B7: Gray | C7: =COUNTIFS(Archives!$S$2:$S$1048576,"Singles",Archives!$V$2:$V$1048576,$B7,Archives!$AB$2:$AB$1048576,"W") -> 5 | D7: =COUNTIFS(Archives!$S$2:$S$1048576,"Singles",Archives!$V$2:$V$1048576,$B7,Archives!$AB$2:$AB$1048576,"L") -> 1 | E7: =COUNTIFS(Archives!$S$2:$S$1048576,"Singles",Archives!$V$2:$V$1048576,$B7,Archives!$AB$2:$AB$1048576,"T") -> 1 | F7: =IF(G7=0,0,(C7+0.5*E7)/G7) -> 0.78571429 | G7: =C7+D7+E7 -> 7 | I7: Connolly / Perkins | J7: =COUNTIFS(Archives!$S$2:$S$1048576,"Doubles",Archives!$V$2:$V$1048576,"Connolly",Archives!$Y$2:$Y$1048576,"Perkins",Archives!$AB$2:$AB$1048576,"W")+COUNTIFS(Archives!$S$2:$S$1048576,"Doubles",Archives!$V$2:$V$1048576,"Perkins",Archives!$Y$2:$Y$1048576,"Connolly",Archives!$AB$2:$AB$1048576,"W") -> 2 | K7: =COUNTIFS(Archives!$S$2:$S$1048576,"Doubles",Archives!$V$2:$V$1048576,"Connolly",Archives!$Y$2:$Y$1048576,"Perkins",Archives!$AB$2:$AB$1048576,"L")+COUNTIFS(Archives!$S$2:$S$1048576,"Doubles",Archives!$V$2:$V$1048576,"Perkins",Archives!$Y$2:$Y$1048576,"Connolly",Archives!$AB$2:$AB$1048576,"L") -> 0 | L7: =COUNTIFS(Archives!$S$2:$S$1048576,"Doubles",Archives!$V$2:$V$1048576,"Connolly",Archives!$Y$2:$Y$1048576,"Perkins",Archives!$AB$2:$AB$1048576,"T")+COUNTIFS(Archives!$S$2:$S$1048576,"Doubles",Archives!$V$2:$V$1048576,"Perkins",Archives!$Y$2:$Y$1048576,"Connolly",Archives!$AB$2:$AB$1048576,"T") -> 0 | M7: =IF(N7=0,0,(J7+0.5*L7)/N7) -> 1 | N7: =J7+K7+L7 -> 2
B8: Poirier | C8: =COUNTIFS(Archives!$S$2:$S$1048576,"Singles",Archives!$V$2:$V$1048576,$B8,Archives!$AB$2:$AB$1048576,"W") -> 5 | D8: =COUNTIFS(Archives!$S$2:$S$1048576,"Singles",Archives!$V$2:$V$1048576,$B8,Archives!$AB$2:$AB$1048576,"L") -> 1 | E8: =COUNTIFS(Archives!$S$2:$S$1048576,"Singles",Archives!$V$2:$V$1048576,$B8,Archives!$AB$2:$AB$1048576,"T") -> 1 | F8: =IF(G8=0,0,(C8+0.5*E8)/G8) -> 0.78571429 | G8: =C8+D8+E8 -> 7 | I8: Connolly / Grise | J8: =COUNTIFS(Archives!$S$2:$S$1048576,"Doubles",Archives!$V$2:$V$1048576,"Connolly",Archives!$Y$2:$Y$1048576,"Grise",Archives!$AB$2:$AB$1048576,"W")+COUNTIFS(Archives!$S$2:$S$1048576,"Doubles",Archives!$V$2:$V$1048576,"Grise",Archives!$Y$2:$Y$1048576,"Connolly",Archives!$AB$2:$AB$1048576,"W") -> 2 | K8: =COUNTIFS(Archives!$S$2:$S$1048576,"Doubles",Archives!$V$2:$V$1048576,"Connolly",Archives!$Y$2:$Y$1048576,"Grise",Archives!$AB$2:$AB$1048576,"L")+COUNTIFS(Archives!$S$2:$S$1048576,"Doubles",Archives!$V$2:$V$1048576,"Grise",Archives!$Y$2:$Y$1048576,"Connolly",Archives!$AB$2:$AB$1048576,"L") -> 0 | L8: =COUNTIFS(Archives!$S$2:$S$1048576,"Doubles",Archives!$V$2:$V$1048576,"Connolly",Archives!$Y$2:$Y$1048576,"Grise",Archives!$AB$2:$AB$1048576,"T")+COUNTIFS(Archives!$S$2:$S$1048576,"Doubles",Archives!$V$2:$V$1048576,"Grise",Archives!$Y$2:$Y$1048576,"Connolly",Archives!$AB$2:$AB$1048576,"T") -> 0 | M8: =IF(N8=0,0,(J8+0.5*L8)/N8) -> 1 | N8: =J8+K8+L8 -> 2
B9: Perkins | C9: =COUNTIFS(Archives!$S$2:$S$1048576,"Singles",Archives!$V$2:$V$1048576,$B9,Archives!$AB$2:$AB$1048576,"W") -> 3 | D9: =COUNTIFS(Archives!$S$2:$S$1048576,"Singles",Archives!$V$2:$V$1048576,$B9,Archives!$AB$2:$AB$1048576,"L") -> 1 | E9: =COUNTIFS(Archives!$S$2:$S$1048576,"Singles",Archives!$V$2:$V$1048576,$B9,Archives!$AB$2:$AB$1048576,"T") -> 0 | F9: =IF(G9=0,0,(C9+0.5*E9)/G9) -> 0.75 | G9: =C9+D9+E9 -> 4 | I9: Delaney / Lynch | J9: =COUNTIFS(Archives!$S$2:$S$1048576,"Doubles",Archives!$V$2:$V$1048576,"Delaney",Archives!$Y$2:$Y$1048576,"Lynch",Archives!$AB$2:$AB$1048576,"W")+COUNTIFS(Archives!$S$2:$S$1048576,"Doubles",Archives!$V$2:$V$1048576,"Lynch",Archives!$Y$2:$Y$1048576,"Delaney",Archives!$AB$2:$AB$1048576,"W") -> 2 | K9: =COUNTIFS(Archives!$S$2:$S$1048576,"Doubles",Archives!$V$2:$V$1048576,"Delaney",Archives!$Y$2:$Y$1048576,"Lynch",Archives!$AB$2:$AB$1048576,"L")+COUNTIFS(Archives!$S$2:$S$1048576,"Doubles",Archives!$V$2:$V$1048576,"Lynch",Archives!$Y$2:$Y$1048576,"Delaney",Archives!$AB$2:$AB$1048576,"L") -> 0 | L9: =COUNTIFS(Archives!$S$2:$S$1048576,"Doubles",Archives!$V$2:$V$1048576,"Delaney",Archives!$Y$2:$Y$1048576,"Lynch",Archives!$AB$2:$AB$1048576,"T")+COUNTIFS(Archives!$S$2:$S$1048576,"Doubles",Archives!$V$2:$V$1048576,"Lynch",Archives!$Y$2:$Y$1048576,"Delaney",Archives!$AB$2:$AB$1048576,"T") -> 0 | M9: =IF(N9=0,0,(J9+0.5*L9)/N9) -> 1 | N9: =J9+K9+L9 -> 2
B10: McInerney | C10: =COUNTIFS(Archives!$S$2:$S$1048576,"Singles",Archives!$V$2:$V$1048576,$B10,Archives!$AB$2:$AB$1048576,"W") -> 6 | D10: =COUNTIFS(Archives!$S$2:$S$1048576,"Singles",Archives!$V$2:$V$1048576,$B10,Archives!$AB$2:$AB$1048576,"L") -> 2 | E10: =COUNTIFS(Archives!$S$2:$S$1048576,"Singles",Archives!$V$2:$V$1048576,$B10,Archives!$AB$2:$AB$1048576,"T") -> 2 | F10: =IF(G10=0,0,(C10+0.5*E10)/G10) -> 0.7 | G10: =C10+D10+E10 -> 10 | I10: Delneky / Forster | J10: =COUNTIFS(Archives!$S$2:$S$1048576,"Doubles",Archives!$V$2:$V$1048576,"Delneky",Archives!$Y$2:$Y$1048576,"Forster",Archives!$AB$2:$AB$1048576,"W")+COUNTIFS(Archives!$S$2:$S$1048576,"Doubles",Archives!$V$2:$V$1048576,"Forster",Archives!$Y$2:$Y$1048576,"Delneky",Archives!$AB$2:$AB$1048576,"W") -> 2 | K10: =COUNTIFS(Archives!$S$2:$S$1048576,"Doubles",Archives!$V$2:$V$1048576,"Delneky",Archives!$Y$2:$Y$1048576,"Forster",Archives!$AB$2:$AB$1048576,"L")+COUNTIFS(Archives!$S$2:$S$1048576,"Doubles",Archives!$V$2:$V$1048576,"Forster",Archives!$Y$2:$Y$1048576,"Delneky",Archives!$AB$2:$AB$1048576,"L") -> 0 | L10: =COUNTIFS(Archives!$S$2:$S$1048576,"Doubles",Archives!$V$2:$V$1048576,"Delneky",Archives!$Y$2:$Y$1048576,"Forster",Archives!$AB$2:$AB$1048576,"T")+COUNTIFS(Archives!$S$2:$S$1048576,"Doubles",Archives!$V$2:$V$1048576,"Forster",Archives!$Y$2:$Y$1048576,"Delneky",Archives!$AB$2:$AB$1048576,"T") -> 0 | M10: =IF(N10=0,0,(J10+0.5*L10)/N10) -> 1 | N10: =J10+K10+L10 -> 2
B11: Connolly | C11: =COUNTIFS(Archives!$S$2:$S$1048576,"Singles",Archives!$V$2:$V$1048576,$B11,Archives!$AB$2:$AB$1048576,"W") -> 8 | D11: =COUNTIFS(Archives!$S$2:$S$1048576,"Singles",Archives!$V$2:$V$1048576,$B11,Archives!$AB$2:$AB$1048576,"L") -> 4 | E11: =COUNTIFS(Archives!$S$2:$S$1048576,"Singles",Archives!$V$2:$V$1048576,$B11,Archives!$AB$2:$AB$1048576,"T") -> 0 | F11: =IF(G11=0,0,(C11+0.5*E11)/G11) -> 0.66666667 | G11: =C11+D11+E11 -> 12 | I11: Ferrin / Fogan | J11: =COUNTIFS(Archives!$S$2:$S$1048576,"Doubles",Archives!$V$2:$V$1048576,"Ferrin",Archives!$Y$2:$Y$1048576,"Fogan",Archives!$AB$2:$AB$1048576,"W")+COUNTIFS(Archives!$S$2:$S$1048576,"Doubles",Archives!$V$2:$V$1048576,"Fogan",Archives!$Y$2:$Y$1048576,"Ferrin",Archives!$AB$2:$AB$1048576,"W") -> 2 | K11: =COUNTIFS(Archives!$S$2:$S$1048576,"Doubles",Archives!$V$2:$V$1048576,"Ferrin",Archives!$Y$2:$Y$1048576,"Fogan",Archives!$AB$2:$AB$1048576,"L")+COUNTIFS(Archives!$S$2:$S$1048576,"Doubles",Archives!$V$2:$V$1048576,"Fogan",Archives!$Y$2:$Y$1048576,"Ferrin",Archives!$AB$2:$AB$1048576,"L") -> 0 | L11: =COUNTIFS(Archives!$S$2:$S$1048576,"Doubles",Archives!$V$2:$V$1048576,"Ferrin",Archives!$Y$2:$Y$1048576,"Fogan",Archives!$AB$2:$AB$1048576,"T")+COUNTIFS(Archives!$S$2:$S$1048576,"Doubles",Archives!$V$2:$V$1048576,"Fogan",Archives!$Y$2:$Y$1048576,"Ferrin",Archives!$AB$2:$AB$1048576,"T") -> 0 | M11: =IF(N11=0,0,(J11+0.5*L11)/N11) -> 1 | N11: =J11+K11+L11 -> 2
B12: Forster | C12: =COUNTIFS(Archives!$S$2:$S$1048576,"Singles",Archives!$V$2:$V$1048576,$B12,Archives!$AB$2:$AB$1048576,"W") -> 7 | D12: =COUNTIFS(Archives!$S$2:$S$1048576,"Singles",Archives!$V$2:$V$1048576,$B12,Archives!$AB$2:$AB$1048576,"L") -> 4 | E12: =COUNTIFS(Archives!$S$2:$S$1048576,"Singles",Archives!$V$2:$V$1048576,$B12,Archives!$AB$2:$AB$1048576,"T") -> 1 | F12: =IF(G12=0,0,(C12+0.5*E12)/G12) -> 0.625 | G12: =C12+D12+E12 -> 12 | I12: Flanders / Lynch | J12: =COUNTIFS(Archives!$S$2:$S$1048576,"Doubles",Archives!$V$2:$V$1048576,"Flanders",Archives!$Y$2:$Y$1048576,"Lynch",Archives!$AB$2:$AB$1048576,"W")+COUNTIFS(Archives!$S$2:$S$1048576,"Doubles",Archives!$V$2:$V$1048576,"Lynch",Archives!$Y$2:$Y$1048576,"Flanders",Archives!$AB$2:$AB$1048576,"W") -> 2 | K12: =COUNTIFS(Archives!$S$2:$S$1048576,"Doubles",Archives!$V$2:$V$1048576,"Flanders",Archives!$Y$2:$Y$1048576,"Lynch",Archives!$AB$2:$AB$1048576,"L")+COUNTIFS(Archives!$S$2:$S$1048576,"Doubles",Archives!$V$2:$V$1048576,"Lynch",Archives!$Y$2:$Y$1048576,"Flanders",Archives!$AB$2:$AB$1048576,"L") -> 0 | L12: =COUNTIFS(Archives!$S$2:$S$1048576,"Doubles",Archives!$V$2:$V$1048576,"Flanders",Archives!$Y$2:$Y$1048576,"Lynch",Archives!$AB$2:$AB$1048576,"T")+COUNTIFS(Archives!$S$2:$S$1048576,"Doubles",Archives!$V$2:$V$1048576,"Lynch",Archives!$Y$2:$Y$1048576,"Flanders",Archives!$AB$2:$AB$1048576,"T") -> 0 | M12: =IF(N12=0,0,(J12+0.5*L12)/N12) -> 1 | N12: =J12+K12+L12 -> 2
B13: Zimmer | C13: =COUNTIFS(Archives!$S$2:$S$1048576,"Singles",Archives!$V$2:$V$1048576,$B13,Archives!$AB$2:$AB$1048576,"W") -> 6 | D13: =COUNTIFS(Archives!$S$2:$S$1048576,"Singles",Archives!$V$2:$V$1048576,$B13,Archives!$AB$2:$AB$1048576,"L") -> 3 | E13: =COUNTIFS(Archives!$S$2:$S$1048576,"Singles",Archives!$V$2:$V$1048576,$B13,Archives!$AB$2:$AB$1048576,"T") -> 3 | F13: =IF(G13=0,0,(C13+0.5*E13)/G13) -> 0.625 | G13: =C13+D13+E13 -> 12 | I13: Fogan / Poirier | J13: =COUNTIFS(Archives!$S$2:$S$1048576,"Doubles",Archives!$V$2:$V$1048576,"Fogan",Archives!$Y$2:$Y$1048576,"Poirier",Archives!$AB$2:$AB$1048576,"W")+COUNTIFS(Archives!$S$2:$S$1048576,"Doubles",Archives!$V$2:$V$1048576,"Poirier",Archives!$Y$2:$Y$1048576,"Fogan",Archives!$AB$2:$AB$1048576,"W") -> 2 | K13: =COUNTIFS(Archives!$S$2:$S$1048576,"Doubles",Archives!$V$2:$V$1048576,"Fogan",Archives!$Y$2:$Y$1048576,"Poirier",Archives!$AB$2:$AB$1048576,"L")+COUNTIFS(Archives!$S$2:$S$1048576,"Doubles",Archives!$V$2:$V$1048576,"Poirier",Archives!$Y$2:$Y$1048576,"Fogan",Archives!$AB$2:$AB$1048576,"L") -> 0 | L13: =COUNTIFS(Archives!$S$2:$S$1048576,"Doubles",Archives!$V$2:$V$1048576,"Fogan",Archives!$Y$2:$Y$1048576,"Poirier",Archives!$AB$2:$AB$1048576,"T")+COUNTIFS(Archives!$S$2:$S$1048576,"Doubles",Archives!$V$2:$V$1048576,"Poirier",Archives!$Y$2:$Y$1048576,"Fogan",Archives!$AB$2:$AB$1048576,"T") -> 0 | M13: =IF(N13=0,0,(J13+0.5*L13)/N13) -> 1 | N13: =J13+K13+L13 -> 2
B14: Delneky | C14: =COUNTIFS(Archives!$S$2:$S$1048576,"Singles",Archives!$V$2:$V$1048576,$B14,Archives!$AB$2:$AB$1048576,"W") -> 3 | D14: =COUNTIFS(Archives!$S$2:$S$1048576,"Singles",Archives!$V$2:$V$1048576,$B14,Archives!$AB$2:$AB$1048576,"L") -> 2 | E14: =COUNTIFS(Archives!$S$2:$S$1048576,"Singles",Archives!$V$2:$V$1048576,$B14,Archives!$AB$2:$AB$1048576,"T") -> 1 | F14: =IF(G14=0,0,(C14+0.5*E14)/G14) -> 0.58333333 | G14: =C14+D14+E14 -> 6 | I14: Forster / Lynch | J14: =COUNTIFS(Archives!$S$2:$S$1048576,"Doubles",Archives!$V$2:$V$1048576,"Forster",Archives!$Y$2:$Y$1048576,"Lynch",Archives!$AB$2:$AB$1048576,"W")+COUNTIFS(Archives!$S$2:$S$1048576,"Doubles",Archives!$V$2:$V$1048576,"Lynch",Archives!$Y$2:$Y$1048576,"Forster",Archives!$AB$2:$AB$1048576,"W") -> 2 | K14: =COUNTIFS(Archives!$S$2:$S$1048576,"Doubles",Archives!$V$2:$V$1048576,"Forster",Archives!$Y$2:$Y$1048576,"Lynch",Archives!$AB$2:$AB$1048576,"L")+COUNTIFS(Archives!$S$2:$S$1048576,"Doubles",Archives!$V$2:$V$1048576,"Lynch",Archives!$Y$2:$Y$1048576,"Forster",Archives!$AB$2:$AB$1048576,"L") -> 0 | L14: =COUNTIFS(Archives!$S$2:$S$1048576,"Doubles",Archives!$V$2:$V$1048576,"Forster",Archives!$Y$2:$Y$1048576,"Lynch",Archives!$AB$2:$AB$1048576,"T")+COUNTIFS(Archives!$S$2:$S$1048576,"Doubles",Archives!$V$2:$V$1048576,"Lynch",Archives!$Y$2:$Y$1048576,"Forster",Archives!$AB$2:$AB$1048576,"T") -> 0 | M14: =IF(N14=0,0,(J14+0.5*L14)/N14) -> 1 | N14: =J14+K14+L14 -> 2
B15: Norat | C15: =COUNTIFS(Archives!$S$2:$S$1048576,"Singles",Archives!$V$2:$V$1048576,$B15,Archives!$AB$2:$AB$1048576,"W") -> 3 | D15: =COUNTIFS(Archives!$S$2:$S$1048576,"Singles",Archives!$V$2:$V$1048576,$B15,Archives!$AB$2:$AB$1048576,"L") -> 2 | E15: =COUNTIFS(Archives!$S$2:$S$1048576,"Singles",Archives!$V$2:$V$1048576,$B15,Archives!$AB$2:$AB$1048576,"T") -> 1 | F15: =IF(G15=0,0,(C15+0.5*E15)/G15) -> 0.58333333 | G15: =C15+D15+E15 -> 6 | I15: Forster / Poirier | J15: =COUNTIFS(Archives!$S$2:$S$1048576,"Doubles",Archives!$V$2:$V$1048576,"Forster",Archives!$Y$2:$Y$1048576,"Poirier",Archives!$AB$2:$AB$1048576,"W")+COUNTIFS(Archives!$S$2:$S$1048576,"Doubles",Archives!$V$2:$V$1048576,"Poirier",Archives!$Y$2:$Y$1048576,"Forster",Archives!$AB$2:$AB$1048576,"W") -> 2 | K15: =COUNTIFS(Archives!$S$2:$S$1048576,"Doubles",Archives!$V$2:$V$1048576,"Forster",Archives!$Y$2:$Y$1048576,"Poirier",Archives!$AB$2:$AB$1048576,"L")+COUNTIFS(Archives!$S$2:$S$1048576,"Doubles",Archives!$V$2:$V$1048576,"Poirier",Archives!$Y$2:$Y$1048576,"Forster",Archives!$AB$2:$AB$1048576,"L") -> 0 | L15: =COUNTIFS(Archives!$S$2:$S$1048576,"Doubles",Archives!$V$2:$V$1048576,"Forster",Archives!$Y$2:$Y$1048576,"Poirier",Archives!$AB$2:$AB$1048576,"T")+COUNTIFS(Archives!$S$2:$S$1048576,"Doubles",Archives!$V$2:$V$1048576,"Poirier",Archives!$Y$2:$Y$1048576,"Forster",Archives!$AB$2:$AB$1048576,"T") -> 0 | M15: =IF(N15=0,0,(J15+0.5*L15)/N15) -> 1 | N15: =J15+K15+L15 -> 2
B16: Cole | C16: =COUNTIFS(Archives!$S$2:$S$1048576,"Singles",Archives!$V$2:$V$1048576,$B16,Archives!$AB$2:$AB$1048576,"W") -> 5 | D16: =COUNTIFS(Archives!$S$2:$S$1048576,"Singles",Archives!$V$2:$V$1048576,$B16,Archives!$AB$2:$AB$1048576,"L") -> 4 | E16: =COUNTIFS(Archives!$S$2:$S$1048576,"Singles",Archives!$V$2:$V$1048576,$B16,Archives!$AB$2:$AB$1048576,"T") -> 1 | F16: =IF(G16=0,0,(C16+0.5*E16)/G16) -> 0.55 | G16: =C16+D16+E16 -> 10 | I16: Gray / Welker | J16: =COUNTIFS(Archives!$S$2:$S$1048576,"Doubles",Archives!$V$2:$V$1048576,"Gray",Archives!$Y$2:$Y$1048576,"Welker",Archives!$AB$2:$AB$1048576,"W")+COUNTIFS(Archives!$S$2:$S$1048576,"Doubles",Archives!$V$2:$V$1048576,"Welker",Archives!$Y$2:$Y$1048576,"Gray",Archives!$AB$2:$AB$1048576,"W") -> 2 | K16: =COUNTIFS(Archives!$S$2:$S$1048576,"Doubles",Archives!$V$2:$V$1048576,"Gray",Archives!$Y$2:$Y$1048576,"Welker",Archives!$AB$2:$AB$1048576,"L")+COUNTIFS(Archives!$S$2:$S$1048576,"Doubles",Archives!$V$2:$V$1048576,"Welker",Archives!$Y$2:$Y$1048576,"Gray",Archives!$AB$2:$AB$1048576,"L") -> 0 | L16: =COUNTIFS(Archives!$S$2:$S$1048576,"Doubles",Archives!$V$2:$V$1048576,"Gray",Archives!$Y$2:$Y$1048576,"Welker",Archives!$AB$2:$AB$1048576,"T")+COUNTIFS(Archives!$S$2:$S$1048576,"Doubles",Archives!$V$2:$V$1048576,"Welker",Archives!$Y$2:$Y$1048576,"Gray",Archives!$AB$2:$AB$1048576,"T") -> 0 | M16: =IF(N16=0,0,(J16+0.5*L16)/N16) -> 1 | N16: =J16+K16+L16 -> 2
B17: Fogan | C17: =COUNTIFS(Archives!$S$2:$S$1048576,"Singles",Archives!$V$2:$V$1048576,$B17,Archives!$AB$2:$AB$1048576,"W") -> 6 | D17: =COUNTIFS(Archives!$S$2:$S$1048576,"Singles",Archives!$V$2:$V$1048576,$B17,Archives!$AB$2:$AB$1048576,"L") -> 5 | E17: =COUNTIFS(Archives!$S$2:$S$1048576,"Singles",Archives!$V$2:$V$1048576,$B17,Archives!$AB$2:$AB$1048576,"T") -> 0 | F17: =IF(G17=0,0,(C17+0.5*E17)/G17) -> 0.54545455 | G17: =C17+D17+E17 -> 11 | I17: Gray / Grise | J17: =COUNTIFS(Archives!$S$2:$S$1048576,"Doubles",Archives!$V$2:$V$1048576,"Gray",Archives!$Y$2:$Y$1048576,"Grise",Archives!$AB$2:$AB$1048576,"W")+COUNTIFS(Archives!$S$2:$S$1048576,"Doubles",Archives!$V$2:$V$1048576,"Grise",Archives!$Y$2:$Y$1048576,"Gray",Archives!$AB$2:$AB$1048576,"W") -> 2 | K17: =COUNTIFS(Archives!$S$2:$S$1048576,"Doubles",Archives!$V$2:$V$1048576,"Gray",Archives!$Y$2:$Y$1048576,"Grise",Archives!$AB$2:$AB$1048576,"L")+COUNTIFS(Archives!$S$2:$S$1048576,"Doubles",Archives!$V$2:$V$1048576,"Grise",Archives!$Y$2:$Y$1048576,"Gray",Archives!$AB$2:$AB$1048576,"L") -> 0 | L17: =COUNTIFS(Archives!$S$2:$S$1048576,"Doubles",Archives!$V$2:$V$1048576,"Gray",Archives!$Y$2:$Y$1048576,"Grise",Archives!$AB$2:$AB$1048576,"T")+COUNTIFS(Archives!$S$2:$S$1048576,"Doubles",Archives!$V$2:$V$1048576,"Grise",Archives!$Y$2:$Y$1048576,"Gray",Archives!$AB$2:$AB$1048576,"T") -> 0 | M17: =IF(N17=0,0,(J17+0.5*L17)/N17) -> 1 | N17: =J17+K17+L17 -> 2
B18: Ferrin | C18: =COUNTIFS(Archives!$S$2:$S$1048576,"Singles",Archives!$V$2:$V$1048576,$B18,Archives!$AB$2:$AB$1048576,"W") -> 6 | D18: =COUNTIFS(Archives!$S$2:$S$1048576,"Singles",Archives!$V$2:$V$1048576,$B18,Archives!$AB$2:$AB$1048576,"L") -> 5 | E18: =COUNTIFS(Archives!$S$2:$S$1048576,"Singles",Archives!$V$2:$V$1048576,$B18,Archives!$AB$2:$AB$1048576,"T") -> 1 | F18: =IF(G18=0,0,(C18+0.5*E18)/G18) -> 0.54166667 | G18: =C18+D18+E18 -> 12 | I18: Grise / Welker | J18: =COUNTIFS(Archives!$S$2:$S$1048576,"Doubles",Archives!$V$2:$V$1048576,"Grise",Archives!$Y$2:$Y$1048576,"Welker",Archives!$AB$2:$AB$1048576,"W")+COUNTIFS(Archives!$S$2:$S$1048576,"Doubles",Archives!$V$2:$V$1048576,"Welker",Archives!$Y$2:$Y$1048576,"Grise",Archives!$AB$2:$AB$1048576,"W") -> 2 | K18: =COUNTIFS(Archives!$S$2:$S$1048576,"Doubles",Archives!$V$2:$V$1048576,"Grise",Archives!$Y$2:$Y$1048576,"Welker",Archives!$AB$2:$AB$1048576,"L")+COUNTIFS(Archives!$S$2:$S$1048576,"Doubles",Archives!$V$2:$V$1048576,"Welker",Archives!$Y$2:$Y$1048576,"Grise",Archives!$AB$2:$AB$1048576,"L") -> 0 | L18: =COUNTIFS(Archives!$S$2:$S$1048576,"Doubles",Archives!$V$2:$V$1048576,"Grise",Archives!$Y$2:$Y$1048576,"Welker",Archives!$AB$2:$AB$1048576,"T")+COUNTIFS(Archives!$S$2:$S$1048576,"Doubles",Archives!$V$2:$V$1048576,"Welker",Archives!$Y$2:$Y$1048576,"Grise",Archives!$AB$2:$AB$1048576,"T") -> 0 | M18: =IF(N18=0,0,(J18+0.5*L18)/N18) -> 1 | N18: =J18+K18+L18 -> 2
B19: Grise | C19: =COUNTIFS(Archives!$S$2:$S$1048576,"Singles",Archives!$V$2:$V$1048576,$B19,Archives!$AB$2:$AB$1048576,"W") -> 6 | D19: =COUNTIFS(Archives!$S$2:$S$1048576,"Singles",Archives!$V$2:$V$1048576,$B19,Archives!$AB$2:$AB$1048576,"L") -> 6 | E19: =COUNTIFS(Archives!$S$2:$S$1048576,"Singles",Archives!$V$2:$V$1048576,$B19,Archives!$AB$2:$AB$1048576,"T") -> 0 | F19: =IF(G19=0,0,(C19+0.5*E19)/G19) -> 0.5 | G19: =C19+D19+E19 -> 12 | I19: Hilts / Welker | J19: =COUNTIFS(Archives!$S$2:$S$1048576,"Doubles",Archives!$V$2:$V$1048576,"Hilts",Archives!$Y$2:$Y$1048576,"Welker",Archives!$AB$2:$AB$1048576,"W")+COUNTIFS(Archives!$S$2:$S$1048576,"Doubles",Archives!$V$2:$V$1048576,"Welker",Archives!$Y$2:$Y$1048576,"Hilts",Archives!$AB$2:$AB$1048576,"W") -> 2 | K19: =COUNTIFS(Archives!$S$2:$S$1048576,"Doubles",Archives!$V$2:$V$1048576,"Hilts",Archives!$Y$2:$Y$1048576,"Welker",Archives!$AB$2:$AB$1048576,"L")+COUNTIFS(Archives!$S$2:$S$1048576,"Doubles",Archives!$V$2:$V$1048576,"Welker",Archives!$Y$2:$Y$1048576,"Hilts",Archives!$AB$2:$AB$1048576,"L") -> 0 | L19: =COUNTIFS(Archives!$S$2:$S$1048576,"Doubles",Archives!$V$2:$V$1048576,"Hilts",Archives!$Y$2:$Y$1048576,"Welker",Archives!$AB$2:$AB$1048576,"T")+COUNTIFS(Archives!$S$2:$S$1048576,"Doubles",Archives!$V$2:$V$1048576,"Welker",Archives!$Y$2:$Y$1048576,"Hilts",Archives!$AB$2:$AB$1048576,"T") -> 0 | M19: =IF(N19=0,0,(J19+0.5*L19)/N19) -> 1 | N19: =J19+K19+L19 -> 2
B20: Hilts | C20: =COUNTIFS(Archives!$S$2:$S$1048576,"Singles",Archives!$V$2:$V$1048576,$B20,Archives!$AB$2:$AB$1048576,"W") -> 6 | D20: =COUNTIFS(Archives!$S$2:$S$1048576,"Singles",Archives!$V$2:$V$1048576,$B20,Archives!$AB$2:$AB$1048576,"L") -> 5 | E20: =COUNTIFS(Archives!$S$2:$S$1048576,"Singles",Archives!$V$2:$V$1048576,$B20,Archives!$AB$2:$AB$1048576,"T") -> 0 | F20: =IF(G20=0,0,(C20+0.5*E20)/G20) -> 0.54545455 | G20: =C20+D20+E20 -> 11 | I20: Jackson / McInerney | J20: =COUNTIFS(Archives!$S$2:$S$1048576,"Doubles",Archives!$V$2:$V$1048576,"Jackson",Archives!$Y$2:$Y$1048576,"McInerney",Archives!$AB$2:$AB$1048576,"W")+COUNTIFS(Archives!$S$2:$S$1048576,"Doubles",Archives!$V$2:$V$1048576,"McInerney",Archives!$Y$2:$Y$1048576,"Jackson",Archives!$AB$2:$AB$1048576,"W") -> 2 | K20: =COUNTIFS(Archives!$S$2:$S$1048576,"Doubles",Archives!$V$2:$V$1048576,"Jackson",Archives!$Y$2:$Y$1048576,"McInerney",Archives!$AB$2:$AB$1048576,"L")+COUNTIFS(Archives!$S$2:$S$1048576,"Doubles",Archives!$V$2:$V$1048576,"McInerney",Archives!$Y$2:$Y$1048576,"Jackson",Archives!$AB$2:$AB$1048576,"L") -> 0 | L20: =COUNTIFS(Archives!$S$2:$S$1048576,"Doubles",Archives!$V$2:$V$1048576,"Jackson",Archives!$Y$2:$Y$1048576,"McInerney",Archives!$AB$2:$AB$1048576,"T")+COUNTIFS(Archives!$S$2:$S$1048576,"Doubles",Archives!$V$2:$V$1048576,"McInerney",Archives!$Y$2:$Y$1048576,"Jackson",Archives!$AB$2:$AB$1048576,"T") -> 0 | M20: =IF(N20=0,0,(J20+0.5*L20)/N20) -> 1 | N20: =J20+K20+L20 -> 2
B21: Welker | C21: =COUNTIFS(Archives!$S$2:$S$1048576,"Singles",Archives!$V$2:$V$1048576,$B21,Archives!$AB$2:$AB$1048576,"W") -> 4 | D21: =COUNTIFS(Archives!$S$2:$S$1048576,"Singles",Archives!$V$2:$V$1048576,$B21,Archives!$AB$2:$AB$1048576,"L") -> 4 | E21: =COUNTIFS(Archives!$S$2:$S$1048576,"Singles",Archives!$V$2:$V$1048576,$B21,Archives!$AB$2:$AB$1048576,"T") -> 0 | F21: =IF(G21=0,0,(C21+0.5*E21)/G21) -> 0.5 | G21: =C21+D21+E21 -> 8 | I21: Lynch / Zimmer | J21: =COUNTIFS(Archives!$S$2:$S$1048576,"Doubles",Archives!$V$2:$V$1048576,"Lynch",Archives!$Y$2:$Y$1048576,"Zimmer",Archives!$AB$2:$AB$1048576,"W")+COUNTIFS(Archives!$S$2:$S$1048576,"Doubles",Archives!$V$2:$V$1048576,"Zimmer",Archives!$Y$2:$Y$1048576,"Lynch",Archives!$AB$2:$AB$1048576,"W") -> 2 | K21: =COUNTIFS(Archives!$S$2:$S$1048576,"Doubles",Archives!$V$2:$V$1048576,"Lynch",Archives!$Y$2:$Y$1048576,"Zimmer",Archives!$AB$2:$AB$1048576,"L")+COUNTIFS(Archives!$S$2:$S$1048576,"Doubles",Archives!$V$2:$V$1048576,"Zimmer",Archives!$Y$2:$Y$1048576,"Lynch",Archives!$AB$2:$AB$1048576,"L") -> 0 | L21: =COUNTIFS(Archives!$S$2:$S$1048576,"Doubles",Archives!$V$2:$V$1048576,"Lynch",Archives!$Y$2:$Y$1048576,"Zimmer",Archives!$AB$2:$AB$1048576,"T")+COUNTIFS(Archives!$S$2:$S$1048576,"Doubles",Archives!$V$2:$V$1048576,"Zimmer",Archives!$Y$2:$Y$1048576,"Lynch",Archives!$AB$2:$AB$1048576,"T") -> 0 | M21: =IF(N21=0,0,(J21+0.5*L21)/N21) -> 1 | N21: =J21+K21+L21 -> 2
B22: Jackson | C22: =COUNTIFS(Archives!$S$2:$S$1048576,"Singles",Archives!$V$2:$V$1048576,$B22,Archives!$AB$2:$AB$1048576,"W") -> 5 | D22: =COUNTIFS(Archives!$S$2:$S$1048576,"Singles",Archives!$V$2:$V$1048576,$B22,Archives!$AB$2:$AB$1048576,"L") -> 6 | E22: =COUNTIFS(Archives!$S$2:$S$1048576,"Singles",Archives!$V$2:$V$1048576,$B22,Archives!$AB$2:$AB$1048576,"T") -> 1 | F22: =IF(G22=0,0,(C22+0.5*E22)/G22) -> 0.45833333 | G22: =C22+D22+E22 -> 12 | I22: Mangold / Perkins | J22: =COUNTIFS(Archives!$S$2:$S$1048576,"Doubles",Archives!$V$2:$V$1048576,"Mangold",Archives!$Y$2:$Y$1048576,"Perkins",Archives!$AB$2:$AB$1048576,"W")+COUNTIFS(Archives!$S$2:$S$1048576,"Doubles",Archives!$V$2:$V$1048576,"Perkins",Archives!$Y$2:$Y$1048576,"Mangold",Archives!$AB$2:$AB$1048576,"W") -> 2 | K22: =COUNTIFS(Archives!$S$2:$S$1048576,"Doubles",Archives!$V$2:$V$1048576,"Mangold",Archives!$Y$2:$Y$1048576,"Perkins",Archives!$AB$2:$AB$1048576,"L")+COUNTIFS(Archives!$S$2:$S$1048576,"Doubles",Archives!$V$2:$V$1048576,"Perkins",Archives!$Y$2:$Y$1048576,"Mangold",Archives!$AB$2:$AB$1048576,"L") -> 0 | L22: =COUNTIFS(Archives!$S$2:$S$1048576,"Doubles",Archives!$V$2:$V$1048576,"Mangold",Archives!$Y$2:$Y$1048576,"Perkins",Archives!$AB$2:$AB$1048576,"T")+COUNTIFS(Archives!$S$2:$S$1048576,"Doubles",Archives!$V$2:$V$1048576,"Perkins",Archives!$Y$2:$Y$1048576,"Mangold",Archives!$AB$2:$AB$1048576,"T") -> 0 | M22: =IF(N22=0,0,(J22+0.5*L22)/N22) -> 1 | N22: =J22+K22+L22 -> 2
B23: Flanders | C23: =COUNTIFS(Archives!$S$2:$S$1048576,"Singles",Archives!$V$2:$V$1048576,$B23,Archives!$AB$2:$AB$1048576,"W") -> 4 | D23: =COUNTIFS(Archives!$S$2:$S$1048576,"Singles",Archives!$V$2:$V$1048576,$B23,Archives!$AB$2:$AB$1048576,"L") -> 6 | E23: =COUNTIFS(Archives!$S$2:$S$1048576,"Singles",Archives!$V$2:$V$1048576,$B23,Archives!$AB$2:$AB$1048576,"T") -> 2 | F23: =IF(G23=0,0,(C23+0.5*E23)/G23) -> 0.41666667 | G23: =C23+D23+E23 -> 12 | I23: McInerney / Perkins | J23: =COUNTIFS(Archives!$S$2:$S$1048576,"Doubles",Archives!$V$2:$V$1048576,"McInerney",Archives!$Y$2:$Y$1048576,"Perkins",Archives!$AB$2:$AB$1048576,"W")+COUNTIFS(Archives!$S$2:$S$1048576,"Doubles",Archives!$V$2:$V$1048576,"Perkins",Archives!$Y$2:$Y$1048576,"McInerney",Archives!$AB$2:$AB$1048576,"W") -> 2 | K23: =COUNTIFS(Archives!$S$2:$S$1048576,"Doubles",Archives!$V$2:$V$1048576,"McInerney",Archives!$Y$2:$Y$1048576,"Perkins",Archives!$AB$2:$AB$1048576,"L")+COUNTIFS(Archives!$S$2:$S$1048576,"Doubles",Archives!$V$2:$V$1048576,"Perkins",Archives!$Y$2:$Y$1048576,"McInerney",Archives!$AB$2:$AB$1048576,"L") -> 0 | L23: =COUNTIFS(Archives!$S$2:$S$1048576,"Doubles",Archives!$V$2:$V$1048576,"McInerney",Archives!$Y$2:$Y$1048576,"Perkins",Archives!$AB$2:$AB$1048576,"T")+COUNTIFS(Archives!$S$2:$S$1048576,"Doubles",Archives!$V$2:$V$1048576,"Perkins",Archives!$Y$2:$Y$1048576,"McInerney",Archives!$AB$2:$AB$1048576,"T") -> 0 | M23: =IF(N23=0,0,(J23+0.5*L23)/N23) -> 1 | N23: =J23+K23+L23 -> 2
B24: Lynch | C24: =COUNTIFS(Archives!$S$2:$S$1048576,"Singles",Archives!$V$2:$V$1048576,$B24,Archives!$AB$2:$AB$1048576,"W") -> 4 | D24: =COUNTIFS(Archives!$S$2:$S$1048576,"Singles",Archives!$V$2:$V$1048576,$B24,Archives!$AB$2:$AB$1048576,"L") -> 7 | E24: =COUNTIFS(Archives!$S$2:$S$1048576,"Singles",Archives!$V$2:$V$1048576,$B24,Archives!$AB$2:$AB$1048576,"T") -> 1 | F24: =IF(G24=0,0,(C24+0.5*E24)/G24) -> 0.375 | G24: =C24+D24+E24 -> 12 | I24: Cole / Connolly | J24: =COUNTIFS(Archives!$S$2:$S$1048576,"Doubles",Archives!$V$2:$V$1048576,"Cole",Archives!$Y$2:$Y$1048576,"Connolly",Archives!$AB$2:$AB$1048576,"W")+COUNTIFS(Archives!$S$2:$S$1048576,"Doubles",Archives!$V$2:$V$1048576,"Connolly",Archives!$Y$2:$Y$1048576,"Cole",Archives!$AB$2:$AB$1048576,"W") -> 1 | K24: =COUNTIFS(Archives!$S$2:$S$1048576,"Doubles",Archives!$V$2:$V$1048576,"Cole",Archives!$Y$2:$Y$1048576,"Connolly",Archives!$AB$2:$AB$1048576,"L")+COUNTIFS(Archives!$S$2:$S$1048576,"Doubles",Archives!$V$2:$V$1048576,"Connolly",Archives!$Y$2:$Y$1048576,"Cole",Archives!$AB$2:$AB$1048576,"L") -> 0 | L24: =COUNTIFS(Archives!$S$2:$S$1048576,"Doubles",Archives!$V$2:$V$1048576,"Cole",Archives!$Y$2:$Y$1048576,"Connolly",Archives!$AB$2:$AB$1048576,"T")+COUNTIFS(Archives!$S$2:$S$1048576,"Doubles",Archives!$V$2:$V$1048576,"Connolly",Archives!$Y$2:$Y$1048576,"Cole",Archives!$AB$2:$AB$1048576,"T") -> 0 | M24: =IF(N24=0,0,(J24+0.5*L24)/N24) -> 1 | N24: =J24+K24+L24 -> 1
B25: Delaney | C25: =COUNTIFS(Archives!$S$2:$S$1048576,"Singles",Archives!$V$2:$V$1048576,$B25,Archives!$AB$2:$AB$1048576,"W") -> 2 | D25: =COUNTIFS(Archives!$S$2:$S$1048576,"Singles",Archives!$V$2:$V$1048576,$B25,Archives!$AB$2:$AB$1048576,"L") -> 4 | E25: =COUNTIFS(Archives!$S$2:$S$1048576,"Singles",Archives!$V$2:$V$1048576,$B25,Archives!$AB$2:$AB$1048576,"T") -> 0 | F25: =IF(G25=0,0,(C25+0.5*E25)/G25) -> 0.33333333 | G25: =C25+D25+E25 -> 6 | I25: Connors / Delneky | J25: =COUNTIFS(Archives!$S$2:$S$1048576,"Doubles",Archives!$V$2:$V$1048576,"Connors",Archives!$Y$2:$Y$1048576,"Delneky",Archives!$AB$2:$AB$1048576,"W")+COUNTIFS(Archives!$S$2:$S$1048576,"Doubles",Archives!$V$2:$V$1048576,"Delneky",Archives!$Y$2:$Y$1048576,"Connors",Archives!$AB$2:$AB$1048576,"W") -> 1 | K25: =COUNTIFS(Archives!$S$2:$S$1048576,"Doubles",Archives!$V$2:$V$1048576,"Connors",Archives!$Y$2:$Y$1048576,"Delneky",Archives!$AB$2:$AB$1048576,"L")+COUNTIFS(Archives!$S$2:$S$1048576,"Doubles",Archives!$V$2:$V$1048576,"Delneky",Archives!$Y$2:$Y$1048576,"Connors",Archives!$AB$2:$AB$1048576,"L") -> 0 | L25: =COUNTIFS(Archives!$S$2:$S$1048576,"Doubles",Archives!$V$2:$V$1048576,"Connors",Archives!$Y$2:$Y$1048576,"Delneky",Archives!$AB$2:$AB$1048576,"T")+COUNTIFS(Archives!$S$2:$S$1048576,"Doubles",Archives!$V$2:$V$1048576,"Delneky",Archives!$Y$2:$Y$1048576,"Connors",Archives!$AB$2:$AB$1048576,"T") -> 0 | M25: =IF(N25=0,0,(J25+0.5*L25)/N25) -> 1 | N25: =J25+K25+L25 -> 1
